Workbook
Name SelectedSmells: 'EA Smell Catalogue'!$C$58:$C$67
Name SmellCatalogue: 'EA Smell Catalogue'!$B$12:$E$18

Sheet Cover
B2: EA Smell Prioritization Tool
B4: AHP-Based Decision Support | Enterprise Architecture
B7: Project | C7: EA Smell Prioritisation Toolkit (AHP-Based Decision Support) | D7: v1.0
B8: Owner: | C8: Tolkounai K. | D8: 46252
B11: PURPOSE
B13: This tool applies the Analytic Hierarchy Process (AHP) to prioritize Enterprise Architecture (EA) smell instances identified during architectural reviews. It provides structured, multi-criteria evaluation with full consistency checking and scenario-based sensitivity analysis.
B16: HOW TO USE
B17: Step 1 | C17: 1.0 Case Context | D17: Define the decision context | E17: Read-Only
B18: Step 2 | C18: 1.1 AHP Hierarchy | D18: Review the AHP decision structure | E18: Read-Only
B19: Step 3 | C19: 1.2 Criteria Weights | D19: Set criteria importance | E19: User Input Required
B20: Step 4 | C20: 1.3 Intensity Priorities | D20: Set rating-level priorities | E20: Optional / Advanced Input
B21: Step 5 | C21: 1.4 EA Smell Scoring | D21: Rate EA smells against criteria | E21: User Input Required
B22: Step 6 | C22: 1.5 Results – EA Smell Dashboard | D22: Review prioritisation results | E22: Read-Only
B24: SHEET OVERVIEW
B25: Sheet | C25: Description | E25: Access
C26: 1.6 IP Calculations | D26: Review intensity priority calculations | E26: Optional / Read-Only
C27: 1.7 AHP Calculations | D27: Review criteria-weight calculations | E27: Optional / Read-Only
C28: EA Smell Catalogue | D28: Review and select EA smells | E28: Reference / Input
C29: AHP Saaty Reference | D29: Review the Saaty judgment scale | E29: Reference

Sheet 1.0 Case Context
D2: Case Context — Architecture Evidence
D5: ARCHIMATE MODEL
D6: #VALUE!
C9: SMELL EVIDENCE — Observations from the Architecture Model
C10: ID | D10: EA Smell | E10: Systems Involved | F10: Architectural Situation | G10: Observable Impact
C11: S1 | D11: Shared Persistency | E11: Salesforce CRM, SAP S/4HANA ERP, Power BI | F11: A shared central database is accessed by CRM, ERP, and Power BI, containing customer, order, invoice, and payment data. | G11: Changes to shared data structures require coordinated updates across multiple systems, introducing risks of data inconsistency and reducing system independence.
C12: S2 | D12: Feature Envy | E12: Salesforce CRM, SAP S/4HANA ERP | F12: The Customer Risk Assessment function in Salesforce CRM repeatedly accesses externally managed customer and financial data. | G12: Business logic becomes distributed across systems, increasing dependency on external data access and making changes harder to localize.
C13: S3 | D13: Cyclic Dependency | E13: Salesforce CRM, SAP S/4HANA ERP | F13: Salesforce CRM sends customer and order data to SAP S/4HANA ERP, while ERP returns invoice and payment status data to CRM, forming a bidirectional dependency. | G13: Independent modification, testing, or deployment of either system becomes difficult, as each system depends on the other’s outputs.
C14: S4 | D14: Stovepipe System | E14: Salesforce CRM, SAP S/4HANA ERP, Power BI | F14: Salesforce CRM, SAP S/4HANA ERP, and Power BI are integrated through system-specific data exchanges without a shared service abstraction layer. | G14: Integration logic is duplicated across system connections, reducing reusability and leading to brittle, hard-to-evolve integrations.
C15: S5 | D15: Vendor Lock-In | E15: SAP S/4HANA ERP, SAP Business Technology Platform | F15: Core enterprise processes and integration flows are implemented within the SAP ecosystem, including SAP S/4HANA ERP and SAP Business Technology Platform. | G15: Integration logic relies on SAP-specific technologies and platform services, increasing the effort required to migrate to alternative platforms or integration solutions.

Sheet 1.1 AHP Hierarchy
B2: AHP Hierarchy

Sheet 1.2 Weights
B2: Step 1 — Determine Criteria Importance (AHP Pairwise Comparisons)
B4: Select the pairwise judgment that best represents the relative importance between Criterion A and Criterion B. The AHP score is calculated automatically and should not be modified.
B6: Q# | C6: Question | D6: Criterion A | F6: Criterion B | G6: Pairwise Judgment | H6: AHP Score (calculated)
B8: SECTION 1 — Main Criteria
B9: Q1 | C9: With respect to prioritizing EA smell instances, which criterion is more important? | D9: Remediation Effort Remediation Effort (cost / effort to fix) | E9: vs | F9: Impact (architectural & operational impact) | G9: Equal importance (1) | H9: =IFERROR(_xlfn.XLOOKUP($G9,'AHP Saaty Reference'!$H$8:$H$24,'AHP Saaty Reference'!$I$8:$I$24),"") -> 1
B11: SECTION 2 — Remediation Effort Subcriteria
B12: Q2 | C12: With respect to remediation effort, which criterion is more important? | D12: Scope (number of affected elements) | E12: vs | F12: Restructuring Complexity (structural change effort) | G12: Equal importance (1) | H12: =IFERROR(_xlfn.XLOOKUP($G12,'AHP Saaty Reference'!$H$8:$H$24,'AHP Saaty Reference'!$I$8:$I$24),"") -> 1
B14: SECTION 3 — Impact Subcriteria
B15: Q5 | C15: With respect to impact, which criterion is more important? | D15: Evolution Constraint (architectural adaptability) | E15: vs | F15: Governance & Coordination Overhead (organizational complexity of change) | G15: Equal importance (1) | H15: =IFERROR(_xlfn.XLOOKUP($G15,'AHP Saaty Reference'!$H$8:$H$24,'AHP Saaty Reference'!$I$8:$I$24),"") -> 1
B16: Q6 | C16: With respect to impact, which criterion is more important? | D16: Evolution Constraint (architectural adaptability) | E16: vs | F16: Operational Reliability Impact (service disruption severity) | G16: Equal importance (1) | H16: =IFERROR(_xlfn.XLOOKUP($G16,'AHP Saaty Reference'!$H$8:$H$24,'AHP Saaty Reference'!$I$8:$I$24),"") -> 1
B17: Q7 | C17: With respect to impact, which criterion is more important? | D17: Governance & Coordination Overhead (organizational complexity of change) | E17: vs | F17: Operational Reliability Impact (service disruption severity) | G17: Equal importance (1) | H17: =IFERROR(_xlfn.XLOOKUP($G17,'AHP Saaty Reference'!$H$8:$H$24,'AHP Saaty Reference'!$I$8:$I$24),"") -> 1
B19: Step 2 — Check Consistency of Judgments
C21: Consistency Ratio (CR) – The consistency ratio evaluates the consistency of your pairwise judgments. A CR ≤ 0.10 indicates acceptable consistency. If the CR exceeds 0.10, revise your pairwise judgments. | F21: =IFERROR( IF('1.7 AHP Calculations'!C52<=0.1, "Acceptable"&CHAR(10)& "CR = "&TEXT('1.7 AHP Calculations'!C52,"0.000"), "Not Acceptable – Revise judgments"&CHAR(10)& "CR = "&TEXT('1.7 AHP Calculations'!C52,"0.000")), "Awaiting judgment inputs") -> Acceptable CR = 0.000
B23: Step 3 — Review Derived Criteria Weights
C25: Criterion | D25: Subcriterion | F25: Local Weight | G25: Global Weight
C26: Remediation Effort | F26: ='1.7 AHP Calculations'!$F$18 -> 0.5 | G26: ='1.2 Weights'!$F26 -> 0.5
D27: Scope | F27: ='1.7 AHP Calculations'!$D$60 -> 0.5 | G27: =F27*$F$26 -> 0.25
D28: Restructuring Complexity | F28: ='1.7 AHP Calculations'!$D$61 -> 0.5 | G28: =F28*$F$26 -> 0.25
C29: Impact | F29: ='1.7 AHP Calculations'!$F$19 -> 0.5 | G29: ='1.2 Weights'!$F29 -> 0.5
D30: Evolution Constraint | F30: ='1.7 AHP Calculations'!$D$62 -> 0.33333333 | G30: =F30*$F$29 -> 0.16666667
D31: Governance & Coordination Overhead | F31: ='1.7 AHP Calculations'!$D$63 -> 0.33333333 | G31: =F31*$F$29 -> 0.16666667
D32: Operational Reliability Impact | F32: ='1.7 AHP Calculations'!$D$64 -> 0.33333333 | G32: =F32*$F$29 -> 0.16666667

Sheet 1.3 IP Pairwise
B2: Intensity Priorities (AHP Pairwise Comparisons) - Advanced Input / Optional
B4: Pairwise judgments have been predefined based on the Level 1–5 progression. AHP scores are calculated automatically. Judgments may be adjusted to reflect a different decision context.
B8: Pair | C8: Criterion A | E8: Criterion B | F8: Pairwise Judgment | G8: AHP Score (calculated) | H8: Decision Rationale (Optional) | J8: ► (click +) | K8: Level | L8: Description | M8: Boundary Defintion | N8: Illustrative Example | S8: ► Column Helper
B10: Scope | J10: Scope ► | K10: How many architectural elements must change to eliminate this EA smell instance?
B12: Pair | C12: Criterion A | E12: Criterion B | F12: Pairwise Judgment | G12: AHP Score (calculated) | H12: Decision Rationale (Optional) | K12: Level | L12: Description | M12: Boundary Defintion | N12: Illustrative Example | T12: Pair | U12: A ID | V12: B ID
B13: 1 | C13: =_xlfn.XLOOKUP(_xlfn.XLOOKUP($B13,$T$13:$T$22,$U$13:$U$22),$K$13:$K$17,$K$13:$K$17)&" – "&_xlfn.XLOOKUP(_xlfn.XLOOKUP($B13,$T$13:$T$22,$U$13:$U$22),$K$13:$K$17,$L$13:$L$17) -> L1 – Single Element | D13: vs | E13: =_xlfn.XLOOKUP(_xlfn.XLOOKUP($B13,$T$13:$T$22,$V$13:$V$22),$K$13:$K$17,$K$13:$K$17)&" – "&_xlfn.XLOOKUP(_xlfn.XLOOKUP($B13,$T$13:$T$22,$V$13:$V$22),$K$13:$K$17,$L$13:$L$17) -> L2 – Single System | F13: Criterion A – Intermediate value between Equal and Moderate importance (2) | G13: =IFERROR(_xlfn.XLOOKUP($F13,'AHP Saaty Reference'!$H$8:$H$24,'AHP Saaty Reference'!$I$8:$I$24),"") -> 2 | H13: Scope increases, but remediation remains within a single system boundary. | K13: L1 | L13: Single Element | M13: Changes affect one architectural element only (e.g., component, service, or interface). | N13: In the CRM system, the Customer Service interface is incorrectly defined. Fixing the issue requires modifying only the Customer Service interface. | T13: 1 | U13: L1 | V13: L2
B14: 2 | C14: =_xlfn.XLOOKUP(_xlfn.XLOOKUP($B14,$T$13:$T$22,$U$13:$U$22),$K$13:$K$17,$K$13:$K$17)&" – "&_xlfn.XLOOKUP(_xlfn.XLOOKUP($B14,$T$13:$T$22,$U$13:$U$22),$K$13:$K$17,$L$13:$L$17) -> L1 – Single Element | D14: vs | E14: =_xlfn.XLOOKUP(_xlfn.XLOOKUP($B14,$T$13:$T$22,$V$13:$V$22),$K$13:$K$17,$K$13:$K$17)&" – "&_xlfn.XLOOKUP(_xlfn.XLOOKUP($B14,$T$13:$T$22,$V$13:$V$22),$K$13:$K$17,$L$13:$L$17) -> L3 – Multiple Systems (Limited Scope) | F14: Criterion A – Moderate importance (3) | G14: =IFERROR(_xlfn.XLOOKUP($F14,'AHP Saaty Reference'!$H$8:$H$24,'AHP Saaty Reference'!$I$8:$I$24),"") -> 3 | H14: The remediation expands from one element to multiple systems, creating a clear cross-system increase in scope. | K14: L2 | L14: Single System | M14: Changes affect multiple architectural elements within the same application/system boundary, but no other systems are involved. | N14: Within the ERP system, the Order Service is tightly coupled to the Inventory Service. Resolving the issue requires modifying both services within the ERP system. | T14: 2 | U14: L1 | V14: L3
B15: 3 | C15: =_xlfn.XLOOKUP(_xlfn.XLOOKUP($B15,$T$13:$T$22,$U$13:$U$22),$K$13:$K$17,$K$13:$K$17)&" – "&_xlfn.XLOOKUP(_xlfn.XLOOKUP($B15,$T$13:$T$22,$U$13:$U$22),$K$13:$K$17,$L$13:$L$17) -> L1 – Single Element | D15: vs | E15: =_xlfn.XLOOKUP(_xlfn.XLOOKUP($B15,$T$13:$T$22,$V$13:$V$22),$K$13:$K$17,$K$13:$K$17)&" – "&_xlfn.XLOOKUP(_xlfn.XLOOKUP($B15,$T$13:$T$22,$V$13:$V$22),$K$13:$K$17,$L$13:$L$17) -> L4 – Multiple Systems (Broad Scope) | F15: Criterion A – Strong importance (5) | G15: =IFERROR(_xlfn.XLOOKUP($F15,'AHP Saaty Reference'!$H$8:$H$24,'AHP Saaty Reference'!$I$8:$I$24),"") -> 5 | H15: The remediation spans multiple systems and multiple architectural element types, representing a strong increase over a single-element change. | K15: L3 | L15: Multiple Systems (Limited Scope) | M15: Changes affect multiple applications or systems, requiring modifications to a specific type of architectural element within each system (e.g., interfaces or services). | N15: The CRM and ERP systems exchange customer data through a poorly designed integration interface. Resolving the issue requires modifying the integration interfaces in both CRM and ERP systems. | T15: 3 | U15: L1 | V15: L4
B16: 4 | C16: =_xlfn.XLOOKUP(_xlfn.XLOOKUP($B16,$T$13:$T$22,$U$13:$U$22),$K$13:$K$17,$K$13:$K$17)&" – "&_xlfn.XLOOKUP(_xlfn.XLOOKUP($B16,$T$13:$T$22,$U$13:$U$22),$K$13:$K$17,$L$13:$L$17) -> L1 – Single Element | D16: vs | E16: =_xlfn.XLOOKUP(_xlfn.XLOOKUP($B16,$T$13:$T$22,$V$13:$V$22),$K$13:$K$17,$K$13:$K$17)&" – "&_xlfn.XLOOKUP(_xlfn.XLOOKUP($B16,$T$13:$T$22,$V$13:$V$22),$K$13:$K$17,$L$13:$L$17) -> L5 – Enterprise-Wide Scope | F16: Criterion A – Very strong importance (7) | G16: =IFERROR(_xlfn.XLOOKUP($F16,'AHP Saaty Reference'!$H$8:$H$24,'AHP Saaty Reference'!$I$8:$I$24),"") -> 7 | H16: Enterprise-wide shared architectural assets create a very large increase in scope compared with a single-element change. | K16: L4 | L16: Multiple Systems (Broad Scope) | M16: Changes affect multiple applications or systems and require modifications to multiple types of architectural elements within each system (e.g., services, interfaces, and data structures). | N16: The CRM and ERP systems are tightly coupled through multiple interacting components and data exchanges. Resolving the issue requires modifying components, interfaces, and data structures in both systems. | T16: 4 | U16: L1 | V16: L5
B17: 5 | C17: =_xlfn.XLOOKUP(_xlfn.XLOOKUP($B17,$T$13:$T$22,$U$13:$U$22),$K$13:$K$17,$K$13:$K$17)&" – "&_xlfn.XLOOKUP(_xlfn.XLOOKUP($B17,$T$13:$T$22,$U$13:$U$22),$K$13:$K$17,$L$13:$L$17) -> L2 – Single System | D17: vs | E17: =_xlfn.XLOOKUP(_xlfn.XLOOKUP($B17,$T$13:$T$22,$V$13:$V$22),$K$13:$K$17,$K$13:$K$17)&" – "&_xlfn.XLOOKUP(_xlfn.XLOOKUP($B17,$T$13:$T$22,$V$13:$V$22),$K$13:$K$17,$L$13:$L$17) -> L3 – Multiple Systems (Limited Scope) | F17: Criterion A – Moderate importance (3) | G17: =IFERROR(_xlfn.XLOOKUP($F17,'AHP Saaty Reference'!$H$8:$H$24,'AHP Saaty Reference'!$I$8:$I$24),"") -> 3 | H17: The scope expands from one system to multiple systems, introducing cross-system coordination. | K17: L5 | L17: Enterprise-Wide Scope | M17: Changes affect multiple systems or applications and require modifications to shared or common architectural elements used across systems (e.g., shared data models, integration platforms, or core services). | N17: Customer information is stored in a shared data model used by CRM, ERP, and Marketing systems. Resolving the issue requires modifying the shared data model, affecting all dependent systems. | T17: 5 | U17: L2 | V17: L3
B18: 6 | C18: =_xlfn.XLOOKUP(_xlfn.XLOOKUP($B18,$T$13:$T$22,$U$13:$U$22),$K$13:$K$17,$K$13:$K$17)&" – "&_xlfn.XLOOKUP(_xlfn.XLOOKUP($B18,$T$13:$T$22,$U$13:$U$22),$K$13:$K$17,$L$13:$L$17) -> L2 – Single System | D18: vs | E18: =_xlfn.XLOOKUP(_xlfn.XLOOKUP($B18,$T$13:$T$22,$V$13:$V$22),$K$13:$K$17,$K$13:$K$17)&" – "&_xlfn.XLOOKUP(_xlfn.XLOOKUP($B18,$T$13:$T$22,$V$13:$V$22),$K$13:$K$17,$L$13:$L$17) -> L4 – Multiple Systems (Broad Scope) | F18: Criterion A – Strong importance (5) | G18: =IFERROR(_xlfn.XLOOKUP($F18,'AHP Saaty Reference'!$H$8:$H$24,'AHP Saaty Reference'!$I$8:$I$24),"") -> 5 | H18: L4 expands beyond one system and affects multiple architectural element types across systems. | T18: 6 | U18: L2 | V18: L4
B19: 7 | C19: =_xlfn.XLOOKUP(_xlfn.XLOOKUP($B19,$T$13:$T$22,$U$13:$U$22),$K$13:$K$17,$K$13:$K$17)&" – "&_xlfn.XLOOKUP(_xlfn.XLOOKUP($B19,$T$13:$T$22,$U$13:$U$22),$K$13:$K$17,$L$13:$L$17) -> L2 – Single System | D19: vs | E19: =_xlfn.XLOOKUP(_xlfn.XLOOKUP($B19,$T$13:$T$22,$V$13:$V$22),$K$13:$K$17,$K$13:$K$17)&" – "&_xlfn.XLOOKUP(_xlfn.XLOOKUP($B19,$T$13:$T$22,$V$13:$V$22),$K$13:$K$17,$L$13:$L$17) -> L5 – Enterprise-Wide Scope | F19: Criterion A – Very strong importance (7) | G19: =IFERROR(_xlfn.XLOOKUP($F19,'AHP Saaty Reference'!$H$8:$H$24,'AHP Saaty Reference'!$I$8:$I$24),"") -> 7 | H19: The scope moves from a single-system change to shared enterprise architecture affecting dependent systems across the organization. | T19: 7 | U19: L2 | V19: L5
B20: 8 | C20: =_xlfn.XLOOKUP(_xlfn.XLOOKUP($B20,$T$13:$T$22,$U$13:$U$22),$K$13:$K$17,$K$13:$K$17)&" – "&_xlfn.XLOOKUP(_xlfn.XLOOKUP($B20,$T$13:$T$22,$U$13:$U$22),$K$13:$K$17,$L$13:$L$17) -> L3 – Multiple Systems (Limited Scope) | D20: vs | E20: =_xlfn.XLOOKUP(_xlfn.XLOOKUP($B20,$T$13:$T$22,$V$13:$V$22),$K$13:$K$17,$K$13:$K$17)&" – "&_xlfn.XLOOKUP(_xlfn.XLOOKUP($B20,$T$13:$T$22,$V$13:$V$22),$K$13:$K$17,$L$13:$L$17) -> L4 – Multiple Systems (Broad Scope) | F20: Criterion A – Intermediate value between Equal and Moderate importance (2) | G20: =IFERROR(_xlfn.XLOOKUP($F20,'AHP Saaty Reference'!$H$8:$H$24,'AHP Saaty Reference'!$I$8:$I$24),"") -> 2 | H20: Both affect multiple systems, but L4 requires modifications to a broader range of architectural element types. | T20: 8 | U20: L3 | V20: L4
B21: 9 | C21: =_xlfn.XLOOKUP(_xlfn.XLOOKUP($B21,$T$13:$T$22,$U$13:$U$22),$K$13:$K$17,$K$13:$K$17)&" – "&_xlfn.XLOOKUP(_xlfn.XLOOKUP($B21,$T$13:$T$22,$U$13:$U$22),$K$13:$K$17,$L$13:$L$17) -> L3 – Multiple Systems (Limited Scope) | D21: vs | E21: =_xlfn.XLOOKUP(_xlfn.XLOOKUP($B21,$T$13:$T$22,$V$13:$V$22),$K$13:$K$17,$K$13:$K$17)&" – "&_xlfn.XLOOKUP(_xlfn.XLOOKUP($B21,$T$13:$T$22,$V$13:$V$22),$K$13:$K$17,$L$13:$L$17) -> L5 – Enterprise-Wide Scope | F21: Criterion A – Strong importance (5) | G21: =IFERROR(_xlfn.XLOOKUP($F21,'AHP Saaty Reference'!$H$8:$H$24,'AHP Saaty Reference'!$I$8:$I$24),"") -> 5 | H21: L5 affects shared enterprise assets and their dependent systems, substantially exceeding limited multi-system scope. | T21: 9 | U21: L3 | V21: L5
B22: 10 | C22: =_xlfn.XLOOKUP(_xlfn.XLOOKUP($B22,$T$13:$T$22,$U$13:$U$22),$K$13:$K$17,$K$13:$K$17)&" – "&_xlfn.XLOOKUP(_xlfn.XLOOKUP($B22,$T$13:$T$22,$U$13:$U$22),$K$13:$K$17,$L$13:$L$17) -> L4 – Multiple Systems (Broad Scope) | D22: vs | E22: =_xlfn.XLOOKUP(_xlfn.XLOOKUP($B22,$T$13:$T$22,$V$13:$V$22),$K$13:$K$17,$K$13:$K$17)&" – "&_xlfn.XLOOKUP(_xlfn.XLOOKUP($B22,$T$13:$T$22,$V$13:$V$22),$K$13:$K$17,$L$13:$L$17) -> L5 – Enterprise-Wide Scope | F22: Criterion A – Strong importance (5) | G22: =IFERROR(_xlfn.XLOOKUP($F22,'AHP Saaty Reference'!$H$8:$H$24,'AHP Saaty Reference'!$I$8:$I$24),"") -> 5 | H22: L5 shifts the remediation from broad multi-system changes to shared enterprise architecture with wider dependency propagation. | T22: 10 | U22: L4 | V22: L5
B24: Consistency Ratio (CR) – The consistency ratio evaluates the consistency of your pairwise judgments. A CR ≤ 0.10 indicates acceptable consistency. If the CR exceeds 0.10, revise your pairwise judgments. | G24: =IF( '1.6 IP Calculations'!$C$52="", "Awaiting judgment inputs", IF( '1.6 IP Calculations'!$C$52<=0.1, "Acceptable"&CHAR(10)&"CR = "&TEXT('1.6 IP Calculations'!$C$52,"0.000"), "Not Acceptable – Revise judgments"&CHAR(10)&"CR = "&TEXT('1.6 IP Calculations'!$C$52,"0.000") ) ) -> Acceptable CR = 0.059
B26: Calculated Results Derived Intensity Priorities (Priority Vector)
B28: The priority vector is derived from the pairwise comparisons using the Analytic Hierarchy Process (AHP). Idealized priorities are obtained by dividing each priority by the largest priority, resulting in a maximum value of 1.000. These idealized priorities are automatically used during EA smell scoring.
B31: Level | C31: Idealized Priority
B32: L1 | C32: =IF(OR('1.6 IP Calculations'!$D26="",ISBLANK('1.6 IP Calculations'!$D26)),"Awaiting input",'1.6 IP Calculations'!$D26) -> 1
B33: L2 | C33: =IF(OR('1.6 IP Calculations'!$D27="",ISBLANK('1.6 IP Calculations'!$D27)),"Awaiting input",'1.6 IP Calculations'!$D27) -> 0.76050351
B34: L3 | C34: =IF(OR('1.6 IP Calculations'!$D28="",ISBLANK('1.6 IP Calculations'!$D28)),"Awaiting input",'1.6 IP Calculations'!$D28) -> 0.34263524
B35: L4 | C35: =IF(OR('1.6 IP Calculations'!$D29="",ISBLANK('1.6 IP Calculations'!$D29)),"Awaiting input",'1.6 IP Calculations'!$D29) -> 0.22309669
B36: L5 | C36: =IF(OR('1.6 IP Calculations'!$D30="",ISBLANK('1.6 IP Calculations'!$D30)),"Awaiting input",'1.6 IP Calculations'!$D30) -> 0.085534816
B39: Restructuring Complexity | J39: Restructuring Complexity ► | K39: How structurally difficult is it to remove this EA smell instance from the architecture?
B41: Pair | C41: Criterion A | E41: Criterion B | F41: Pairwise Judgment | G41: AHP Score (calculated) | H41: Decision Rationale (Optional) | K41: Level | L41: Description | M41: Boundary Defintion | N41: Representative Refactoring Types (derived from Liss et al.)
B42: 1 | C42: =_xlfn.XLOOKUP(_xlfn.XLOOKUP($B42,$T$13:$T$22,$U$13:$U$22),$K$42:$K$46,$K$42:$K$46)&" – "&_xlfn.XLOOKUP(_xlfn.XLOOKUP($B42,$T$13:$T$22,$U$13:$U$22),$K$42:$K$46,$L$42:$L$46) -> L1 – Minor Architectural Adjustment | D42: vs | E42: =_xlfn.XLOOKUP(_xlfn.XLOOKUP($B42,$T$13:$T$22,$V$13:$V$22),$K$42:$K$46,$K$42:$K$46)&" – "&_xlfn.XLOOKUP(_xlfn.XLOOKUP($B42,$T$13:$T$22,$V$13:$V$22),$K$42:$K$46,$L$42:$L$46) -> L2 – Local Component Modification | F42: Criterion A – Intermediate value between Equal and Moderate importance (2) | G42: =IFERROR(_xlfn.XLOOKUP($F42,'AHP Saaty Reference'!$H$8:$H$24,'AHP Saaty Reference'!$I$8:$I$24),"") -> 2 | H42: The remediation expands from one element to multiple systems, creating a clear cross-system increase in scope. | K42: L1 | L42: Minor Architectural Adjustment | M42: Small changes to architectural elements that do not alter component responsibilities or the overall architectural structure. | N42: Rename Component
B43: 2 | C43: =_xlfn.XLOOKUP(_xlfn.XLOOKUP($B43,$T$13:$T$22,$U$13:$U$22),$K$42:$K$46,$K$42:$K$46)&" – "&_xlfn.XLOOKUP(_xlfn.XLOOKUP($B43,$T$13:$T$22,$U$13:$U$22),$K$42:$K$46,$L$42:$L$46) -> L1 – Minor Architectural Adjustment | D43: vs | E43: =_xlfn.XLOOKUP(_xlfn.XLOOKUP($B43,$T$13:$T$22,$V$13:$V$22),$K$42:$K$46,$K$42:$K$46)&" – "&_xlfn.XLOOKUP(_xlfn.XLOOKUP($B43,$T$13:$T$22,$V$13:$V$22),$K$42:$K$46,$L$42:$L$46) -> L3 – Component Restructuring (Single System) | F43: Criterion A – Moderate importance (3) | G43: =IFERROR(_xlfn.XLOOKUP($F43,'AHP Saaty Reference'!$H$8:$H$24,'AHP Saaty Reference'!$I$8:$I$24),"") -> 3 | H43: L3 reorganizes component responsibilities and interactions within a system, whereas L1 is limited to minor architectural adjustments. | K43: L2 | L43: Local Component Modification | M43: Changes affecting a single architectural component without altering how the architecture is organized or relationships between components. | N43: Remove Dead Component, Inline Service
B44: 3 | C44: =_xlfn.XLOOKUP(_xlfn.XLOOKUP($B44,$T$13:$T$22,$U$13:$U$22),$K$42:$K$46,$K$42:$K$46)&" – "&_xlfn.XLOOKUP(_xlfn.XLOOKUP($B44,$T$13:$T$22,$U$13:$U$22),$K$42:$K$46,$L$42:$L$46) -> L1 – Minor Architectural Adjustment | D44: vs | E44: =_xlfn.XLOOKUP(_xlfn.XLOOKUP($B44,$T$13:$T$22,$V$13:$V$22),$K$42:$K$46,$K$42:$K$46)&" – "&_xlfn.XLOOKUP(_xlfn.XLOOKUP($B44,$T$13:$T$22,$V$13:$V$22),$K$42:$K$46,$L$42:$L$46) -> L4 – Architectural Reorganization | F44: Criterion A – Strong importance (5) | G44: =IFERROR(_xlfn.XLOOKUP($F44,'AHP Saaty Reference'!$H$8:$H$24,'AHP Saaty Reference'!$I$8:$I$24),"") -> 5 | H44: L4 reorganizes architectural relationships across system boundaries, whereas L1 involves only minor local architectural adjustments. | K44: L3 | L44: Component Restructuring (Single System) | M44: Refactoring that reorganizes responsibilities between architectural components within the same system, modifying component interactions while preserving the overall system structure. | N44: Break Up Component, Extract Component, Merge Components
B45: 4 | C45: =_xlfn.XLOOKUP(_xlfn.XLOOKUP($B45,$T$13:$T$22,$U$13:$U$22),$K$42:$K$46,$K$42:$K$46)&" – "&_xlfn.XLOOKUP(_xlfn.XLOOKUP($B45,$T$13:$T$22,$U$13:$U$22),$K$42:$K$46,$L$42:$L$46) -> L1 – Minor Architectural Adjustment | D45: vs | E45: =_xlfn.XLOOKUP(_xlfn.XLOOKUP($B45,$T$13:$T$22,$V$13:$V$22),$K$42:$K$46,$K$42:$K$46)&" – "&_xlfn.XLOOKUP(_xlfn.XLOOKUP($B45,$T$13:$T$22,$V$13:$V$22),$K$42:$K$46,$L$42:$L$46) -> L5 – Architectural Layer Restructuring | F45: Criterion A – Very strong importance (7) | G45: =IFERROR(_xlfn.XLOOKUP($F45,'AHP Saaty Reference'!$H$8:$H$24,'AHP Saaty Reference'!$I$8:$I$24),"") -> 7 | H45: L5 fundamentally restructures architectural layers and the overall architecture, whereas L1 is limited to minor architectural adjustments. | K45: L4 | L45: Architectural Reorganization | M45: Refactoring that reorganizes architectural relationships between systems, requiring changes to how components interact across system boundaries and altering integration structures. | N45: Move Component, Reorganization
B46: 5 | C46: =_xlfn.XLOOKUP(_xlfn.XLOOKUP($B46,$T$13:$T$22,$U$13:$U$22),$K$42:$K$46,$K$42:$K$46)&" – "&_xlfn.XLOOKUP(_xlfn.XLOOKUP($B46,$T$13:$T$22,$U$13:$U$22),$K$42:$K$46,$L$42:$L$46) -> L2 – Local Component Modification | D46: vs | E46: =_xlfn.XLOOKUP(_xlfn.XLOOKUP($B46,$T$13:$T$22,$V$13:$V$22),$K$42:$K$46,$K$42:$K$46)&" – "&_xlfn.XLOOKUP(_xlfn.XLOOKUP($B46,$T$13:$T$22,$V$13:$V$22),$K$42:$K$46,$L$42:$L$46) -> L3 – Component Restructuring (Single System) | F46: Criterion A – Intermediate value between Equal and Moderate importance (2) | G46: =IFERROR(_xlfn.XLOOKUP($F46,'AHP Saaty Reference'!$H$8:$H$24,'AHP Saaty Reference'!$I$8:$I$24),"") -> 2 | H46: L3 reorganizes responsibilities between architectural components, whereas L2 modifies only a single architectural component. | K46: L5 | L46: Architectural Layer Restructuring | M46: Refactoring that introduces, removes, or fundamentally restructures architectural layers or abstraction structures, significantly altering the overall architecture. | N46: Isolation Layer, Move Service to Different Layer
B47: 6 | C47: =_xlfn.XLOOKUP(_xlfn.XLOOKUP($B47,$T$13:$T$22,$U$13:$U$22),$K$42:$K$46,$K$42:$K$46)&" – "&_xlfn.XLOOKUP(_xlfn.XLOOKUP($B47,$T$13:$T$22,$U$13:$U$22),$K$42:$K$46,$L$42:$L$46) -> L2 – Local Component Modification | D47: vs | E47: =_xlfn.XLOOKUP(_xlfn.XLOOKUP($B47,$T$13:$T$22,$V$13:$V$22),$K$42:$K$46,$K$42:$K$46)&" – "&_xlfn.XLOOKUP(_xlfn.XLOOKUP($B47,$T$13:$T$22,$V$13:$V$22),$K$42:$K$46,$L$42:$L$46) -> L4 – Architectural Reorganization | F47: Criterion A – Strong importance (5) | G47: =IFERROR(_xlfn.XLOOKUP($F47,'AHP Saaty Reference'!$H$8:$H$24,'AHP Saaty Reference'!$I$8:$I$24),"") -> 5 | H47: L4 reorganizes cross-system architectural relationships and integration structures, whereas L2 modifies only a single architectural component.
B48: 7 | C48: =_xlfn.XLOOKUP(_xlfn.XLOOKUP($B48,$T$13:$T$22,$U$13:$U$22),$K$42:$K$46,$K$42:$K$46)&" – "&_xlfn.XLOOKUP(_xlfn.XLOOKUP($B48,$T$13:$T$22,$U$13:$U$22),$K$42:$K$46,$L$42:$L$46) -> L2 – Local Component Modification | D48: vs | E48: =_xlfn.XLOOKUP(_xlfn.XLOOKUP($B48,$T$13:$T$22,$V$13:$V$22),$K$42:$K$46,$K$42:$K$46)&" – "&_xlfn.XLOOKUP(_xlfn.XLOOKUP($B48,$T$13:$T$22,$V$13:$V$22),$K$42:$K$46,$L$42:$L$46) -> L5 – Architectural Layer Restructuring | F48: Criterion A – Very strong importance (7) | G48: =IFERROR(_xlfn.XLOOKUP($F48,'AHP Saaty Reference'!$H$8:$H$24,'AHP Saaty Reference'!$I$8:$I$24),"") -> 7 | H48: L5 fundamentally restructures architectural layers, whereas L2 modifies only a single architectural component.
B49: 8 | C49: =_xlfn.XLOOKUP(_xlfn.XLOOKUP($B49,$T$13:$T$22,$U$13:$U$22),$K$42:$K$46,$K$42:$K$46)&" – "&_xlfn.XLOOKUP(_xlfn.XLOOKUP($B49,$T$13:$T$22,$U$13:$U$22),$K$42:$K$46,$L$42:$L$46) -> L3 – Component Restructuring (Single System) | D49: vs | E49: =_xlfn.XLOOKUP(_xlfn.XLOOKUP($B49,$T$13:$T$22,$V$13:$V$22),$K$42:$K$46,$K$42:$K$46)&" – "&_xlfn.XLOOKUP(_xlfn.XLOOKUP($B49,$T$13:$T$22,$V$13:$V$22),$K$42:$K$46,$L$42:$L$46) -> L4 – Architectural Reorganization | F49: Criterion A – Strong importance (5) | G49: =IFERROR(_xlfn.XLOOKUP($F49,'AHP Saaty Reference'!$H$8:$H$24,'AHP Saaty Reference'!$I$8:$I$24),"") -> 5 | H49: L4 reorganizes cross-system interactions and integration structures, whereas L3 restructures components only within a single system.
B50: 9 | C50: =_xlfn.XLOOKUP(_xlfn.XLOOKUP($B50,$T$13:$T$22,$U$13:$U$22),$K$42:$K$46,$K$42:$K$46)&" – "&_xlfn.XLOOKUP(_xlfn.XLOOKUP($B50,$T$13:$T$22,$U$13:$U$22),$K$42:$K$46,$L$42:$L$46) -> L3 – Component Restructuring (Single System) | D50: vs | E50: =_xlfn.XLOOKUP(_xlfn.XLOOKUP($B50,$T$13:$T$22,$V$13:$V$22),$K$42:$K$46,$K$42:$K$46)&" – "&_xlfn.XLOOKUP(_xlfn.XLOOKUP($B50,$T$13:$T$22,$V$13:$V$22),$K$42:$K$46,$L$42:$L$46) -> L5 – Architectural Layer Restructuring | F50: Criterion A – Strong importance (5) | G50: =IFERROR(_xlfn.XLOOKUP($F50,'AHP Saaty Reference'!$H$8:$H$24,'AHP Saaty Reference'!$I$8:$I$24),"") -> 5 | H50: L5 fundamentally restructures architectural layers, whereas L3 restructures component responsibilities within a single system.
B51: 10 | C51: =_xlfn.XLOOKUP(_xlfn.XLOOKUP($B51,$T$13:$T$22,$U$13:$U$22),$K$42:$K$46,$K$42:$K$46)&" – "&_xlfn.XLOOKUP(_xlfn.XLOOKUP($B51,$T$13:$T$22,$U$13:$U$22),$K$42:$K$46,$L$42:$L$46) -> L4 – Architectural Reorganization | D51: vs | E51: =_xlfn.XLOOKUP(_xlfn.XLOOKUP($B51,$T$13:$T$22,$V$13:$V$22),$K$42:$K$46,$K$42:$K$46)&" – "&_xlfn.XLOOKUP(_xlfn.XLOOKUP($B51,$T$13:$T$22,$V$13:$V$22),$K$42:$K$46,$L$42:$L$46) -> L5 – Architectural Layer Restructuring | F51: Criterion A – Strong importance (5) | G51: =IFERROR(_xlfn.XLOOKUP($F51,'AHP Saaty Reference'!$H$8:$H$24,'AHP Saaty Reference'!$I$8:$I$24),"") -> 5 | H51: L5 fundamentally restructures the architectural layers, whereas L4 reorganizes relationships between systems while preserving the overall architectural structure.
B53: Consistency Ratio (CR) – The consistency ratio evaluates the consistency of your pairwise judgments. A CR ≤ 0.10 indicates acceptable consistency. If the CR exceeds 0.10, revise your pairwise judgments. | G53: =IF( '1.6 IP Calculations'!$M$52="", "Awaiting judgment inputs", IF( '1.6 IP Calculations'!$M$52<=0.1, "Acceptable"&CHAR(10)&"CR = "&TEXT('1.6 IP Calculations'!$M$52,"0.000"), "Not Acceptable – Revise judgments"&CHAR(10)&"CR = "&TEXT('1.6 IP Calculations'!$M$52,"0.000") ) ) -> Acceptable CR = 0.088
B55: Calculated Results Derived Intensity Priorities (Priority Vector)
B57: The priority vector is derived from the pairwise comparisons using the Analytic Hierarchy Process (AHP). Idealized priorities are obtained by dividing each priority by the largest priority, resulting in a maximum value of 1.000. These idealized priorities are automatically used during EA smell scoring.
B60: Level | C60: Idealized Priority
B61: L1 | C61: =IF(OR('1.6 IP Calculations'!$N26="",ISBLANK('1.6 IP Calculations'!$N26)),"Awaiting input",'1.6 IP Calculations'!$N26) -> 1
B62: L2 | C62: =IF(OR('1.6 IP Calculations'!$N27="",ISBLANK('1.6 IP Calculations'!$N27)),"Awaiting input",'1.6 IP Calculations'!$N27) -> 0.69078947
B63: L3 | C63: =IF(OR('1.6 IP Calculations'!$N28="",ISBLANK('1.6 IP Calculations'!$N28)),"Awaiting input",'1.6 IP Calculations'!$N28) -> 0.47573088
B64: L4 | C64: =IF(OR('1.6 IP Calculations'!$N29="",ISBLANK('1.6 IP Calculations'!$N29)),"Awaiting input",'1.6 IP Calculations'!$N29) -> 0.19626433
B65: L5 | C65: =IF(OR('1.6 IP Calculations'!$N30="",ISBLANK('1.6 IP Calculations'!$N30)),"Awaiting input",'1.6 IP Calculations'!$N30) -> 0.085643476
B68: Evolution Constraint | J68: Evolution Constraint ► | K68: To what extent does the EA smell instance limit the architecture’s ability to evolve or change?
B70: Pair | C70: Criterion A | E70: Criterion B | F70: Pairwise Judgment | G70: AHP Score (calculated) | H70: Decision Rationale (Optional) | K70: Level | L70: Description | M70: Boundary Defintion | N70: Illustrative Example
B71: 1 | C71: =_xlfn.XLOOKUP(_xlfn.XLOOKUP($B71,$T$13:$T$22,$U$13:$U$22),$K$71:$K$75,$K$71:$K$75)&" – "&_xlfn.XLOOKUP(_xlfn.XLOOKUP($B71,$T$13:$T$22,$U$13:$U$22),$K$71:$K$75,$L$71:$L$75) -> L1 – No Constraint | D71: vs | E71: =_xlfn.XLOOKUP(_xlfn.XLOOKUP($B71,$T$13:$T$22,$V$13:$V$22),$K$71:$K$75,$K$71:$K$75)&" – "&_xlfn.XLOOKUP(_xlfn.XLOOKUP($B71,$T$13:$T$22,$V$13:$V$22),$K$71:$K$75,$L$71:$L$75) -> L2 – Minor Constraint | F71: Criterion B – Intermediate value between Equal and Moderate importance (2) | G71: =IFERROR(_xlfn.XLOOKUP($F71,'AHP Saaty Reference'!$H$8:$H$24,'AHP Saaty Reference'!$I$8:$I$24),"") -> 0.5 | H71: L2 restricts implementation choices within a single architectural element, while the overall architecture remains adaptable; L1 imposes no constraint on architectural evolution. | K71: L1 | L71: No Constraint | M71: The EA smell does not introduce constraints on how changes to architectural elements can be implemented. Changes can be implemented without restrictions on technology choice, integration approach, or application structure. | N71: A duplicate reporting application exists but does not affect other systems; removing or keeping it does not restrict how changes to the architecture can be implemented.
B72: 2 | C72: =_xlfn.XLOOKUP(_xlfn.XLOOKUP($B72,$T$13:$T$22,$U$13:$U$22),$K$71:$K$75,$K$71:$K$75)&" – "&_xlfn.XLOOKUP(_xlfn.XLOOKUP($B72,$T$13:$T$22,$U$13:$U$22),$K$71:$K$75,$L$71:$L$75) -> L1 – No Constraint | D72: vs | E72: =_xlfn.XLOOKUP(_xlfn.XLOOKUP($B72,$T$13:$T$22,$V$13:$V$22),$K$71:$K$75,$K$71:$K$75)&" – "&_xlfn.XLOOKUP(_xlfn.XLOOKUP($B72,$T$13:$T$22,$V$13:$V$22),$K$71:$K$75,$L$71:$L$75) -> L3 – Moderate Constraint | F72: Criterion B – Moderate importance (3) | G72: =IFERROR(_xlfn.XLOOKUP($F72,'AHP Saaty Reference'!$H$8:$H$24,'AHP Saaty Reference'!$I$8:$I$24),"") -> 0.33333333 | H72: L3 requires changes to directly dependent architectural elements when one element is modified, whereas L1 allows changes without affecting other architectural elements. | K72: L2 | L72: Minor Constraint | M72: The EA smell introduces a localized constraint to a single architectural element (e.g., a component, service, or interface). Changes are restricted to specific implementation choices within that element (e.g., fixed technology, configuration, or interface definition), while the overall architecture remains adaptable, allowing new systems, components, or integrations to be introduced without restriction. | N72: An application uses a hard coded configuration for an external service endpoint. Changing the configuration requires modifying the application, but no other architectural elements are affected, and the overall architecture remains flexible.
B73: 3 | C73: =_xlfn.XLOOKUP(_xlfn.XLOOKUP($B73,$T$13:$T$22,$U$13:$U$22),$K$71:$K$75,$K$71:$K$75)&" – "&_xlfn.XLOOKUP(_xlfn.XLOOKUP($B73,$T$13:$T$22,$U$13:$U$22),$K$71:$K$75,$L$71:$L$75) -> L1 – No Constraint | D73: vs | E73: =_xlfn.XLOOKUP(_xlfn.XLOOKUP($B73,$T$13:$T$22,$V$13:$V$22),$K$71:$K$75,$K$71:$K$75)&" – "&_xlfn.XLOOKUP(_xlfn.XLOOKUP($B73,$T$13:$T$22,$V$13:$V$22),$K$71:$K$75,$L$71:$L$75) -> L4 – Strong Constraint | F73: Criterion B – Strong importance (5) | G73: =IFERROR(_xlfn.XLOOKUP($F73,'AHP Saaty Reference'!$H$8:$H$24,'AHP Saaty Reference'!$I$8:$I$24),"") -> 0.2 | H73: L4 causes changes to propagate across multiple levels of dependency, whereas L1 allows architectural elements to be changed without restrictions or dependent changes. | K73: L3 | L73: Moderate Constraint | M73: The EA smell introduces dependency-driven constraints between architectural elements. Changes to one architectural element require updates to directly dependent architectural elements (e.g., modifying an interface requires updating components that use that interface); however, the impact remains limited to a single level of dependency and does not propagate further. | N73: The CRM system exposes an interface consumed by the ERP system. Modifying the interface (e.g., changing required data fields) requires updating the ERP system to maintain compatibility, but no further elements are affected.
B74: 4 | C74: =_xlfn.XLOOKUP(_xlfn.XLOOKUP($B74,$T$13:$T$22,$U$13:$U$22),$K$71:$K$75,$K$71:$K$75)&" – "&_xlfn.XLOOKUP(_xlfn.XLOOKUP($B74,$T$13:$T$22,$U$13:$U$22),$K$71:$K$75,$L$71:$L$75) -> L1 – No Constraint | D74: vs | E74: =_xlfn.XLOOKUP(_xlfn.XLOOKUP($B74,$T$13:$T$22,$V$13:$V$22),$K$71:$K$75,$K$71:$K$75)&" – "&_xlfn.XLOOKUP(_xlfn.XLOOKUP($B74,$T$13:$T$22,$V$13:$V$22),$K$71:$K$75,$L$71:$L$75) -> L5 – Severe Constraint | F74: Criterion B – Extreme importance (9) | G74: =IFERROR(_xlfn.XLOOKUP($F74,'AHP Saaty Reference'!$H$8:$H$24,'AHP Saaty Reference'!$I$8:$I$24),"") -> 0.11111111 | H74: L5 prevents independent architectural evolution through a shared dependency and may require restructuring of the shared element, whereas L1 allows architectural changes without dependency-driven restrictions. | K74: L4 | L74: Strong Constraint | M74: The EA smell introduces dependency-driven constraints such that architectural elements depend on each other in a chain. Changes to one architectural element require coordinated updates to directly dependent architectural elements, with the impact propagating across multiple levels of dependency. | N74: The CRM system exposes an interface consumed by the ERP system, which relies on specific data fields. The ERP system provides this data to the Reporting system. Modifying the CRM interface (e.g., changing required data fields) requires updating the ERP system, which then requires updates in the Reporting system, causing the change to propagate across multiple dependent elements.
B75: 5 | C75: =_xlfn.XLOOKUP(_xlfn.XLOOKUP($B75,$T$13:$T$22,$U$13:$U$22),$K$71:$K$75,$K$71:$K$75)&" – "&_xlfn.XLOOKUP(_xlfn.XLOOKUP($B75,$T$13:$T$22,$U$13:$U$22),$K$71:$K$75,$L$71:$L$75) -> L2 – Minor Constraint | D75: vs | E75: =_xlfn.XLOOKUP(_xlfn.XLOOKUP($B75,$T$13:$T$22,$V$13:$V$22),$K$71:$K$75,$K$71:$K$75)&" – "&_xlfn.XLOOKUP(_xlfn.XLOOKUP($B75,$T$13:$T$22,$V$13:$V$22),$K$71:$K$75,$L$71:$L$75) -> L3 – Moderate Constraint | F75: Criterion B – Moderate importance (3) | G75: =IFERROR(_xlfn.XLOOKUP($F75,'AHP Saaty Reference'!$H$8:$H$24,'AHP Saaty Reference'!$I$8:$I$24),"") -> 0.33333333 | H75: L3 requires changes to directly dependent architectural elements when one element is modified, whereas L2 restricts changes only within a single architectural element without affecting other elements. | K75: L5 | L75: Severe Constraint | M75: The EA smell introduces dependency-driven constraints centered around a shared architectural element that is used by multiple architectural elements. Changes to the shared architectural element require simultaneous coordination across all dependent architectural elements, preventing independent architectural evolution. Consequently, future architectural evolution may require restructuring or replacement of the shared architectural element. | N75: The CRM, ERP, and Reporting systems rely on a shared data model that defines common data fields. Modifying the shared data model (e.g., changing required data fields) requires simultaneous updates across all dependent systems, preventing independent modification and requiring restructuring of the shared data model.
B76: 6 | C76: =_xlfn.XLOOKUP(_xlfn.XLOOKUP($B76,$T$13:$T$22,$U$13:$U$22),$K$71:$K$75,$K$71:$K$75)&" – "&_xlfn.XLOOKUP(_xlfn.XLOOKUP($B76,$T$13:$T$22,$U$13:$U$22),$K$71:$K$75,$L$71:$L$75) -> L2 – Minor Constraint | D76: vs | E76: =_xlfn.XLOOKUP(_xlfn.XLOOKUP($B76,$T$13:$T$22,$V$13:$V$22),$K$71:$K$75,$K$71:$K$75)&" – "&_xlfn.XLOOKUP(_xlfn.XLOOKUP($B76,$T$13:$T$22,$V$13:$V$22),$K$71:$K$75,$L$71:$L$75) -> L4 – Strong Constraint | F76: Criterion B – Strong importance (5) | G76: =IFERROR(_xlfn.XLOOKUP($F76,'AHP Saaty Reference'!$H$8:$H$24,'AHP Saaty Reference'!$I$8:$I$24),"") -> 0.2 | H76: L4 propagates changes across multiple dependency levels, while L2 remains localized to one architectural element.
B77: 7 | C77: =_xlfn.XLOOKUP(_xlfn.XLOOKUP($B77,$T$13:$T$22,$U$13:$U$22),$K$71:$K$75,$K$71:$K$75)&" – "&_xlfn.XLOOKUP(_xlfn.XLOOKUP($B77,$T$13:$T$22,$U$13:$U$22),$K$71:$K$75,$L$71:$L$75) -> L2 – Minor Constraint | D77: vs | E77: =_xlfn.XLOOKUP(_xlfn.XLOOKUP($B77,$T$13:$T$22,$V$13:$V$22),$K$71:$K$75,$K$71:$K$75)&" – "&_xlfn.XLOOKUP(_xlfn.XLOOKUP($B77,$T$13:$T$22,$V$13:$V$22),$K$71:$K$75,$L$71:$L$75) -> L5 – Severe Constraint | F77: Criterion B – Very strong importance (7) | G77: =IFERROR(_xlfn.XLOOKUP($F77,'AHP Saaty Reference'!$H$8:$H$24,'AHP Saaty Reference'!$I$8:$I$24),"") -> 0.14285714 | H77: L5 prevents independent evolution across multiple dependent architectural elements, while L2 imposes a constraint limited to a single architectural element.
B78: 8 | C78: =_xlfn.XLOOKUP(_xlfn.XLOOKUP($B78,$T$13:$T$22,$U$13:$U$22),$K$71:$K$75,$K$71:$K$75)&" – "&_xlfn.XLOOKUP(_xlfn.XLOOKUP($B78,$T$13:$T$22,$U$13:$U$22),$K$71:$K$75,$L$71:$L$75) -> L3 – Moderate Constraint | D78: vs | E78: =_xlfn.XLOOKUP(_xlfn.XLOOKUP($B78,$T$13:$T$22,$V$13:$V$22),$K$71:$K$75,$K$71:$K$75)&" – "&_xlfn.XLOOKUP(_xlfn.XLOOKUP($B78,$T$13:$T$22,$V$13:$V$22),$K$71:$K$75,$L$71:$L$75) -> L4 – Strong Constraint | F78: Criterion B – Strong importance (5) | G78: =IFERROR(_xlfn.XLOOKUP($F78,'AHP Saaty Reference'!$H$8:$H$24,'AHP Saaty Reference'!$I$8:$I$24),"") -> 0.2 | H78: L4 propagates changes across multiple dependency levels, requiring coordinated updates throughout the dependency chain, whereas L3 confines required changes to a single dependency level.
B79: 9 | C79: =_xlfn.XLOOKUP(_xlfn.XLOOKUP($B79,$T$13:$T$22,$U$13:$U$22),$K$71:$K$75,$K$71:$K$75)&" – "&_xlfn.XLOOKUP(_xlfn.XLOOKUP($B79,$T$13:$T$22,$U$13:$U$22),$K$71:$K$75,$L$71:$L$75) -> L3 – Moderate Constraint | D79: vs | E79: =_xlfn.XLOOKUP(_xlfn.XLOOKUP($B79,$T$13:$T$22,$V$13:$V$22),$K$71:$K$75,$K$71:$K$75)&" – "&_xlfn.XLOOKUP(_xlfn.XLOOKUP($B79,$T$13:$T$22,$V$13:$V$22),$K$71:$K$75,$L$71:$L$75) -> L5 – Severe Constraint | F79: Criterion B – Very strong importance (7) | G79: =IFERROR(_xlfn.XLOOKUP($F79,'AHP Saaty Reference'!$H$8:$H$24,'AHP Saaty Reference'!$I$8:$I$24),"") -> 0.14285714 | H79: L5 prevents multiple dependent architectural elements from evolving independently and may require restructuring of the shared architectural element, whereas L3 confines required changes to a single dependency level without further propagation.
B80: 10 | C80: =_xlfn.XLOOKUP(_xlfn.XLOOKUP($B80,$T$13:$T$22,$U$13:$U$22),$K$71:$K$75,$K$71:$K$75)&" – "&_xlfn.XLOOKUP(_xlfn.XLOOKUP($B80,$T$13:$T$22,$U$13:$U$22),$K$71:$K$75,$L$71:$L$75) -> L4 – Strong Constraint | D80: vs | E80: =_xlfn.XLOOKUP(_xlfn.XLOOKUP($B80,$T$13:$T$22,$V$13:$V$22),$K$71:$K$75,$K$71:$K$75)&" – "&_xlfn.XLOOKUP(_xlfn.XLOOKUP($B80,$T$13:$T$22,$V$13:$V$22),$K$71:$K$75,$L$71:$L$75) -> L5 – Severe Constraint | F80: Criterion B – Strong importance (5) | G80: =IFERROR(_xlfn.XLOOKUP($F80,'AHP Saaty Reference'!$H$8:$H$24,'AHP Saaty Reference'!$I$8:$I$24),"") -> 0.2 | H80: L5 prevents dependent architectural elements from evolving independently and may require restructuring of the shared element, whereas L4 still allows evolution through coordinated changes across the dependency chain.
B82: Consistency Ratio (CR) – The consistency ratio evaluates the consistency of your pairwise judgments. A CR ≤ 0.10 indicates acceptable consistency. If the CR exceeds 0.10, revise your pairwise judgments. | G82: =IF( '1.6 IP Calculations'!$W$52="", "Awaiting judgment inputs", IF( '1.6 IP Calculations'!$W$52<=0.1, "Acceptable"&CHAR(10)&"CR = "&TEXT('1.6 IP Calculations'!$W$52,"0.000"), "Not Acceptable – Revise judgments"&CHAR(10)&"CR = "&TEXT('1.6 IP Calculations'!$W$52,"0.000") ) ) -> Acceptable CR = 0.091
B84: Calculated Results Derived Intensity Priorities (Priority Vector)
B86: The priority vector is derived from the pairwise comparisons using the Analytic Hierarchy Process (AHP). Idealized priorities are obtained by dividing each priority by the largest priority, resulting in a maximum value of 1.000. These idealized priorities are automatically used during EA smell scoring.
B89: Level | C89: Idealized Priority
B90: L1 | C90: =IF(OR('1.6 IP Calculations'!$X26="",ISBLANK('1.6 IP Calculations'!$X26)),"Awaiting input",'1.6 IP Calculations'!$X26) -> 0.066383716
B91: L2 | C91: =IF(OR('1.6 IP Calculations'!$X27="",ISBLANK('1.6 IP Calculations'!$X27)),"Awaiting input",'1.6 IP Calculations'!$X27) -> 0.09315694
B92: L3 | C92: =IF(OR('1.6 IP Calculations'!$X28="",ISBLANK('1.6 IP Calculations'!$X28)),"Awaiting input",'1.6 IP Calculations'!$X28) -> 0.15959483
B93: L4 | C93: =IF(OR('1.6 IP Calculations'!$X29="",ISBLANK('1.6 IP Calculations'!$X29)),"Awaiting input",'1.6 IP Calculations'!$X29) -> 0.40764893
B94: L5 | C94: =IF(OR('1.6 IP Calculations'!$X30="",ISBLANK('1.6 IP Calculations'!$X30)),"Awaiting input",'1.6 IP Calculations'!$X30) -> 1
B97: Gov. & Coord. Overhead | J97: Gov. & Coord. Overhead ► | K97: To what extent does the EA smell instance require coordination across teams or governance bodies?
B99: Pair | C99: Criterion A | E99: Criterion B | F99: Pairwise Judgment | G99: AHP Score (calculated) | H99: Decision Rationale (Optional) | K99: Level | L99: Description | M99: Boundary Defintion | N99: Illustrative Example
B100: 1 | C100: =_xlfn.XLOOKUP(_xlfn.XLOOKUP($B100,$T$13:$T$22,$U$13:$U$22),$K$100:$K$104,$K$100:$K$104)&" – "&_xlfn.XLOOKUP(_xlfn.XLOOKUP($B71,$T$13:$T$22,$U$13:$U$22),$K$100:$K$104,$L$100:$L$104) -> L1 – Minimal Coordination Overhead | D100: vs | E100: =_xlfn.XLOOKUP(_xlfn.XLOOKUP($B100,$T$13:$T$22,$V$13:$V$22),$K$100:$K$104,$K$100:$K$104)&" – "&_xlfn.XLOOKUP(_xlfn.XLOOKUP($B71,$T$13:$T$22,$V$13:$V$22),$K$100:$K$104,$L$100:$L$104) -> L2 – Limited Coordination Overhead | F100: Criterion B – Moderate importance (3) | G100: =IFERROR(_xlfn.XLOOKUP($F100,'AHP Saaty Reference'!$H$8:$H$24,'AHP Saaty Reference'!$I$8:$I$24),"") -> 0.33333333 | H100: L2 introduces cross-group coordination between two stakeholder groups, whereas L1 can be addressed independently within a single stakeholder group. | K100: L1 | L100: Minimal Coordination Overhead | M100: The EA-smell instance creates little or no coordination dependency beyond a single stakeholder group. | N100: Duplicate functionality exists in the ERP and payroll systems for calculating timesheets. A business analyst identifies the redundancy and redesigns the business process so that timesheet calculation is performed only in the ERP system. The architectural condition is confined to the responsibility of a single stakeholder group and does not create coordination dependencies with other teams.
B101: 2 | C101: =_xlfn.XLOOKUP(_xlfn.XLOOKUP($B101,$T$13:$T$22,$U$13:$U$22),$K$100:$K$104,$K$100:$K$104)&" – "&_xlfn.XLOOKUP(_xlfn.XLOOKUP($B72,$T$13:$T$22,$U$13:$U$22),$K$100:$K$104,$L$100:$L$104) -> L1 – Minimal Coordination Overhead | D101: vs | E101: =_xlfn.XLOOKUP(_xlfn.XLOOKUP($B101,$T$13:$T$22,$V$13:$V$22),$K$100:$K$104,$K$100:$K$104)&" – "&_xlfn.XLOOKUP(_xlfn.XLOOKUP($B72,$T$13:$T$22,$V$13:$V$22),$K$100:$K$104,$L$100:$L$104) -> L3 – Moderate Coordination Overhead | F101: Criterion B – Strong importance (5) | G101: =IFERROR(_xlfn.XLOOKUP($F101,'AHP Saaty Reference'!$H$8:$H$24,'AHP Saaty Reference'!$I$8:$I$24),"") -> 0.2 | H101: L3 requires alignment across multiple stakeholder groups, creating substantially greater coordination effort than L1, which can be addressed independently within a single stakeholder group. | K101: L2 | L101: Limited Coordination Overhead | M101: The EA-smell instance creates coordination dependencies between two stakeholder groups. | N101: Duplicate functionality exists in the ERP and payroll systems for calculating timesheets. A business analyst decides that timesheet calculation should be performed only in the ERP system. Developers introduce a simple application interface through which the payroll system imports the calculated timesheets from the ERP system. The dependency between the two systems creates a coordination requirement between business stakeholders and application developers.
B102: 3 | C102: =_xlfn.XLOOKUP(_xlfn.XLOOKUP($B102,$T$13:$T$22,$U$13:$U$22),$K$100:$K$104,$K$100:$K$104)&" – "&_xlfn.XLOOKUP(_xlfn.XLOOKUP($B73,$T$13:$T$22,$U$13:$U$22),$K$100:$K$104,$L$100:$L$104) -> L1 – Minimal Coordination Overhead | D102: vs | E102: =_xlfn.XLOOKUP(_xlfn.XLOOKUP($B102,$T$13:$T$22,$V$13:$V$22),$K$100:$K$104,$K$100:$K$104)&" – "&_xlfn.XLOOKUP(_xlfn.XLOOKUP($B73,$T$13:$T$22,$V$13:$V$22),$K$100:$K$104,$L$100:$L$104) -> L4 – High Coordination Overhead | F102: Criterion B – Very strong importance (7) | G102: =IFERROR(_xlfn.XLOOKUP($F102,'AHP Saaty Reference'!$H$8:$H$24,'AHP Saaty Reference'!$I$8:$I$24),"") -> 0.14285714 | H102: L4 requires coordination across multiple stakeholder groups together with formal architectural governance approval or alignment, whereas L1 can be addressed independently within a single stakeholder group. | K102: L3 | L102: Moderate Coordination Overhead | M102: The EA-smell instance creates coordination dependencies across multiple stakeholder groups. | N102: Duplicate functionality exists in the ERP and payroll systems for calculating timesheets. A business analyst decides that timesheet calculation should be performed only in the ERP system. Developers introduce an application interface for importing the timesheets, while the infrastructure team configures an automated job scheduler to execute the transfer between systems. The resulting dependencies create coordination requirements among business stakeholders, developers, and infrastructure teams.
B103: 4 | C103: =_xlfn.XLOOKUP(_xlfn.XLOOKUP($B103,$T$13:$T$22,$U$13:$U$22),$K$100:$K$104,$K$100:$K$104)&" – "&_xlfn.XLOOKUP(_xlfn.XLOOKUP($B74,$T$13:$T$22,$U$13:$U$22),$K$100:$K$104,$L$100:$L$104) -> L1 – Minimal Coordination Overhead | D103: vs | E103: =_xlfn.XLOOKUP(_xlfn.XLOOKUP($B103,$T$13:$T$22,$V$13:$V$22),$K$100:$K$104,$K$100:$K$104)&" – "&_xlfn.XLOOKUP(_xlfn.XLOOKUP($B74,$T$13:$T$22,$V$13:$V$22),$K$100:$K$104,$L$100:$L$104) -> L5 – Strategic Coordination Overhead | F103: Criterion B – Extreme importance (9) | G103: =IFERROR(_xlfn.XLOOKUP($F103,'AHP Saaty Reference'!$H$8:$H$24,'AHP Saaty Reference'!$I$8:$I$24),"") -> 0.11111111 | H103: L5 requires cross-domain coordination among multiple stakeholder groups and enterprise-level strategic approval, whereas L1 can be addressed independently within a single stakeholder group without cross-group coordination. | K103: L4 | L103: High Coordination Overhead | M103: The EA-smell instance creates coordination dependencies across multiple stakeholder groups and requires recurring involvement of formal architectural governance bodies to align or approve changes affecting the architectural condition (e.g., architecture review boards). | N103: An enterprise application relies on vendor-specific database features, creating vendor lock-in. Removing the dependency requires introducing a database abstraction layer to decouple the application from vendor-specific functionality. The architectural and technology dependencies involved create coordination requirements between developers, infrastructure teams, and enterprise architects and require review and approval through architectural governance.
B104: 5 | C104: =_xlfn.XLOOKUP(_xlfn.XLOOKUP($B104,$T$13:$T$22,$U$13:$U$22),$K$100:$K$104,$K$100:$K$104)&" – "&_xlfn.XLOOKUP(_xlfn.XLOOKUP($B75,$T$13:$T$22,$U$13:$U$22),$K$100:$K$104,$L$100:$L$104) -> L2 – Limited Coordination Overhead | D104: vs | E104: =_xlfn.XLOOKUP(_xlfn.XLOOKUP($B104,$T$13:$T$22,$V$13:$V$22),$K$100:$K$104,$K$100:$K$104)&" – "&_xlfn.XLOOKUP(_xlfn.XLOOKUP($B75,$T$13:$T$22,$V$13:$V$22),$K$100:$K$104,$L$100:$L$104) -> L3 – Moderate Coordination Overhead | F104: Criterion B – Moderate importance (3) | G104: =IFERROR(_xlfn.XLOOKUP($F104,'AHP Saaty Reference'!$H$8:$H$24,'AHP Saaty Reference'!$I$8:$I$24),"") -> 0.33333333 | H104: L3 requires alignment across multiple stakeholder groups, increasing coordination complexity compared with L2, where coordination is limited to two stakeholder groups. | K104: L5 | L104: Strategic Coordination Overhead | M104: The EA-smell instance creates coordination dependencies across multiple organizational domains and stakeholder groups and requires strategic decisions or alignment from enterprise leadership or program sponsors (e.g., CIO, steering committee). | N104: Several enterprise applications rely on a vendor-specific database platform, creating strong vendor lock-in. Eliminating the dependency would require migrating multiple systems to an alternative platform and redesigning parts of the application landscape. The resulting cross-system dependencies create coordination requirements across multiple organizational domains and affect the enterprise architecture roadmap, requiring strategic alignment and decisions by enterprise leadership or program sponsors.
B105: 6 | C105: =_xlfn.XLOOKUP(_xlfn.XLOOKUP($B105,$T$13:$T$22,$U$13:$U$22),$K$100:$K$104,$K$100:$K$104)&" – "&_xlfn.XLOOKUP(_xlfn.XLOOKUP($B76,$T$13:$T$22,$U$13:$U$22),$K$100:$K$104,$L$100:$L$104) -> L2 – Limited Coordination Overhead | D105: vs | E105: =_xlfn.XLOOKUP(_xlfn.XLOOKUP($B105,$T$13:$T$22,$V$13:$V$22),$K$100:$K$104,$K$100:$K$104)&" – "&_xlfn.XLOOKUP(_xlfn.XLOOKUP($B76,$T$13:$T$22,$V$13:$V$22),$K$100:$K$104,$L$100:$L$104) -> L4 – High Coordination Overhead | F105: Criterion B – Strong importance (5) | G105: =IFERROR(_xlfn.XLOOKUP($F105,'AHP Saaty Reference'!$H$8:$H$24,'AHP Saaty Reference'!$I$8:$I$24),"") -> 0.2 | H105: L4 extends coordination from two stakeholder groups to multiple groups and introduces formal architectural governance approval or alignment, creating substantially greater coordination overhead than L2.
B106: 7 | C106: =_xlfn.XLOOKUP(_xlfn.XLOOKUP($B106,$T$13:$T$22,$U$13:$U$22),$K$100:$K$104,$K$100:$K$104)&" – "&_xlfn.XLOOKUP(_xlfn.XLOOKUP($B77,$T$13:$T$22,$U$13:$U$22),$K$100:$K$104,$L$100:$L$104) -> L2 – Limited Coordination Overhead | D106: vs | E106: =_xlfn.XLOOKUP(_xlfn.XLOOKUP($B106,$T$13:$T$22,$V$13:$V$22),$K$100:$K$104,$K$100:$K$104)&" – "&_xlfn.XLOOKUP(_xlfn.XLOOKUP($B77,$T$13:$T$22,$V$13:$V$22),$K$100:$K$104,$L$100:$L$104) -> L5 – Strategic Coordination Overhead | F106: Criterion B – Very strong importance (7) | G106: =IFERROR(_xlfn.XLOOKUP($F106,'AHP Saaty Reference'!$H$8:$H$24,'AHP Saaty Reference'!$I$8:$I$24),"") -> 0.14285714 | H106: L5 extends coordination from two stakeholder groups to multiple organizational domains and introduces enterprise-level strategic approval, creating substantially greater coordination and decision-making overhead than L2.
B107: 8 | C107: =_xlfn.XLOOKUP(_xlfn.XLOOKUP($B107,$T$13:$T$22,$U$13:$U$22),$K$100:$K$104,$K$100:$K$104)&" – "&_xlfn.XLOOKUP(_xlfn.XLOOKUP($B78,$T$13:$T$22,$U$13:$U$22),$K$100:$K$104,$L$100:$L$104) -> L3 – Moderate Coordination Overhead | D107: vs | E107: =_xlfn.XLOOKUP(_xlfn.XLOOKUP($B107,$T$13:$T$22,$V$13:$V$22),$K$100:$K$104,$K$100:$K$104)&" – "&_xlfn.XLOOKUP(_xlfn.XLOOKUP($B78,$T$13:$T$22,$V$13:$V$22),$K$100:$K$104,$L$100:$L$104) -> L4 – High Coordination Overhead | F107: Criterion B – Strong importance (5) | G107: =IFERROR(_xlfn.XLOOKUP($F107,'AHP Saaty Reference'!$H$8:$H$24,'AHP Saaty Reference'!$I$8:$I$24),"") -> 0.2 | H107: L4 introduces formal architectural governance approval or alignment in addition to multi-group coordination, creating substantially greater coordination and decision-making overhead than L3.
B108: 9 | C108: =_xlfn.XLOOKUP(_xlfn.XLOOKUP($B108,$T$13:$T$22,$U$13:$U$22),$K$100:$K$104,$K$100:$K$104)&" – "&_xlfn.XLOOKUP(_xlfn.XLOOKUP($B79,$T$13:$T$22,$U$13:$U$22),$K$100:$K$104,$L$100:$L$104) -> L3 – Moderate Coordination Overhead | D108: vs | E108: =_xlfn.XLOOKUP(_xlfn.XLOOKUP($B108,$T$13:$T$22,$V$13:$V$22),$K$100:$K$104,$K$100:$K$104)&" – "&_xlfn.XLOOKUP(_xlfn.XLOOKUP($B79,$T$13:$T$22,$V$13:$V$22),$K$100:$K$104,$L$100:$L$104) -> L5 – Strategic Coordination Overhead | F108: Criterion B – Very strong importance (7) | G108: =IFERROR(_xlfn.XLOOKUP($F108,'AHP Saaty Reference'!$H$8:$H$24,'AHP Saaty Reference'!$I$8:$I$24),"") -> 0.14285714 | H108: L5 extends coordination across organizational domains and requires enterprise-level strategic approval, creating substantially greater coordination and decision-making overhead than the multi-group coordination required at L3.
B109: 10 | C109: =_xlfn.XLOOKUP(_xlfn.XLOOKUP($B109,$T$13:$T$22,$U$13:$U$22),$K$100:$K$104,$K$100:$K$104)&" – "&_xlfn.XLOOKUP(_xlfn.XLOOKUP($B80,$T$13:$T$22,$U$13:$U$22),$K$100:$K$104,$L$100:$L$104) -> L4 – High Coordination Overhead | D109: vs | E109: =_xlfn.XLOOKUP(_xlfn.XLOOKUP($B109,$T$13:$T$22,$V$13:$V$22),$K$100:$K$104,$K$100:$K$104)&" – "&_xlfn.XLOOKUP(_xlfn.XLOOKUP($B80,$T$13:$T$22,$V$13:$V$22),$K$100:$K$104,$L$100:$L$104) -> L5 – Strategic Coordination Overhead | F109: Criterion B – Moderate importance (3) | G109: =IFERROR(_xlfn.XLOOKUP($F109,'AHP Saaty Reference'!$H$8:$H$24,'AHP Saaty Reference'!$I$8:$I$24),"") -> 0.33333333 | H109: L5 extends governance from architectural approval and alignment to cross-domain coordination and enterprise-level strategic decision-making, whereas L4 remains within formal architectural governance.
B111: Consistency Ratio (CR) – The consistency ratio evaluates the consistency of your pairwise judgments. A CR ≤ 0.10 indicates acceptable consistency. If the CR exceeds 0.10, revise your pairwise judgments. | G111: =IF( '1.6 IP Calculations'!$AH$52="", "Awaiting judgment inputs", IF( '1.6 IP Calculations'!$AH$52<=0.1, "Acceptable"&CHAR(10)&"CR = "&TEXT('1.6 IP Calculations'!$AH$52,"0.000"), "Not Acceptable – Revise judgments"&CHAR(10)&"CR = "&TEXT('1.6 IP Calculations'!$AH$52,"0.000") ) ) -> Acceptable CR = 0.087
B113: Calculated Results Derived Intensity Priorities (Priority Vector)
B115: The priority vector is derived from the pairwise comparisons using the Analytic Hierarchy Process (AHP). Idealized priorities are obtained by dividing each priority by the largest priority, resulting in a maximum value of 1.000. These idealized priorities are automatically used during EA smell scoring.
B118: Level | C118: Idealized Priority
B119: L1 | C119: =IF(OR('1.6 IP Calculations'!$AI26="",ISBLANK('1.6 IP Calculations'!$AI26)),"Awaiting input",'1.6 IP Calculations'!$AI26) -> 0.060797762
B120: L2 | C120: =IF(OR('1.6 IP Calculations'!$AI27="",ISBLANK('1.6 IP Calculations'!$AI27)),"Awaiting input",'1.6 IP Calculations'!$AI27) -> 0.11414868
B121: L3 | C121: =IF(OR('1.6 IP Calculations'!$AI28="",ISBLANK('1.6 IP Calculations'!$AI28)),"Awaiting input",'1.6 IP Calculations'!$AI28) -> 0.20441776
B122: L4 | C122: =IF(OR('1.6 IP Calculations'!$AI29="",ISBLANK('1.6 IP Calculations'!$AI29)),"Awaiting input",'1.6 IP Calculations'!$AI29) -> 0.53621892
B123: L5 | C123: =IF(OR('1.6 IP Calculations'!$AI30="",ISBLANK('1.6 IP Calculations'!$AI30)),"Awaiting input",'1.6 IP Calculations'!$AI30) -> 1
B126: Operational Reliability Impact | J126: Operational Reliability Impact ► | K126: To what extent does the EA smell instance negatively affect system reliability or stability of operations?
B128: Pair | C128: Criterion A | E128: Criterion B | F128: Pairwise Judgment | G128: AHP Score (calculated) | H128: Decision Rationale (Optional) | K128: Level | L128: Description | M128: Boundary Defintion | N128: Illustrative Example
B129: 1 | C129: =_xlfn.XLOOKUP(_xlfn.XLOOKUP($B129,$T$13:$T$22,$U$13:$U$22),$K$129:$K$133,$K$129:$K$133)&" – "&_xlfn.XLOOKUP(_xlfn.XLOOKUP($B129,$T$13:$T$22,$U$13:$U$22),$K$129:$K$133,$L$129:$L$133) -> L1 – No Impact | D129: vs | E129: =_xlfn.XLOOKUP(_xlfn.XLOOKUP($B129,$T$13:$T$22,$V$13:$V$22),$K$100:$K$104,$K$100:$K$104)&" – "&_xlfn.XLOOKUP(_xlfn.XLOOKUP($B129,$T$13:$T$22,$V$13:$V$22),$K$100:$K$104,$L$100:$L$104) -> L2 – Limited Coordination Overhead | F129: Criterion B – Intermediate value between Equal and Moderate importance (2) | G129: =IFERROR(_xlfn.XLOOKUP($F129,'AHP Saaty Reference'!$H$8:$H$24,'AHP Saaty Reference'!$I$8:$I$24),"") -> 0.5 | H129: L2 introduces observable reliability issues that are automatically resolved without affecting system operation, whereas L1 has no observed failures or disruptions. | K129: L1 | L129: No Impact | M129: No failures or disruptions are observed that can be associated with the EA smell. System operation remains stable, with no incident records or logs indicating operational issues. | N129: An EA smell is identified in the architecture, but no incidents, errors, or operational anomalies have been reported, and all services continue to operate as expected.
B130: 2 | C130: =_xlfn.XLOOKUP(_xlfn.XLOOKUP($B130,$T$13:$T$22,$U$13:$U$22),$K$129:$K$133,$K$129:$K$133)&" – "&_xlfn.XLOOKUP(_xlfn.XLOOKUP($B130,$T$13:$T$22,$U$13:$U$22),$K$129:$K$133,$L$129:$L$133) -> L1 – No Impact | D130: vs | E130: =_xlfn.XLOOKUP(_xlfn.XLOOKUP($B130,$T$13:$T$22,$V$13:$V$22),$K$100:$K$104,$K$100:$K$104)&" – "&_xlfn.XLOOKUP(_xlfn.XLOOKUP($B130,$T$13:$T$22,$V$13:$V$22),$K$100:$K$104,$L$100:$L$104) -> L3 – Moderate Coordination Overhead | F130: Criterion B – Strong importance (5) | G130: =IFERROR(_xlfn.XLOOKUP($F130,'AHP Saaty Reference'!$H$8:$H$24,'AHP Saaty Reference'!$I$8:$I$24),"") -> 0.2 | H130: L3 causes a localized operational disruption requiring manual intervention, whereas L1 has no observed failures or disruptions and system operation remains stable. | K130: L2 | L130: Minor Impact | M130: Issues associated with the EA smell may be observable in logs or low-priority events but do not affect system operation. These issues are resolved automatically through built-in mechanisms and do not require manual operational intervention. | N130: Occasional errors related to the EA smell are recorded in system logs but are resolved through retry or fallback mechanisms, and services continue to operate without interruption or user impact.
B131: 3 | C131: =_xlfn.XLOOKUP(_xlfn.XLOOKUP($B131,$T$13:$T$22,$U$13:$U$22),$K$129:$K$133,$K$129:$K$133)&" – "&_xlfn.XLOOKUP(_xlfn.XLOOKUP($B131,$T$13:$T$22,$U$13:$U$22),$K$129:$K$133,$L$129:$L$133) -> L1 – No Impact | D131: vs | E131: =_xlfn.XLOOKUP(_xlfn.XLOOKUP($B131,$T$13:$T$22,$V$13:$V$22),$K$100:$K$104,$K$100:$K$104)&" – "&_xlfn.XLOOKUP(_xlfn.XLOOKUP($B131,$T$13:$T$22,$V$13:$V$22),$K$100:$K$104,$L$100:$L$104) -> L4 – High Coordination Overhead | F131: Criterion B – Very strong importance (7) | G131: =IFERROR(_xlfn.XLOOKUP($F131,'AHP Saaty Reference'!$H$8:$H$24,'AHP Saaty Reference'!$I$8:$I$24),"") -> 0.14285714 | H131: L4 degrades business-critical capabilities and requires substantial operational recovery effort, whereas L1 has no observed failures or disruptions and system operation remains stable. | K131: L3 | L131: Moderate Impact | M131: Failures associated with the EA smell cause a noticeable but localized disruption to system operation and require manual operational intervention to resolve. The impact remains confined to a single component or service and does not degrade business-critical capabilities. | N131: An incident associated with the EA smell results in a localized disruption to a single component or service, requiring manual intervention (e.g., restart or correction), while business-critical capabilities continue to operate normally.
B132: 4 | C132: =_xlfn.XLOOKUP(_xlfn.XLOOKUP($B132,$T$13:$T$22,$U$13:$U$22),$K$129:$K$133,$K$129:$K$133)&" – "&_xlfn.XLOOKUP(_xlfn.XLOOKUP($B132,$T$13:$T$22,$U$13:$U$22),$K$129:$K$133,$L$129:$L$133) -> L1 – No Impact | D132: vs | E132: =_xlfn.XLOOKUP(_xlfn.XLOOKUP($B132,$T$13:$T$22,$V$13:$V$22),$K$100:$K$104,$K$100:$K$104)&" – "&_xlfn.XLOOKUP(_xlfn.XLOOKUP($B132,$T$13:$T$22,$V$13:$V$22),$K$100:$K$104,$L$100:$L$104) -> L5 – Strategic Coordination Overhead | F132: Criterion B – Extreme importance (9) | G132: =IFERROR(_xlfn.XLOOKUP($F132,'AHP Saaty Reference'!$H$8:$H$24,'AHP Saaty Reference'!$I$8:$I$24),"") -> 0.11111111 | H132: L5 results in sustained unavailability of business-critical capabilities that cannot be restored through normal operational actions, whereas L1 has no observed failures or disruptions and system operation remains stable. | K132: L4 | L132: High Impact | M132: Failures associated with the EA smell cause disruptions that degrade business-critical capabilities (e.g., slower performance, reduced functionality, or intermittent failures) while the system remains operational. Recovery requires substantial operational effort. | N132: Incidents associated with the EA smell result in degraded performance of a business-critical capability (e.g., slower response times or limited functionality), requiring repeated operational intervention, while the service remains available.
B133: 5 | C133: =_xlfn.XLOOKUP(_xlfn.XLOOKUP($B133,$T$13:$T$22,$U$13:$U$22),$K$129:$K$133,$K$129:$K$133)&" – "&_xlfn.XLOOKUP(_xlfn.XLOOKUP($B133,$T$13:$T$22,$U$13:$U$22),$K$129:$K$133,$L$129:$L$133) -> L2 – Minor Impact | D133: vs | E133: =_xlfn.XLOOKUP(_xlfn.XLOOKUP($B133,$T$13:$T$22,$V$13:$V$22),$K$100:$K$104,$K$100:$K$104)&" – "&_xlfn.XLOOKUP(_xlfn.XLOOKUP($B133,$T$13:$T$22,$V$13:$V$22),$K$100:$K$104,$L$100:$L$104) -> L3 – Moderate Coordination Overhead | F133: Criterion B – Moderate importance (3) | G133: =IFERROR(_xlfn.XLOOKUP($F133,'AHP Saaty Reference'!$H$8:$H$24,'AHP Saaty Reference'!$I$8:$I$24),"") -> 0.33333333 | H133: L3 causes a localized operational disruption requiring manual intervention, whereas L2 issues are automatically resolved without affecting system operation. | K133: L5 | L133: Critical Impact | M133: Failures associated with the EA smell cannot be restored through normal operational actions and result in sustained unavailability of business-critical capabilities. | N133: Persistent incidents associated with the EA smell result in the sustained unavailability of a business-critical capability, and the system cannot be restored through standard operational actions, requiring architectural redesign.
B134: 6 | C134: =_xlfn.XLOOKUP(_xlfn.XLOOKUP($B134,$T$13:$T$22,$U$13:$U$22),$K$129:$K$133,$K$129:$K$133)&" – "&_xlfn.XLOOKUP(_xlfn.XLOOKUP($B134,$T$13:$T$22,$U$13:$U$22),$K$129:$K$133,$L$129:$L$133) -> L2 – Minor Impact | D134: vs | E134: =_xlfn.XLOOKUP(_xlfn.XLOOKUP($B134,$T$13:$T$22,$V$13:$V$22),$K$100:$K$104,$K$100:$K$104)&" – "&_xlfn.XLOOKUP(_xlfn.XLOOKUP($B134,$T$13:$T$22,$V$13:$V$22),$K$100:$K$104,$L$100:$L$104) -> L4 – High Coordination Overhead | F134: Criterion B – Very strong importance (7) | G134: =IFERROR(_xlfn.XLOOKUP($F134,'AHP Saaty Reference'!$H$8:$H$24,'AHP Saaty Reference'!$I$8:$I$24),"") -> 0.14285714 | H134: L4 degrades business-critical capabilities and requires substantial recovery effort, whereas L2 issues do not affect system operation and are resolved automatically.
B135: 7 | C135: =_xlfn.XLOOKUP(_xlfn.XLOOKUP($B135,$T$13:$T$22,$U$13:$U$22),$K$129:$K$133,$K$129:$K$133)&" – "&_xlfn.XLOOKUP(_xlfn.XLOOKUP($B135,$T$13:$T$22,$U$13:$U$22),$K$129:$K$133,$L$129:$L$133) -> L2 – Minor Impact | D135: vs | E135: =_xlfn.XLOOKUP(_xlfn.XLOOKUP($B135,$T$13:$T$22,$V$13:$V$22),$K$100:$K$104,$K$100:$K$104)&" – "&_xlfn.XLOOKUP(_xlfn.XLOOKUP($B135,$T$13:$T$22,$V$13:$V$22),$K$100:$K$104,$L$100:$L$104) -> L5 – Strategic Coordination Overhead | F135: Criterion B – Extreme importance (9) | G135: =IFERROR(_xlfn.XLOOKUP($F135,'AHP Saaty Reference'!$H$8:$H$24,'AHP Saaty Reference'!$I$8:$I$24),"") -> 0.11111111 | H135: L5 causes sustained unavailability of business-critical capabilities that cannot be restored through normal operational actions, whereas L2 issues do not affect system operation and are resolved automatically.
B136: 8 | C136: =_xlfn.XLOOKUP(_xlfn.XLOOKUP($B136,$T$13:$T$22,$U$13:$U$22),$K$129:$K$133,$K$129:$K$133)&" – "&_xlfn.XLOOKUP(_xlfn.XLOOKUP($B136,$T$13:$T$22,$U$13:$U$22),$K$129:$K$133,$L$129:$L$133) -> L3 – Moderate Impact | D136: vs | E136: =_xlfn.XLOOKUP(_xlfn.XLOOKUP($B136,$T$13:$T$22,$V$13:$V$22),$K$100:$K$104,$K$100:$K$104)&" – "&_xlfn.XLOOKUP(_xlfn.XLOOKUP($B136,$T$13:$T$22,$V$13:$V$22),$K$100:$K$104,$L$100:$L$104) -> L4 – High Coordination Overhead | F136: Criterion B – Strong importance (5) | G136: =IFERROR(_xlfn.XLOOKUP($F136,'AHP Saaty Reference'!$H$8:$H$24,'AHP Saaty Reference'!$I$8:$I$24),"") -> 0.2 | H136: L4 degrades business-critical capabilities and requires substantial recovery effort, whereas L3 remains a localized disruption requiring manual intervention without affecting business-critical capabilities.
B137: 9 | C137: =_xlfn.XLOOKUP(_xlfn.XLOOKUP($B137,$T$13:$T$22,$U$13:$U$22),$K$129:$K$133,$K$129:$K$133)&" – "&_xlfn.XLOOKUP(_xlfn.XLOOKUP($B137,$T$13:$T$22,$U$13:$U$22),$K$129:$K$133,$L$129:$L$133) -> L3 – Moderate Impact | D137: vs | E137: =_xlfn.XLOOKUP(_xlfn.XLOOKUP($B137,$T$13:$T$22,$V$13:$V$22),$K$100:$K$104,$K$100:$K$104)&" – "&_xlfn.XLOOKUP(_xlfn.XLOOKUP($B137,$T$13:$T$22,$V$13:$V$22),$K$100:$K$104,$L$100:$L$104) -> L5 – Strategic Coordination Overhead | F137: Criterion B – Very strong importance (7) | G137: =IFERROR(_xlfn.XLOOKUP($F137,'AHP Saaty Reference'!$H$8:$H$24,'AHP Saaty Reference'!$I$8:$I$24),"") -> 0.14285714 | H137: L5 causes sustained unavailability of business-critical capabilities that cannot be restored through normal operational actions, whereas L3 remains a localized, manually recoverable disruption without affecting business-critical capabilities.
B138: 10 | C138: =_xlfn.XLOOKUP(_xlfn.XLOOKUP($B138,$T$13:$T$22,$U$13:$U$22),$K$129:$K$133,$K$129:$K$133)&" – "&_xlfn.XLOOKUP(_xlfn.XLOOKUP($B138,$T$13:$T$22,$U$13:$U$22),$K$129:$K$133,$L$129:$L$133) -> L4 – High Impact | D138: vs | E138: =_xlfn.XLOOKUP(_xlfn.XLOOKUP($B138,$T$13:$T$22,$V$13:$V$22),$K$100:$K$104,$K$100:$K$104)&" – "&_xlfn.XLOOKUP(_xlfn.XLOOKUP($B138,$T$13:$T$22,$V$13:$V$22),$K$100:$K$104,$L$100:$L$104) -> L5 – Strategic Coordination Overhead | F138: Criterion B – Moderate importance (3) | G138: =IFERROR(_xlfn.XLOOKUP($F138,'AHP Saaty Reference'!$H$8:$H$24,'AHP Saaty Reference'!$I$8:$I$24),"") -> 0.33333333 | H138: L5 results in sustained unavailability of business-critical capabilities that cannot be restored through normal operational actions, whereas L4 degrades those capabilities but keeps the system operational.
B140: Consistency Ratio (CR) – The consistency ratio evaluates the consistency of your pairwise judgments. A CR ≤ 0.10 indicates acceptable consistency. If the CR exceeds 0.10, revise your pairwise judgments. | G140: =IF( '1.6 IP Calculations'!$AR$52="", "Awaiting judgment inputs", IF( '1.6 IP Calculations'!$AR$52<=0.1, "Acceptable"&CHAR(10)&"CR = "&TEXT('1.6 IP Calculations'!$AR$52,"0.000"), "Not Acceptable – Revise judgments"&CHAR(10)&"CR = "&TEXT('1.6 IP Calculations'!$AR$52,"0.000") ) ) -> Acceptable CR = 0.072
...

Sheet 1.4 EA Smell Scoring
B2: Step 3 — EA Smell Scoring Matrix | K2: Scoring Guidance
B4: Instructions: Select up to 10 EA smells in the EA Smell Catalogue sheet, then assign each selected smell a 1–5 rating for every subcriterion using the reference panels on the right [+]. Ratings are entered once and reused across all weighting scenarios; only the criteria weights vary. | K4: Scope ► (click +) | L4: How many architectural elements must change to eliminate this EA smell instance? | P4: Restructuring Complexity ► (click +) | Q4: How structurally difficult is it to remove this EA smell instance from the architecture? | U4: Evolution Constraint ► (click +) | V4: To what extent does the EA smell instance limit the architecture’s ability to evolve or change? | Z4: Gov. & Coord. Overhead ► (click +) | AA4: To what extent does the EA smell instance require coordination across teams or governance bodies? | AE4: Operational Reliability Impact ► (click +) | AF4: To what extent does the EA smell instance negatively affect system reliability or stability of operations?
B6: Go to EA Smell Catalogue → | D6: User Input ↓ Select a rating (1–5) for each subcriterion | K6: Subcriterion definitons are maintained in the Pairwise: Intensity Priorities sheet. Do NOT modify in this sheet.
B7: # | C7: EA Smell | D7: Remediation Effort | F7: Impact | I7: Notes
D8: Scope | E8: Restructuring Complexity | F8: Evolution Constraint | G8: Governance Overhead | H8: Reliability Impact | L8: Level | M8: Boundary Definition | N8: Illustrative Example | Q8: Level | R8: Boundary Definition | S8: Representative Refactoring Types (derived from Liss et al.) | V8: Level | W8: Boundary Definition | X8: Illustrative Example | AA8: Level | AB8: Boundary Definition | AC8: Illustrative Example | AF8: Level | AG8: Boundary Definition | AH8: Illustrative Example
B9: 1 | C9: Cyclic Dependency | D9: 4 | E9: 4 | F9: 4 | G9: 3 | H9: 3 | I9: Mutual dependencies across components increase restructuring complexity and significantly constrain independent evolution. | L9: =_xlfn.CONCAT('1.3 IP Pairwise'!K13," ","-"," ",'1.3 IP Pairwise'!L13) -> L1 - Single Element | M9: ='1.3 IP Pairwise'!M13 -> Changes affect one architectural element only (e.g., component, service, or interface). | N9: ='1.3 IP Pairwise'!N13 -> In the CRM system, the Customer Service interface is incorrectly defined. Fixing the issue requires modifying only the Customer Service interface. | Q9: =_xlfn.CONCAT('1.3 IP Pairwise'!K42," ","-"," ",'1.3 IP Pairwise'!L42) -> L1 - Minor Architectural Adjustment | R9: ='1.3 IP Pairwise'!M42 -> Small changes to architectural elements that do not alter component responsibilities or the overall architectural structure. | S9: ='1.3 IP Pairwise'!N42 -> Rename Component | V9: =_xlfn.CONCAT('1.3 IP Pairwise'!K71," ","-"," ",'1.3 IP Pairwise'!L71) -> L1 - No Constraint | W9: ='1.3 IP Pairwise'!M71 -> The EA smell does not introduce constraints on how changes to architectural elements can be implemented. Changes can be implemented without restrictions on technology choice, integration approach, or application structure. | X9: ='1.3 IP Pairwise'!N71 -> A duplicate reporting application exists but does not affect other systems; removing or keeping it does not restrict how changes to the architecture can be implemented. | AA9: =_xlfn.CONCAT('1.3 IP Pairwise'!K100," ","-"," ",'1.3 IP Pairwise'!L100) -> L1 - Minimal Coordination Overhead | AB9: ='1.3 IP Pairwise'!M100 -> The EA-smell instance creates little or no coordination dependency beyond a single stakeholder group. | AC9: ='1.3 IP Pairwise'!N100 -> Duplicate functionality exists in the ERP and payroll systems for calculating timesheets. A business analyst identifies the redundancy and redesigns the business process so that timesheet calculation is performed only in the ERP system. The architectural condition is confined to the responsibility of a single stakeholder group and does not create coordination dependencies with other teams. | AF9: =_xlfn.CONCAT('1.3 IP Pairwise'!K129," ","-"," ",'1.3 IP Pairwise'!L129) -> L1 - No Impact | AG9: ='1.3 IP Pairwise'!M129 -> No failures or disruptions are observed that can be associated with the EA smell. System operation remains stable, with no incident records or logs indicating operational issues. | AH9: ='1.3 IP Pairwise'!N129 -> An EA smell is identified in the architecture, but no incidents, errors, or operational anomalies have been reported, and all services continue to operate as expected.
B10: 2 | C10: Shared Persistency | D10: 5 | E10: 3 | F10: 5 | G10: 4 | H10: 4 | I10: Shared Persistency was scored with high scope and evolution constraint due to its cross-system impact and tight data coupling, while restructuring complexity was assessed as moderate given the availability of established architectural refactoring approaches. | L10: =_xlfn.CONCAT('1.3 IP Pairwise'!K14," ","-"," ",'1.3 IP Pairwise'!L14) -> L2 - Single System | M10: ='1.3 IP Pairwise'!M14 -> Changes affect multiple architectural elements within the same application/system boundary, but no other systems are involved. | N10: ='1.3 IP Pairwise'!N14 -> Within the ERP system, the Order Service is tightly coupled to the Inventory Service. Resolving the issue requires modifying both services within the ERP system. | Q10: =_xlfn.CONCAT('1.3 IP Pairwise'!K43," ","-"," ",'1.3 IP Pairwise'!L43) -> L2 - Local Component Modification | R10: ='1.3 IP Pairwise'!M43 -> Changes affecting a single architectural component without altering how the architecture is organized or relationships between components. | S10: ='1.3 IP Pairwise'!N43 -> Remove Dead Component, Inline Service | V10: =_xlfn.CONCAT('1.3 IP Pairwise'!K72," ","-"," ",'1.3 IP Pairwise'!L72) -> L2 - Minor Constraint | W10: ='1.3 IP Pairwise'!M72 -> The EA smell introduces a localized constraint to a single architectural element (e.g., a component, service, or interface). Changes are restricted to specific implementation choices within that element (e.g., fixed technology, configuration, or interface definition), while the overall architecture remains adaptable, allowing new systems, components, or integrations to be introduced without restriction. | X10: ='1.3 IP Pairwise'!N72 -> An application uses a hard coded configuration for an external service endpoint. Changing the configuration requires modifying the application, but no other architectural elements are affected, and the overall architecture remains flexible. | AA10: =_xlfn.CONCAT('1.3 IP Pairwise'!K101," ","-"," ",'1.3 IP Pairwise'!L101) -> L2 - Limited Coordination Overhead | AB10: ='1.3 IP Pairwise'!M101 -> The EA-smell instance creates coordination dependencies between two stakeholder groups. | AC10: ='1.3 IP Pairwise'!N101 -> Duplicate functionality exists in the ERP and payroll systems for calculating timesheets. A business analyst decides that timesheet calculation should be performed only in the ERP system. Developers introduce a simple application interface through which the payroll system imports the calculated timesheets from the ERP system. The dependency between the two systems creates a coordination requirement between business stakeholders and application developers. | AF10: =_xlfn.CONCAT('1.3 IP Pairwise'!K130," ","-"," ",'1.3 IP Pairwise'!L130) -> L2 - Minor Impact | AG10: ='1.3 IP Pairwise'!M130 -> Issues associated with the EA smell may be observable in logs or low-priority events but do not affect system operation. These issues are resolved automatically through built-in mechanisms and do not require manual operational intervention. | AH10: ='1.3 IP Pairwise'!N130 -> Occasional errors related to the EA smell are recorded in system logs but are resolved through retry or fallback mechanisms, and services continue to operate without interruption or user impact.
B11: 3 | C11: Feature Envy | D11: 3 | E11: 3 | F11: 3 | G11: 2 | H11: 2 | I11: A localized design issue causing moderate refactoring effort, with limited scope and low impact on coordination and system reliability. | L11: =_xlfn.CONCAT('1.3 IP Pairwise'!K15," ","-"," ",'1.3 IP Pairwise'!L15) -> L3 - Multiple Systems (Limited Scope) | M11: ='1.3 IP Pairwise'!M15 -> Changes affect multiple applications or systems, requiring modifications to a specific type of architectural element within each system (e.g., interfaces or services). | N11: ='1.3 IP Pairwise'!N15 -> The CRM and ERP systems exchange customer data through a poorly designed integration interface. Resolving the issue requires modifying the integration interfaces in both CRM and ERP systems. | Q11: =_xlfn.CONCAT('1.3 IP Pairwise'!K44," ","-"," ",'1.3 IP Pairwise'!L44) -> L3 - Component Restructuring (Single System) | R11: ='1.3 IP Pairwise'!M44 -> Refactoring that reorganizes responsibilities between architectural components within the same system, modifying component interactions while preserving the overall system structure. | S11: ='1.3 IP Pairwise'!N44 -> Break Up Component, Extract Component, Merge Components | V11: =_xlfn.CONCAT('1.3 IP Pairwise'!K73," ","-"," ",'1.3 IP Pairwise'!L73) -> L3 - Moderate Constraint | W11: ='1.3 IP Pairwise'!M73 -> The EA smell introduces dependency-driven constraints between architectural elements. Changes to one architectural element require updates to directly dependent architectural elements (e.g., modifying an interface requires updating components that use that interface); however, the impact remains limited to a single level of dependency and does not propagate further. | X11: ='1.3 IP Pairwise'!N73 -> The CRM system exposes an interface consumed by the ERP system. Modifying the interface (e.g., changing required data fields) requires updating the ERP system to maintain compatibility, but no further elements are affected. | AA11: =_xlfn.CONCAT('1.3 IP Pairwise'!K102," ","-"," ",'1.3 IP Pairwise'!L102) -> L3 - Moderate Coordination Overhead | AB11: ='1.3 IP Pairwise'!M102 -> The EA-smell instance creates coordination dependencies across multiple stakeholder groups. | AC11: ='1.3 IP Pairwise'!N102 -> Duplicate functionality exists in the ERP and payroll systems for calculating timesheets. A business analyst decides that timesheet calculation should be performed only in the ERP system. Developers introduce an application interface for importing the timesheets, while the infrastructure team configures an automated job scheduler to execute the transfer between systems. The resulting dependencies create coordination requirements among business stakeholders, developers, and infrastructure teams. | AF11: =_xlfn.CONCAT('1.3 IP Pairwise'!K131," ","-"," ",'1.3 IP Pairwise'!L131) -> L3 - Moderate Impact | AG11: ='1.3 IP Pairwise'!M131 -> Failures associated with the EA smell cause a noticeable but localized disruption to system operation and require manual operational intervention to resolve. The impact remains confined to a single component or service and does not degrade business-critical capabilities. | AH11: ='1.3 IP Pairwise'!N131 -> An incident associated with the EA smell results in a localized disruption to a single component or service, requiring manual intervention (e.g., restart or correction), while business-critical capabilities continue to operate normally.
B12: 4 | C12: Stovepipe System | D12: 4 | E12: 4 | F12: 4 | G12: 3 | H12: 4 | I12: Siloed systems require substantial integration effort, limiting architectural flexibility and affecting operational consistency. | L12: =_xlfn.CONCAT('1.3 IP Pairwise'!K16," ","-"," ",'1.3 IP Pairwise'!L16) -> L4 - Multiple Systems (Broad Scope) | M12: ='1.3 IP Pairwise'!M16 -> Changes affect multiple applications or systems and require modifications to multiple types of architectural elements within each system (e.g., services, interfaces, and data structures). | N12: ='1.3 IP Pairwise'!N16 -> The CRM and ERP systems are tightly coupled through multiple interacting components and data exchanges. Resolving the issue requires modifying components, interfaces, and data structures in both systems. | Q12: =_xlfn.CONCAT('1.3 IP Pairwise'!K45," ","-"," ",'1.3 IP Pairwise'!L45) -> L4 - Architectural Reorganization | R12: ='1.3 IP Pairwise'!M45 -> Refactoring that reorganizes architectural relationships between systems, requiring changes to how components interact across system boundaries and altering integration structures. | S12: ='1.3 IP Pairwise'!N45 -> Move Component, Reorganization | V12: =_xlfn.CONCAT('1.3 IP Pairwise'!K74," ","-"," ",'1.3 IP Pairwise'!L74) -> L4 - Strong Constraint | W12: ='1.3 IP Pairwise'!M74 -> The EA smell introduces dependency-driven constraints such that architectural elements depend on each other in a chain. Changes to one architectural element require coordinated updates to directly dependent architectural elements, with the impact propagating across multiple levels of dependency. | X12: ='1.3 IP Pairwise'!N74 -> The CRM system exposes an interface consumed by the ERP system, which relies on specific data fields. The ERP system provides this data to the Reporting system. Modifying the CRM interface (e.g., changing required data fields) requires updating the ERP system, which then requires updates in the Reporting system, causing the change to propagate across multiple dependent elements. | AA12: =_xlfn.CONCAT('1.3 IP Pairwise'!K103," ","-"," ",'1.3 IP Pairwise'!L103) -> L4 - High Coordination Overhead | AB12: ='1.3 IP Pairwise'!M103 -> The EA-smell instance creates coordination dependencies across multiple stakeholder groups and requires recurring involvement of formal architectural governance bodies to align or approve changes affecting the architectural condition (e.g., architecture review boards). | AC12: ='1.3 IP Pairwise'!N103 -> An enterprise application relies on vendor-specific database features, creating vendor lock-in. Removing the dependency requires introducing a database abstraction layer to decouple the application from vendor-specific functionality. The architectural and technology dependencies involved create coordination requirements between developers, infrastructure teams, and enterprise architects and require review and approval through architectural governance. | AF12: =_xlfn.CONCAT('1.3 IP Pairwise'!K132," ","-"," ",'1.3 IP Pairwise'!L132) -> L4 - High Impact | AG12: ='1.3 IP Pairwise'!M132 -> Failures associated with the EA smell cause disruptions that degrade business-critical capabilities (e.g., slower performance, reduced functionality, or intermittent failures) while the system remains operational. Recovery requires substantial operational effort. | AH12: ='1.3 IP Pairwise'!N132 -> Incidents associated with the EA smell result in degraded performance of a business-critical capability (e.g., slower response times or limited functionality), requiring repeated operational intervention, while the service remains available.
B13: 5 | C13: Vendor Lock-In | D13: 4 | E13: 5 | F13: 5 | G13: 5 | H13: 4 | I13: Dependence on a specific vendor imposes severe constraints on technology evolution and requires high coordination despite manageable migration effort. | L13: =_xlfn.CONCAT('1.3 IP Pairwise'!K17," ","-"," ",'1.3 IP Pairwise'!L17) -> L5 - Enterprise-Wide Scope | M13: ='1.3 IP Pairwise'!M17 -> Changes affect multiple systems or applications and require modifications to shared or common architectural elements used across systems (e.g., shared data models, integration platforms, or core services). | N13: ='1.3 IP Pairwise'!N17 -> Customer information is stored in a shared data model used by CRM, ERP, and Marketing systems. Resolving the issue requires modifying the shared data model, affecting all dependent systems. | Q13: =_xlfn.CONCAT('1.3 IP Pairwise'!K46," ","-"," ",'1.3 IP Pairwise'!L46) -> L5 - Architectural Layer Restructuring | R13: ='1.3 IP Pairwise'!M46 -> Refactoring that introduces, removes, or fundamentally restructures architectural layers or abstraction structures, significantly altering the overall architecture. | S13: ='1.3 IP Pairwise'!N46 -> Isolation Layer, Move Service to Different Layer | V13: =_xlfn.CONCAT('1.3 IP Pairwise'!K75," ","-"," ",'1.3 IP Pairwise'!L75) -> L5 - Severe Constraint | W13: ='1.3 IP Pairwise'!M75 -> The EA smell introduces dependency-driven constraints centered around a shared architectural element that is used by multiple architectural elements. Changes to the shared architectural element require simultaneous coordination across all dependent architectural elements, preventing independent architectural evolution. Consequently, future architectural evolution may require restructuring or replacement of the shared architectural element. | X13: ='1.3 IP Pairwise'!N75 -> The CRM, ERP, and Reporting systems rely on a shared data model that defines common data fields. Modifying the shared data model (e.g., changing required data fields) requires simultaneous updates across all dependent systems, preventing independent modification and requiring restructuring of the shared data model. | AA13: =_xlfn.CONCAT('1.3 IP Pairwise'!K104," ","-"," ",'1.3 IP Pairwise'!L104) -> L5 - Strategic Coordination Overhead | AB13: ='1.3 IP Pairwise'!M104 -> The EA-smell instance creates coordination dependencies across multiple organizational domains and stakeholder groups and requires strategic decisions or alignment from enterprise leadership or program sponsors (e.g., CIO, steering committee). | AC13: ='1.3 IP Pairwise'!N104 -> Several enterprise applications rely on a vendor-specific database platform, creating strong vendor lock-in. Eliminating the dependency would require migrating multiple systems to an alternative platform and redesigning parts of the application landscape. The resulting cross-system dependencies create coordination requirements across multiple organizational domains and affect the enterprise architecture roadmap, requiring strategic alignment and decisions by enterprise leadership or program sponsors. | AF13: =_xlfn.CONCAT('1.3 IP Pairwise'!K133," ","-"," ",'1.3 IP Pairwise'!L133) -> L5 - Critical Impact | AG13: ='1.3 IP Pairwise'!M133 -> Failures associated with the EA smell cannot be restored through normal operational actions and result in sustained unavailability of business-critical capabilities. | AH13: ='1.3 IP Pairwise'!N133 -> Persistent incidents associated with the EA smell result in the sustained unavailability of a business-critical capability, and the system cannot be restored through standard operational actions, requiring architectural redesign.
B14: 6
B15: 7
B16: 8
B17: 9
B18: 10

Sheet 1.5 Results EA Smell Dashboard
A1: EA SMELL PRIORITISATION DASHBOARD
B5: 1 | C5: CRITERIA WEIGHTS (GLOBAL) User-input weights defining the importance of each criterion.
E33: Criterion | F33: Subcriterion | G33: Local Weight | H33: Global Weight
E34: Remediation Effort | G34: ='1.7 AHP Calculations'!$F$18 -> 0.5 | H34: =Table1[[#This Row],[Local Weight]] -> 0.5
F35: Scope | G35: ='1.7 AHP Calculations'!$D$60 -> 0.5 | H35: =Table1[[#This Row],[Local Weight]]*$G$34 -> 0.25
F36: Restructuring Complexity | G36: ='1.7 AHP Calculations'!$D$61 -> 0.5 | H36: =Table1[[#This Row],[Local Weight]]*$G$34 -> 0.25
E37: Impact | G37: ='1.7 AHP Calculations'!$F$19 -> 0.5 | H37: =Table1[[#This Row],[Local Weight]] -> 0.5
F38: Evolution Constraint | G38: ='1.7 AHP Calculations'!$D$62 -> 0.33333333 | H38: =Table1[[#This Row],[Local Weight]]*$G$37 -> 0.16666667
F39: Governance & Coordination Overhead | G39: ='1.7 AHP Calculations'!$D$63 -> 0.33333333 | H39: =Table1[[#This Row],[Local Weight]]*$G$37 -> 0.16666667
F40: Operational Reliability Impact | G40: ='1.7 AHP Calculations'!$D$64 -> 0.33333333 | H40: =Table1[[#This Row],[Local Weight]]*$G$37 -> 0.16666667
E42: After changing the input data, select Data → Refresh All to update the tables below.
B44: 2 | C44: EA SMELL RATINGS User-provided ratings for each EA smell across all criteria. | E44: Rating (Intensity Priority): Rating assigned on the 1–5 scale, with its corresponding AHP-derived priority shown in parentheses.
E46: EA Smell Instance | F46: Scope Rating / Intensity Priority | G46: Restructuring Complexity Rating / Intensity Priority | H46: Evolution Constraint Rating / Intensity Priority | I46: Governance Overhead Rating / Intensity Priority | J46: Operational Reliability Rating / Intensity Priority
E47: Cyclic Dependency | F47: 4 (0.2231) | G47: 4 (0.1963) | H47: 4 (0.4076) | I47: 3 (0.2044) | J47: 3 (0.1915)
E48: Feature Envy | F48: 3 (0.3426) | G48: 3 (0.4757) | H48: 3 (0.1596) | I48: 2 (0.1141) | J48: 2 (0.0875)
E49: Shared Persistency | F49: 5 (0.0855) | G49: 3 (0.4757) | H49: 5 (1.0000) | I49: 4 (0.5362) | J49: 4 (0.5423)
E50: Stovepipe System | F50: 4 (0.2231) | G50: 4 (0.1963) | H50: 4 (0.4076) | I50: 3 (0.2044) | J50: 4 (0.5423)
E51: Vendor Lock-In | F51: 4 (0.2231) | G51: 5 (0.0856) | H51: 5 (1.0000) | I51: 5 (1.0000) | J51: 4 (0.5423)
E52: (blank)
B64: 3 | C64: FINAL RESULTS Computed weighted scores used to rank EA smells. | E64: How to read the results: Total is the weighted score for each EA smell instance, based on its ratings across the subcriteria. Normalized Priority is the normalized Total, showing the relative priority of each EA smell. Priority values sum to 1 (100%) and determine the final ranking.
E66: Rank | F66: EA Smell Instance | G66: Weighted Score / Total | H66: Normalized Priority
E67: 1 | F67: Vendor Lock-In | G67: 0.50089603 | H67: 0.28007762
E68: 2 | F68: Shared Persistency | G68: 0.48673056 | H68: 0.27215696
E69: 3 | F69: Stovepipe System | G69: 0.29722902 | H69: 0.16619656
E70: 4 | F70: Feature Envy | G70: 0.26479366 | H70: 0.14806023
E71: 5 | F71: Cyclic Dependency | G71: 0.23876932 | H71: 0.13350863
F72: (blank)

Sheet 1.6 IP Calculations
B1: Scope | J1: Restructuring Complexity | L1: Restructuring Complexity | T1: Evolution Constraint | V1: Evolution Constraint | AE1: Gov. and Coordination Overhead | AG1: Gov. & Coord. Overhead | AO1: Operational Reliability Impact | AQ1: Operational Reliability Impact
B3: Pairwise Comparison Matrix | L3: Pairwise Comparison Matrix | V3: Pairwise Comparison Matrix | AG3: Pairwise Comparison Matrix | AQ3: Pairwise Comparison Matrix
B5: Level | C5: L1 | D5: L2 | E5: L3 | F5: L4 | G5: L5 | L5: Level | M5: L1 | N5: L2 | O5: L3 | P5: L4 | Q5: L5 | V5: Level | W5: L1 | X5: L2 | Y5: L3 | Z5: L4 | AA5: L5 | AG5: Level | AH5: L1 | AI5: L2 | AJ5: L3 | AK5: L4 | AL5: L5 | AQ5: Level | AR5: L1 | AS5: L2 | AT5: L3 | AU5: L4 | AV5: L5
B6: L1 | C6: 1 | D6: =IF('1.3 IP Pairwise'!$G$13="",NA(),'1.3 IP Pairwise'!$G$13) -> 2 | E6: =IF('1.3 IP Pairwise'!$G$14="",NA(),'1.3 IP Pairwise'!$G$14) -> 3 | F6: =IF('1.3 IP Pairwise'!$G$15="",NA(),'1.3 IP Pairwise'!$G$15) -> 5 | G6: =IF('1.3 IP Pairwise'!$G$16="",NA(),'1.3 IP Pairwise'!$G$16) -> 7 | L6: L1 | M6: 1 | N6: =IF('1.3 IP Pairwise'!$G$42="",NA(),'1.3 IP Pairwise'!$G$42) -> 2 | O6: =IF('1.3 IP Pairwise'!$G$43="",NA(),'1.3 IP Pairwise'!$G$43) -> 3 | P6: =IF('1.3 IP Pairwise'!$G$44="",NA(),'1.3 IP Pairwise'!$G$44) -> 5 | Q6: =IF('1.3 IP Pairwise'!$G$45="",NA(),'1.3 IP Pairwise'!$G$45) -> 7 | V6: L1 | W6: 1 | X6: =IF('1.3 IP Pairwise'!$G$71="",NA(),'1.3 IP Pairwise'!$G$71) -> 0.5 | Y6: =IF('1.3 IP Pairwise'!$G$72="",NA(),'1.3 IP Pairwise'!$G$72) -> 0.33333333 | Z6: =IF('1.3 IP Pairwise'!$G$73="",NA(),'1.3 IP Pairwise'!$G$73) -> 0.2 | AA6: =IF('1.3 IP Pairwise'!$G$74="",NA(),'1.3 IP Pairwise'!$G$74) -> 0.11111111 | AG6: L1 | AH6: 1 | AI6: =IF('1.3 IP Pairwise'!$G$100="",NA(),'1.3 IP Pairwise'!$G$100) -> 0.33333333 | AJ6: =IF('1.3 IP Pairwise'!$G$101="",NA(),'1.3 IP Pairwise'!$G$101) -> 0.2 | AK6: =IF('1.3 IP Pairwise'!$G$102="",NA(),'1.3 IP Pairwise'!$G$102) -> 0.14285714 | AL6: =IF('1.3 IP Pairwise'!$G$103="",NA(),'1.3 IP Pairwise'!$G$103) -> 0.11111111 | AQ6: L1 | AR6: 1 | AS6: =IF('1.3 IP Pairwise'!$G$129="",NA(),'1.3 IP Pairwise'!$G$129) -> 0.5 | AT6: =IF('1.3 IP Pairwise'!$G$130="",NA(),'1.3 IP Pairwise'!$G$130) -> 0.2 | AU6: =IF('1.3 IP Pairwise'!$G$131="",NA(),'1.3 IP Pairwise'!$G$131) -> 0.14285714 | AV6: =IF('1.3 IP Pairwise'!$G$132="",NA(),'1.3 IP Pairwise'!$G$132) -> 0.11111111
B7: L2 | C7: =IFERROR(1/D6,NA()) -> 0.5 | D7: 1 | E7: =IF('1.3 IP Pairwise'!$G$17="",NA(),'1.3 IP Pairwise'!$G$17) -> 3 | F7: =IF('1.3 IP Pairwise'!$G$18="",NA(),'1.3 IP Pairwise'!$G$18) -> 5 | G7: =IF('1.3 IP Pairwise'!$G$19="",NA(),'1.3 IP Pairwise'!$G$19) -> 7 | L7: L2 | M7: =IFERROR(1/N6,NA()) -> 0.5 | N7: 1 | O7: =IF('1.3 IP Pairwise'!$G$46="",NA(),'1.3 IP Pairwise'!$G$46) -> 2 | P7: =IF('1.3 IP Pairwise'!$G$47="",NA(),'1.3 IP Pairwise'!$G$47) -> 5 | Q7: =IF('1.3 IP Pairwise'!$G$48="",NA(),'1.3 IP Pairwise'!$G$48) -> 7 | V7: L2 | W7: =IFERROR(1/X6,NA()) -> 2 | X7: 1 | Y7: =IF('1.3 IP Pairwise'!$G$75="",NA(),'1.3 IP Pairwise'!$G$75) -> 0.33333333 | Z7: =IF('1.3 IP Pairwise'!$G$76="",NA(),'1.3 IP Pairwise'!$G$76) -> 0.2 | AA7: =IF('1.3 IP Pairwise'!$G$77="",NA(),'1.3 IP Pairwise'!$G$77) -> 0.14285714 | AG7: L2 | AH7: =IFERROR(1/AI6,NA()) -> 3 | AI7: 1 | AJ7: =IF('1.3 IP Pairwise'!$G$104="",NA(),'1.3 IP Pairwise'!$G$104) -> 0.33333333 | AK7: =IF('1.3 IP Pairwise'!$G$105="",NA(),'1.3 IP Pairwise'!$G$105) -> 0.2 | AL7: =IF('1.3 IP Pairwise'!$G$106="",NA(),'1.3 IP Pairwise'!$G$106) -> 0.14285714 | AQ7: L2 | AR7: =IFERROR(1/AS6,NA()) -> 2 | AS7: 1 | AT7: =IF('1.3 IP Pairwise'!$G$133="",NA(),'1.3 IP Pairwise'!$G$133) -> 0.33333333 | AU7: =IF('1.3 IP Pairwise'!$G$134="",NA(),'1.3 IP Pairwise'!$G$134) -> 0.14285714 | AV7: =IF('1.3 IP Pairwise'!$G$135="",NA(),'1.3 IP Pairwise'!$G$135) -> 0.11111111
B8: L3 | C8: =IFERROR(1/E6,NA()) -> 0.33333333 | D8: =IFERROR(1/E7,NA()) -> 0.33333333 | E8: 1 | F8: =IF('1.3 IP Pairwise'!$G$20="",NA(),'1.3 IP Pairwise'!$G$20) -> 2 | G8: =IF('1.3 IP Pairwise'!$G$21="",NA(),'1.3 IP Pairwise'!$G$21) -> 5 | L8: L3 | M8: =IFERROR(1/O6,NA()) -> 0.33333333 | N8: =IFERROR(1/O7,NA()) -> 0.5 | O8: 1 | P8: =IF('1.3 IP Pairwise'!$G$49="",NA(),'1.3 IP Pairwise'!$G$49) -> 5 | Q8: =IF('1.3 IP Pairwise'!$G$50="",NA(),'1.3 IP Pairwise'!$G$50) -> 5 | V8: L3 | W8: =IFERROR(1/Y6,NA()) -> 3 | X8: =IFERROR(1/Y7,NA()) -> 3 | Y8: 1 | Z8: =IF('1.3 IP Pairwise'!$G$78="",NA(),'1.3 IP Pairwise'!$G$78) -> 0.2 | AA8: =IF('1.3 IP Pairwise'!$G$79="",NA(),'1.3 IP Pairwise'!$G$79) -> 0.14285714 | AG8: L3 | AH8: =IFERROR(1/AJ6,NA()) -> 5 | AI8: =IFERROR(1/AJ7,NA()) -> 3 | AJ8: 1 | AK8: =IF('1.3 IP Pairwise'!$G$107="",NA(),'1.3 IP Pairwise'!$G$107) -> 0.2 | AL8: =IF('1.3 IP Pairwise'!$G$108="",NA(),'1.3 IP Pairwise'!$G$108) -> 0.14285714 | AQ8: L3 | AR8: =IFERROR(1/AT6,NA()) -> 5 | AS8: =IFERROR(1/AT7,NA()) -> 3 | AT8: 1 | AU8: =IF('1.3 IP Pairwise'!$G$136="",NA(),'1.3 IP Pairwise'!$G$136) -> 0.2 | AV8: =IF('1.3 IP Pairwise'!$G$137="",NA(),'1.3 IP Pairwise'!$G$137) -> 0.14285714
B9: L4 | C9: =IFERROR(1/F6,NA()) -> 0.2 | D9: =IFERROR(1/F7,NA()) -> 0.2 | E9: =IFERROR(1/F8,NA()) -> 0.5 | F9: 1 | G9: =IF('1.3 IP Pairwise'!$G$22="",NA(),'1.3 IP Pairwise'!$G$22) -> 5 | L9: L4 | M9: =IFERROR(1/P6,NA()) -> 0.2 | N9: =IFERROR(1/P7,NA()) -> 0.2 | O9: =IFERROR(1/P8,NA()) -> 0.2 | P9: 1 | Q9: =IF('1.3 IP Pairwise'!$G$51="",NA(),'1.3 IP Pairwise'!$G$51) -> 5 | V9: L4 | W9: =IFERROR(1/Z6,NA()) -> 5 | X9: =IFERROR(1/Z7,NA()) -> 5 | Y9: =IFERROR(1/Z8,NA()) -> 5 | Z9: 1 | AA9: =IF('1.3 IP Pairwise'!$G$80="",NA(),'1.3 IP Pairwise'!$G$80) -> 0.2 | AG9: L4 | AH9: =IFERROR(1/AK6,NA()) -> 7 | AI9: =IFERROR(1/AK7,NA()) -> 5 | AJ9: =IFERROR(1/AK8,NA()) -> 5 | AK9: 1 | AL9: =IF('1.3 IP Pairwise'!$G$109="",NA(),'1.3 IP Pairwise'!$G$109) -> 0.33333333 | AQ9: L4 | AR9: =IFERROR(1/AU6,NA()) -> 7 | AS9: =IFERROR(1/AU7,NA()) -> 7 | AT9: =IFERROR(1/AU8,NA()) -> 5 | AU9: 1 | AV9: =IF('1.3 IP Pairwise'!$G$138="",NA(),'1.3 IP Pairwise'!$G$138) -> 0.33333333
B10: L5 | C10: =IFERROR(1/G6,NA()) -> 0.14285714 | D10: =IFERROR(1/G7,NA()) -> 0.14285714 | E10: =IFERROR(1/G8,NA()) -> 0.2 | F10: =IFERROR(1/G9,NA()) -> 0.2 | G10: 1 | L10: L5 | M10: =IFERROR(1/Q6,NA()) -> 0.14285714 | N10: =IFERROR(1/Q7,NA()) -> 0.14285714 | O10: =IFERROR(1/Q8,NA()) -> 0.2 | P10: =IFERROR(1/Q9,NA()) -> 0.2 | Q10: 1 | V10: L5 | W10: =IFERROR(1/AA6,NA()) -> 9 | X10: =IFERROR(1/AA7,NA()) -> 7 | Y10: =IFERROR(1/AA8,NA()) -> 7 | Z10: =IFERROR(1/AA9,NA()) -> 5 | AA10: 1 | AG10: L5 | AH10: =IFERROR(1/AL6,NA()) -> 9 | AI10: =IFERROR(1/AL7,NA()) -> 7 | AJ10: =IFERROR(1/AL8,NA()) -> 7 | AK10: =IFERROR(1/AL9,NA()) -> 3 | AL10: 1 | AQ10: L5 | AR10: =IFERROR(1/AV6,NA()) -> 9 | AS10: =IFERROR(1/AV7,NA()) -> 9 | AT10: =IFERROR(1/AV8,NA()) -> 7 | AU10: =IFERROR(1/AV9,NA()) -> 3 | AV10: 1
B11: col sum | C11: =SUM(C6:C10) -> 2.1761905 | D11: =SUM(D6:D10) -> 3.6761905 | E11: =SUM(E6:E10) -> 7.7 | F11: =SUM(F6:F10) -> 13.2 | G11: =SUM(G6:G10) -> 25 | L11: col sum | M11: =SUM(M6:M10) -> 2.1761905 | N11: =SUM(N6:N10) -> 3.8428571 | O11: =SUM(O6:O10) -> 6.4 | P11: =SUM(P6:P10) -> 16.2 | Q11: =SUM(Q6:Q10) -> 25 | V11: col sum | W11: =SUM(W6:W10) -> 20 | X11: =SUM(X6:X10) -> 16.5 | Y11: =SUM(Y6:Y10) -> 13.666667 | Z11: =SUM(Z6:Z10) -> 6.6 | AA11: =SUM(AA6:AA10) -> 1.5968254 | AG11: col sum | AH11: =SUM(AH6:AH10) -> 25 | AI11: =SUM(AI6:AI10) -> 16.333333 | AJ11: =SUM(AJ6:AJ10) -> 13.533333 | AK11: =SUM(AK6:AK10) -> 4.5428571 | AL11: =SUM(AL6:AL10) -> 1.7301587 | AQ11: col sum | AR11: =SUM(AR6:AR10) -> 24 | AS11: =SUM(AS6:AS10) -> 20.5 | AT11: =SUM(AT6:AT10) -> 13.533333 | AU11: =SUM(AU6:AU10) -> 4.4857143 | AV11: =SUM(AV6:AV10) -> 1.6984127
B13: Normalized Matrix | L13: Normalized Matrix | V13: Normalized Matrix | AG13: Normalized Matrix | AQ13: Normalized Matrix
B15: Level | C15: L1 | D15: L2 | E15: L3 | F15: L4 | G15: L5 | L15: Level | M15: L1 | N15: L2 | O15: L3 | P15: L4 | Q15: L5 | V15: Level | W15: L1 | X15: L2 | Y15: L3 | Z15: L4 | AA15: L5 | AG15: Level | AH15: L1 | AI15: L2 | AJ15: L3 | AK15: L4 | AL15: L5 | AQ15: Level | AR15: L1 | AS15: L2 | AT15: L3 | AU15: L4 | AV15: L5
B16: L1 | C16: =$C6/$C$11 -> 0.4595186 | D16: =$D6/$D$11 -> 0.54404145 | E16: =$E6/$E$11 -> 0.38961039 | F16: =$F6/$F$11 -> 0.37878788 | G16: =$G6/$G$11 -> 0.28 | L16: L1 | M16: =$M6/$M$11 -> 0.4595186 | N16: =$N6/$N$11 -> 0.5204461 | O16: =$O6/$O$11 -> 0.46875 | P16: =$P6/$P$11 -> 0.30864198 | Q16: =$Q6/$Q$11 -> 0.28 | V16: L1 | W16: =$W6/$W$11 -> 0.05 | X16: =$X6/$X$11 -> 0.03030303 | Y16: =$Y6/$Y$11 -> 0.024390244 | Z16: =$Z6/$Z$11 -> 0.03030303 | AA16: =$AA6/$AA$11 -> 0.069582505 | AG16: L1 | AH16: =$AH6/$AH$11 -> 0.04 | AI16: =$AI6/$AI$11 -> 0.020408163 | AJ16: =$AJ6/$AJ$11 -> 0.014778325 | AK16: =$AK6/$AK$11 -> 0.031446541 | AL16: =$AL6/$AL$11 -> 0.064220183 | AQ16: L1 | AR16: =$AR6/$AR$11 -> 0.041666667 | AS16: =$AS6/$AS$11 -> 0.024390244 | AT16: =$AT6/$AT$11 -> 0.014778325 | AU16: =$AU6/$AU$11 -> 0.031847134 | AV16: =$AV6/$AV$11 -> 0.065420561
B17: L2 | C17: =$C7/$C$11 -> 0.2297593 | D17: =$D7/$D$11 -> 0.27202073 | E17: =$E7/$E$11 -> 0.38961039 | F17: =$F7/$F$11 -> 0.37878788 | G17: =$G7/$G$11 -> 0.28 | L17: L2 | M17: =$M7/$M$11 -> 0.2297593 | N17: =$N7/$N$11 -> 0.26022305 | O17: =$O7/$O$11 -> 0.3125 | P17: =$P7/$P$11 -> 0.30864198 | Q17: =$Q7/$Q$11 -> 0.28 | V17: L2 | W17: =$W7/$W$11 -> 0.1 | X17: =$X7/$X$11 -> 0.060606061 | Y17: =$Y7/$Y$11 -> 0.024390244 | Z17: =$Z7/$Z$11 -> 0.03030303 | AA17: =$AA7/$AA$11 -> 0.089463221 | AG17: L2 | AH17: =$AH7/$AH$11 -> 0.12 | AI17: =$AI7/$AI$11 -> 0.06122449 | AJ17: =$AJ7/$AJ$11 -> 0.024630542 | AK17: =$AK7/$AK$11 -> 0.044025157 | AL17: =$AL7/$AL$11 -> 0.082568807 | AQ17: L2 | AR17: =$AR7/$AR$11 -> 0.083333333 | AS17: =$AS7/$AS$11 -> 0.048780488 | AT17: =$AT7/$AT$11 -> 0.024630542 | AU17: =$AU7/$AU$11 -> 0.031847134 | AV17: =$AV7/$AV$11 -> 0.065420561
B18: L3 | C18: =$C8/$C$11 -> 0.15317287 | D18: =$D8/$D$11 -> 0.090673575 | E18: =$E8/$E$11 -> 0.12987013 | F18: =$F8/$F$11 -> 0.15151515 | G18: =$G8/$G$11 -> 0.2 | L18: L3 | M18: =$M8/$M$11 -> 0.15317287 | N18: =$N8/$N$11 -> 0.13011152 | O18: =$O8/$O$11 -> 0.15625 | P18: =$P8/$P$11 -> 0.30864198 | Q18: =$Q8/$Q$11 -> 0.2 | V18: L3 | W18: =$W8/$W$11 -> 0.15 | X18: =$X8/$X$11 -> 0.18181818 | Y18: =$Y8/$Y$11 -> 0.073170732 | Z18: =$Z8/$Z$11 -> 0.03030303 | AA18: =$AA8/$AA$11 -> 0.089463221 | AG18: L3 | AH18: =$AH8/$AH$11 -> 0.2 | AI18: =$AI8/$AI$11 -> 0.18367347 | AJ18: =$AJ8/$AJ$11 -> 0.073891626 | AK18: =$AK8/$AK$11 -> 0.044025157 | AL18: =$AL8/$AL$11 -> 0.082568807 | AQ18: L3 | AR18: =$AR8/$AR$11 -> 0.20833333 | AS18: =$AS8/$AS$11 -> 0.14634146 | AT18: =$AT8/$AT$11 -> 0.073891626 | AU18: =$AU8/$AU$11 -> 0.044585987 | AV18: =$AV8/$AV$11 -> 0.08411215
B19: L4 | C19: =$C9/$C$11 -> 0.09190372 | D19: =$D9/$D$11 -> 0.054404145 | E19: =$E9/$E$11 -> 0.064935065 | F19: =$F9/$F$11 -> 0.075757576 | G19: =$G9/$G$11 -> 0.2 | L19: L4 | M19: =$M9/$M$11 -> 0.09190372 | N19: =$N9/$N$11 -> 0.05204461 | O19: =$O9/$O$11 -> 0.03125 | P19: =$P9/$P$11 -> 0.061728395 | Q19: =$Q9/$Q$11 -> 0.2 | V19: L4 | W19: =$W9/$W$11 -> 0.25 | X19: =$X9/$X$11 -> 0.3030303 | Y19: =$Y9/$Y$11 -> 0.36585366 | Z19: =$Z9/$Z$11 -> 0.15151515 | AA19: =$AA9/$AA$11 -> 0.12524851 | AG19: L4 | AH19: =$AH9/$AH$11 -> 0.28 | AI19: =$AI9/$AI$11 -> 0.30612245 | AJ19: =$AJ9/$AJ$11 -> 0.36945813 | AK19: =$AK9/$AK$11 -> 0.22012579 | AL19: =$AL9/$AL$11 -> 0.19266055 | AQ19: L4 | AR19: =$AR9/$AR$11 -> 0.29166667 | AS19: =$AS9/$AS$11 -> 0.34146341 | AT19: =$AT9/$AT$11 -> 0.36945813 | AU19: =$AU9/$AU$11 -> 0.22292994 | AV19: =$AV9/$AV$11 -> 0.19626168
B20: L5 | C20: =$C10/$C$11 -> 0.065645514 | D20: =$D10/$D$11 -> 0.038860104 | E20: =$E10/$E$11 -> 0.025974026 | F20: =$F10/$F$11 -> 0.015151515 | G20: =$G10/$G$11 -> 0.04 | L20: L5 | M20: =$M10/$M$11 -> 0.065645514 | N20: =$N10/$N$11 -> 0.037174721 | O20: =$O10/$O$11 -> 0.03125 | P20: =$P10/$P$11 -> 0.012345679 | Q20: =$Q10/$Q$11 -> 0.04 | V20: L5 | W20: =$W10/$W$11 -> 0.45 | X20: =$X10/$X$11 -> 0.42424242 | Y20: =$Y10/$Y$11 -> 0.51219512 | Z20: =$Z10/$Z$11 -> 0.75757576 | AA20: =$AA10/$AA$11 -> 0.62624254 | AG20: L5 | AH20: =$AH10/$AH$11 -> 0.36 | AI20: =$AI10/$AI$11 -> 0.42857143 | AJ20: =$AJ10/$AJ$11 -> 0.51724138 | AK20: =$AK10/$AK$11 -> 0.66037736 | AL20: =$AL10/$AL$11 -> 0.57798165 | AQ20: L5 | AR20: =$AR10/$AR$11 -> 0.375 | AS20: =$AS10/$AS$11 -> 0.43902439 | AT20: =$AT10/$AT$11 -> 0.51724138 | AU20: =$AU10/$AU$11 -> 0.66878981 | AV20: =$AV10/$AV$11 -> 0.58878505
B21: col sum | C21: =SUM(C16:C20) -> 1 | D21: =SUM(D16:D20) -> 1 | E21: =SUM(E16:E20) -> 1 | F21: =SUM(F16:F20) -> 1 | G21: =SUM(G16:G20) -> 1 | L21: col sum | M21: =SUM(M16:M20) -> 1 | N21: =SUM(N16:N20) -> 1 | O21: =SUM(O16:O20) -> 1 | P21: =SUM(P16:P20) -> 1 | Q21: =SUM(Q16:Q20) -> 1 | V21: col sum | W21: =SUM(W16:W20) -> 1 | X21: =SUM(X16:X20) -> 1 | Y21: =SUM(Y16:Y20) -> 1 | Z21: =SUM(Z16:Z20) -> 1 | AA21: =SUM(AA16:AA20) -> 1 | AG21: col sum | AH21: =SUM(AH16:AH20) -> 1 | AI21: =SUM(AI16:AI20) -> 1 | AJ21: =SUM(AJ16:AJ20) -> 1 | AK21: =SUM(AK16:AK20) -> 1 | AL21: =SUM(AL16:AL20) -> 1 | AQ21: col sum | AR21: =SUM(AR16:AR20) -> 1 | AS21: =SUM(AS16:AS20) -> 1 | AT21: =SUM(AT16:AT20) -> 1 | AU21: =SUM(AU16:AU20) -> 1 | AV21: =SUM(AV16:AV20) -> 1
B23: Priority Vector | L23: Priority Vector | V23: Priority Vector | AG23: Priority Vector | AQ23: Priority Vector
B25: Level | C25: Normalized Priority | D25: Idealized Priority | L25: Level | M25: Normalized Priority | N25: Idealized Priority | V25: Level | W25: Normalized Priority | X25: Idealized Priority | AG25: Level | AH25: Normalized Priority | AI25: Idealized Priority | AQ25: Level | AR25: Normalized Priority | AS25: Idealized Priority
B26: L1 | C26: {=_xlfn.LET(_xlpm.A,$C$6:$G$10,_xlpm.v0,_xlfn.SEQUENCE(5,,0.2,0),_xlpm.v,_xlfn.REDUCE(_xlpm.v0,_xlfn.SEQUENCE(50),_xlfn.LAMBDA(_xlpm.x,_xlpm.k,_xlfn.LET(_xlpm.y,MMULT(_xlpm.A,_xlpm.x),_xlpm.y/SUM(_xlpm.y)))),_xlpm.v)} -> 0.41463319 | D26: =$C26/MAX($C$26:$C$30) -> 1 | L26: L1 | M26: {=_xlfn.LET(_xlpm.A,$M$6:$Q$10,_xlpm.v0,_xlfn.SEQUENCE(5,,0.2,0),_xlpm.v,_xlfn.REDUCE(_xlpm.v0,_xlfn.SEQUENCE(50),_xlfn.LAMBDA(_xlpm.x,_xlpm.k,_xlfn.LET(_xlpm.y,MMULT(_xlpm.A,_xlpm.x),_xlpm.y/SUM(_xlpm.y)))),_xlpm.v)} -> 0.4084253 | N26: =$M26/MAX($M$26:$M$30) -> 1 | V26: L1 | W26: {=_xlfn.LET(_xlpm.A,$W$6:$AA$10,_xlpm.v0,_xlfn.SEQUENCE(5,,0.2,0),_xlpm.v,_xlfn.REDUCE(_xlpm.v0,_xlfn.SEQUENCE(50),_xlfn.LAMBDA(_xlpm.x,_xlpm.k,_xlfn.LET(_xlpm.y,MMULT(_xlpm.A,_xlpm.x),_xlpm.y/SUM(_xlpm.y)))),_xlpm.v)} -> 0.038443546 | X26: =$W26/MAX($W$26:$W$30) -> 0.066383716 | AG26: L1 | AH26: {=_xlfn.LET(_xlpm.A,$AH$6:$AL$10,_xlpm.v0,_xlfn.SEQUENCE(5,,0.2,0),_xlpm.v,_xlfn.REDUCE(_xlpm.v0,_xlfn.SEQUENCE(50),_xlfn.LAMBDA(_xlpm.x,_xlpm.k,_xlfn.LET(_xlpm.y,MMULT(_xlpm.A,_xlpm.x),_xlpm.y/SUM(_xlpm.y)))),_xlpm.v)} -> 0.031738514 | AI26: =$AH26/MAX($AH$26:$AH$30) -> 0.060797762 | AQ26: L1 | AR26: {=_xlfn.LET(_xlpm.A,$AR$6:$AV$10,_xlpm.v0,_xlfn.SEQUENCE(5,,0.2,0),_xlpm.v,_xlfn.REDUCE(_xlpm.v0,_xlfn.SEQUENCE(50),_xlfn.LAMBDA(_xlpm.x,_xlpm.k,_xlfn.LET(_xlpm.y,MMULT(_xlpm.A,_xlpm.x),_xlpm.y/SUM(_xlpm.y)))),_xlpm.v)} -> 0.033262388 | AS26: =$AR26/MAX($AR$26:$AR$30) -> 0.062663215
B27: L2 | C27: 0.31533 | D27: =$C27/MAX($C$26:$C$30) -> 0.76050351 | L27: L2 | M27: 0.28213589 | N27: =$M27/MAX($M$26:$M$30) -> 0.69078947 | V27: L2 | W27: 0.053948217 | X27: =$W27/MAX($W$26:$W$30) -> 0.09315694 | AG27: L2 | AH27: 0.05958952 | AI27: =$AH27/MAX($AH$26:$AH$30) -> 0.11414868 | AQ27: L2 | AR27: 0.046429752 | AS27: =$AR27/MAX($AR$26:$AR$30) -> 0.087469293
B28: L3 | C28: 0.14206794 | D28: =$C28/MAX($C$26:$C$30) -> 0.34263524 | L28: L3 | M28: 0.19430053 | N28: =$M28/MAX($M$26:$M$30) -> 0.47573088 | V28: L3 | W28: 0.092423133 | X28: =$W28/MAX($W$26:$W$30) -> 0.15959483 | AG28: L3 | AH28: 0.10671307 | AI28: =$AH28/MAX($AH$26:$AH$30) -> 0.20441776 | AQ28: L3 | AR28: 0.10165457 | AS28: =$AR28/MAX($AR$26:$AR$30) -> 0.19150767
B29: L4 | C29: 0.092503293 | D29: =$C29/MAX($C$26:$C$30) -> 0.22309669 | L29: L4 | M29: 0.080159319 | N29: =$M29/MAX($M$26:$M$30) -> 0.19626433 | V29: L4 | W29: 0.23607402 | X29: =$W29/MAX($W$26:$W$30) -> 0.40764893 | AG29: L4 | AH29: 0.27992464 | AI29: =$AH29/MAX($AH$26:$AH$30) -> 0.53621892 | AQ29: L4 | AR29: 0.28784127 | AS29: =$AR29/MAX($AR$26:$AR$30) -> 0.54226592
B30: L5 | C30: 0.035465574 | D30: =$C30/MAX($C$26:$C$30) -> 0.085534816 | L30: L5 | M30: 0.034978962 | N30: =$M30/MAX($M$26:$M$30) -> 0.085643476 | V30: L5 | W30: 0.57911109 | X30: =$W30/MAX($W$26:$W$30) -> 1 | AG30: L5 | AH30: 0.52203425 | AI30: =$AH30/MAX($AH$26:$AH$30) -> 1 | AQ30: L5 | AR30: 0.53081202 | AS30: =$AR30/MAX($AR$26:$AR$30) -> 1
B32: AHP Consistency Calculations | L32: AHP Consistency Calculations | V32: AHP Consistency Calculations | AG32: AHP Consistency Calculations | AQ32: AHP Consistency Calculations
B34: Level | C34: L1 | D34: L2 | E34: L3 | F34: L4 | G34: L5 | H34: SUM | L34: Level | M34: L1 | N34: L2 | O34: L3 | P34: L4 | Q34: L5 | R34: SUM | V34: Level | W34: L1 | X34: L2 | Y34: L3 | Z34: L4 | AA34: L5 | AB34: SUM | AG34: Level | AH34: L1 | AI34: L2 | AJ34: L3 | AK34: L4 | AL34: L5 | AM34: SUM | AQ34: Level | AR34: L1 | AS34: L2 | AT34: L3 | AU34: L4 | AV34: L5 | AW34: SUM
B35: L1 | C35: =$C6*$C$26 -> 0.41463319 | D35: =$D6*$C$27 -> 0.63066 | E35: =$E6*$C$28 -> 0.42620383 | F35: =$F6*$C$29 -> 0.46251646 | G35: =$G6*$C$30 -> 0.24825902 | H35: =SUM(C35:G35) -> 2.1822725 | L35: L1 | M35: =$M6*$M$26 -> 0.4084253 | N35: =$N6*$M$27 -> 0.56427179 | O35: =$O6*$M$28 -> 0.58290158 | P35: =$P6*$M$29 -> 0.4007966 | Q35: =$Q6*$M$30 -> 0.24485274 | R35: =SUM(M35:Q35) -> 2.201248 | V35: L1 | W35: =$W6*$W$26 -> 0.038443546 | X35: =$X6*$W$27 -> 0.026974108 | Y35: =$Y6*$W$28 -> 0.030807711 | Z35: =$Z6*$W$29 -> 0.047214803 | AA35: =$AA6*$W$30 -> 0.064345677 | AB35: =SUM(W35:AA35) -> 0.20778585 | AG35: L1 | AH35: =$AH6*$AH$26 -> 0.031738514 | AI35: =$AI6*$AH$27 -> 0.019863173 | AJ35: =$AJ6*$AH$28 -> 0.021342615 | AK35: =$AK6*$AH$29 -> 0.039989235 | AL35: =$AL6*$AH$30 -> 0.058003806 | AM35: =SUM(AH35:AL35) -> 0.17093734 | AQ35: L1 | AR35: =$AR6*$AR$26 -> 0.033262388 | AS35: =$AS6*$AR$27 -> 0.023214876 | AT35: =$AT6*$AR$28 -> 0.020330914 | AU35: =$AU6*$AR$29 -> 0.041120181 | AV35: =$AV6*$AR$30 -> 0.058979113 | AW35: =SUM(AR35:AV35) -> 0.17690747
B36: L2 | C36: =$C7*$C$26 -> 0.2073166 | D36: =$D7*$C$27 -> 0.31533 | E36: =$E7*$C$28 -> 0.42620383 | F36: =$F7*$C$29 -> 0.46251646 | G36: =$G7*$C$30 -> 0.24825902 | H36: =SUM(C36:G36) -> 1.6596259 | L36: L2 | M36: =$M7*$M$26 -> 0.20421265 | N36: =$N7*$M$27 -> 0.28213589 | O36: =$O7*$M$28 -> 0.38860105 | P36: =$P7*$M$29 -> 0.4007966 | Q36: =$Q7*$M$30 -> 0.24485274 | R36: =SUM(M36:Q36) -> 1.5205989 | V36: L2 | W36: =$W7*$W$26 -> 0.076887092 | X36: =$X7*$W$27 -> 0.053948217 | Y36: =$Y7*$W$28 -> 0.030807711 | Z36: =$Z7*$W$29 -> 0.047214803 | AA36: =$AA7*$W$30 -> 0.082730156 | AB36: =SUM(W36:AA36) -> 0.29158798 | AG36: L2 | AH36: =$AH7*$AH$26 -> 0.095215542 | AI36: =$AI7*$AH$27 -> 0.05958952 | AJ36: =$AJ7*$AH$28 -> 0.035571024 | AK36: =$AK7*$AH$29 -> 0.055984929 | AL36: =$AL7*$AH$30 -> 0.074576321 | AM36: =SUM(AH36:AL36) -> 0.32093734 | AQ36: L2 | AR36: =$AR7*$AR$26 -> 0.066524776 | AS36: =$AS7*$AR$27 -> 0.046429752 | AT36: =$AT7*$AR$28 -> 0.033884857 | AU36: =$AU7*$AR$29 -> 0.041120181 | AV36: =$AV7*$AR$30 -> 0.058979113 | AW36: =SUM(AR36:AV36) -> 0.24693868
B37: L3 | C37: =$C8*$C$26 -> 0.13821106 | D37: =$D8*$C$27 -> 0.10511 | E37: =$E8*$C$28 -> 0.14206794 | F37: =$F8*$C$29 -> 0.18500659 | G37: =$G8*$C$30 -> 0.17732787 | H37: =SUM(C37:G37) -> 0.74772346 | L37: L3 | M37: =$M8*$M$26 -> 0.13614177 | N37: =$N8*$M$27 -> 0.14106795 | O37: =$O8*$M$28 -> 0.19430053 | P37: =$P8*$M$29 -> 0.4007966 | Q37: =$Q8*$M$30 -> 0.17489481 | R37: =SUM(M37:Q37) -> 1.0472016 | V37: L3 | W37: =$W8*$W$26 -> 0.11533064 | X37: =$X8*$W$27 -> 0.16184465 | Y37: =$Y8*$W$28 -> 0.092423133 | Z37: =$Z8*$W$29 -> 0.047214803 | AA37: =$AA8*$W$30 -> 0.082730156 | AB37: =SUM(W37:AA37) -> 0.49954338 | AG37: L3 | AH37: =$AH8*$AH$26 -> 0.15869257 | AI37: =$AI8*$AH$27 -> 0.17876856 | AJ37: =$AJ8*$AH$28 -> 0.10671307 | AK37: =$AK8*$AH$29 -> 0.055984929 | AL37: =$AL8*$AH$30 -> 0.074576321 | AM37: =SUM(AH37:AL37) -> 0.57473545 | AQ37: L3 | AR37: =$AR8*$AR$26 -> 0.16631194 | AS37: =$AS8*$AR$27 -> 0.13928926 | AT37: =$AT8*$AR$28 -> 0.10165457 | AU37: =$AU8*$AR$29 -> 0.057568254 | AV37: =$AV8*$AR$30 -> 0.075830289 | AW37: =SUM(AR37:AV37) -> 0.54065431
B38: L4 | C38: =$C9*$C$26 -> 0.082926638 | D38: =$D9*$C$27 -> 0.063066 | E38: =$E9*$C$28 -> 0.071033971 | F38: =$F9*$C$29 -> 0.092503293 | G38: =$G9*$C$30 -> 0.17732787 | H38: =SUM(C38:G38) -> 0.48685777 | L38: L4 | M38: =$M9*$M$26 -> 0.08168506 | N38: =$N9*$M$27 -> 0.056427179 | O38: =$O9*$M$28 -> 0.038860105 | P38: =$P9*$M$29 -> 0.080159319 | Q38: =$Q9*$M$30 -> 0.17489481 | R38: =SUM(M38:Q38) -> 0.43202647 | V38: L4 | W38: =$W9*$W$26 -> 0.19221773 | X38: =$X9*$W$27 -> 0.26974108 | Y38: =$Y9*$W$28 -> 0.46211567 | Z38: =$Z9*$W$29 -> 0.23607402 | AA38: =$AA9*$W$30 -> 0.11582222 | AB38: =SUM(W38:AA38) -> 1.2759707 | AG38: L4 | AH38: =$AH9*$AH$26 -> 0.2221696 | AI38: =$AI9*$AH$27 -> 0.2979476 | AJ38: =$AJ9*$AH$28 -> 0.53356537 | AK38: =$AK9*$AH$29 -> 0.27992464 | AL38: =$AL9*$AH$30 -> 0.17401142 | AM38: =SUM(AH38:AL38) -> 1.5076186 | AQ38: L4 | AR38: =$AR9*$AR$26 -> 0.23283671 | AS38: =$AS9*$AR$27 -> 0.32500827 | AT38: =$AT9*$AR$28 -> 0.50827286 | AU38: =$AU9*$AR$29 -> 0.28784127 | AV38: =$AV9*$AR$30 -> 0.17693734 | AW38: =SUM(AR38:AV38) -> 1.5308964
B39: L5 | C39: =$C10*$C$26 -> 0.059233313 | D39: =$D10*$C$27 -> 0.045047143 | E39: =$E10*$C$28 -> 0.028413589 | F39: =$F10*$C$29 -> 0.018500659 | G39: =$G10*$C$30 -> 0.035465574 | H39: =SUM(C39:G39) -> 0.18666028 | L39: L5 | M39: =$M10*$M$26 -> 0.058346471 | N39: =$N10*$M$27 -> 0.040305128 | O39: =$O10*$M$28 -> 0.038860105 | P39: =$P10*$M$29 -> 0.016031864 | Q39: =$Q10*$M$30 -> 0.034978962 | R39: =SUM(M39:Q39) -> 0.18852253 | V39: L5 | W39: =$W10*$W$26 -> 0.34599191 | X39: =$X10*$W$27 -> 0.37763752 | Y39: =$Y10*$W$28 -> 0.64696193 | Z39: =$Z10*$W$29 -> 1.1803701 | AA39: =$AA10*$W$30 -> 0.57911109 | AB39: =SUM(W39:AA39) -> 3.1300725 | AG39: L5 | AH39: =$AH10*$AH$26 -> 0.28564662 | AI39: =$AI10*$AH$27 -> 0.41712664 | AJ39: =$AJ10*$AH$28 -> 0.74699151 | AK39: =$AK10*$AH$29 -> 0.83977393 | AL39: =$AL10*$AH$30 -> 0.52203425 | AM39: =SUM(AH39:AL39) -> 2.811573 | AQ39: L5 | AR39: =$AR10*$AR$26 -> 0.29936149 | AS39: =$AS10*$AR$27 -> 0.41786777 | AT39: =$AT10*$AR$28 -> 0.711582 | AU39: =$AU10*$AR$29 -> 0.8635238 | AV39: =$AV10*$AR$30 -> 0.53081202 | AW39: =SUM(AR39:AV39) -> 2.8231471
B41: Level | C41: Con. Vector | L41: Level | M41: Con. Vector | V41: Level | W41: Con. Vector | AG41: Level | AH41: Con. Vector | AQ41: Level | AR41: Con. Vector
B42: L1 | C42: =$H35/$C$26 -> 5.2631399 | L42: L1 | M42: =$R35/$M$26 -> 5.3895976 | V42: L1 | W42: =$AB35/$W$26 -> 5.4049604 | AG42: L1 | AH42: =$AM35/$AH$26 -> 5.3858017 | AQ42: L1 | AR42: =$AW35/$AR$26 -> 5.318544
B43: L2 | C43: =$H36/$C$27 -> 5.2631399 | L43: L2 | M43: =$R36/$M$27 -> 5.3895976 | V43: L2 | W43: =$AB36/$W$27 -> 5.4049604 | AG43: L2 | AH43: =$AM36/$AH$27 -> 5.3858017 | AQ43: L2 | AR43: =$AW36/$AR$27 -> 5.318544
B44: L3 | C44: =$H37/$C$28 -> 5.2631399 | L44: L3 | M44: =$R37/$M$28 -> 5.3895976 | V44: L3 | W44: =$AB37/$W$28 -> 5.4049604 | AG44: L3 | AH44: =$AM37/$AH$28 -> 5.3858017 | AQ44: L3 | AR44: =$AW37/$AR$28 -> 5.318544
B45: L4 | C45: =$H38/$C$29 -> 5.2631399 | L45: L4 | M45: =$R38/$M$29 -> 5.3895976 | V45: L4 | W45: =$AB38/$W$29 -> 5.4049604 | AG45: L4 | AH45: =$AM38/$AH$29 -> 5.3858017 | AQ45: L4 | AR45: =$AW38/$AR$29 -> 5.318544
B46: L5 | C46: =$H39/$C$30 -> 5.2631399 | L46: L5 | M46: =$R39/$M$30 -> 5.3895976 | V46: L5 | W46: =$AB39/$W$30 -> 5.4049604 | AG46: L5 | AH46: =$AM39/$AH$30 -> 5.3858017 | AQ46: L5 | AR46: =$AW39/$AR$30 -> 5.318544
B48: Matrix Size (n) | C48: =COUNTA($B$6:$B$10) -> 5 | L48: Matrix Size (n) | M48: =COUNTA($L$6:$L$10) -> 5 | V48: Matrix Size (n) | W48: =COUNTA($V$6:$V$10) -> 5 | AG48: Matrix Size (n) | AH48: =COUNTA($AH$6:$AH$10) -> 5 | AQ48: Matrix Size (n) | AR48: =COUNTA($AQ$6:$AQ$10) -> 5
B49: λmax | C49: =SUM($C$42:$C$46)/COUNT($C$42:$C$46) -> 5.2631399 | L49: λmax | M49: =SUM($M$42:$M$46)/COUNT($M$42:$M$46) -> 5.3895976 | V49: λmax | W49: =SUM($W$42:$W$46)/COUNT($W$42:$W$46) -> 5.4049604 | AG49: λmax | AH49: =SUM($AH$42:$AH$46)/COUNT($AH$42:$AH$46) -> 5.3858017 | AQ49: λmax | AR49: =SUM($AR$42:$AR$46)/COUNT($AR$42:$AR$46) -> 5.318544
B50: CI = (λmax - 5) / 4 | C50: =($C$49-$C$48)/($C$48-1) -> 0.065784977 | L50: CI = (λmax - 5) / 4 | M50: =($M$49-$M$48)/($M$48-1) -> 0.097399395 | V50: CI = (λmax - 5) / 4 | W50: =($W$49-$W$48)/($W$48-1) -> 0.10124011 | AG50: CI = (λmax - 5) / 4 | AH50: =($AH$49-$AH$48)/($AH$48-1) -> 0.096450426 | AQ50: CI = (λmax - 5) / 4 | AR50: =($AR$49-$AR$48)/($AR$48-1) -> 0.079635997
B51: RI | C51: =_xlfn.XLOOKUP($C$48,'AHP Saaty Reference'!$B$22:$B$37,'AHP Saaty Reference'!$C$22:$C$37) -> 1.11 | L51: RI | M51: =_xlfn.XLOOKUP($M$48,'AHP Saaty Reference'!$B$22:$B$37,'AHP Saaty Reference'!$C$22:$C$37) -> 1.11 | V51: RI | W51: =_xlfn.XLOOKUP($W$48,'AHP Saaty Reference'!$B$22:$B$37,'AHP Saaty Reference'!$C$22:$C$37) -> 1.11 | AG51: RI | AH51: =_xlfn.XLOOKUP($AH$48,'AHP Saaty Reference'!$B$22:$B$37,'AHP Saaty Reference'!$C$22:$C$37) -> 1.11 | AQ51: RI | AR51: =_xlfn.XLOOKUP($AR$48,'AHP Saaty Reference'!$B$22:$B$37,'AHP Saaty Reference'!$C$22:$C$37) -> 1.11
B52: CR = CI / RI | C52: =$C$50/$C$51 -> 0.059265745 | L52: CR = CI / RI | M52: =$M$50/$M$51 -> 0.087747203 | V52: CR = CI / RI | W52: =$W$50/$W$51 -> 0.091207308 | AG52: CR = CI / RI | AH52: =$AH$50/$AH$51 -> 0.086892275 | AQ52: CR = CI / RI | AR52: =$AR$50/$AR$51 -> 0.071744142
B53: Status | C53: =IF(C52<=0.1,"Acceptable","Not Acceptable — Revise judgments") -> Acceptable | L53: Status | M53: =IF(M52<=0.1,"Acceptable","Not Acceptable — Revise judgments") -> Acceptable | V53: Status | W53: =IF(W52<=0.1,"Acceptable","Not Acceptable — Revise judgments") -> Acceptable | AG53: Status | AH53: =IF(AH52<=0.1,"Acceptable","Not Acceptable — Revise judgments") -> Acceptable | AQ53: Status | AR53: =IF(AR52<=0.1,"Acceptable","Not Acceptable — Revise judgments") -> Acceptable

Sheet 1.7 AHP Calculations
B1: AHP Trace — Step-by-Step Calculation
B3: ℹ️ Note: Cells displaying #N/A indicate that required inputs have not yet been provided. Please complete the pairwise comparisons to enable calculations.
B8: PHASE 1 — Derive Criteria Weights
B10: Level 1 — Main Criteria: Remediation Effort vs Impact
B12: Criterion | C12: Remediation Effort | D12: Impact
B13: Remediation Effort | C13: 1 | D13: =IF('1.2 Weights'!$H$9="", NA(), IF('1.2 Weights'!$F$9="Equal importance",1,'1.2 Weights'!$H$9) ) -> 1
B14: Impact | C14: =IF($D$13="","",1/$D$13) -> 1 | D14: 1
B15: Column Sum | C15: =SUM(C13:C14) -> 2 | D15: =SUM(D13:D14) -> 2
B17: Criterion | C17: Norm. Col 1 | D17: Norm. Col 2 | E17: Row Average (unnormalised) | F17: Normalised Weight (÷ Σ row avgs)
B18: Remediation Effort | C18: =C13/C15 -> 0.5 | D18: =IF(OR(D13="",D15="",D15=0),"",D13/D15) -> 0.5 | E18: =AVERAGE(C18:D18) -> 0.5 | F18: =E18/SUM($E$18:$E$19) -> 0.5
B19: Impact | C19: =IF(OR(C14="",C15="",C15=0),"",C14/C15) -> 0.5 | D19: =D14/D15 -> 0.5 | E19: =AVERAGE(C19:D19) -> 0.5 | F19: =E19/SUM($E$18:$E$19) -> 0.5
B20: Σ row avgs (unnorm) → Σ normalised weights → must = 1.0000 | E20: =SUM(E18:E19) -> 1 | F20: =SUM(F18:F19) -> 1
B22: Level 2a — Remediation Effort Subcriteria: Scope vs Restructuring Complexity
B24: Subcriterion | C24: Scope | D24: Restructuring Complexity
B25: Scope | C25: 1 | D25: =IF('1.2 Weights'!$F$12="Equal importance", 1, IF('1.2 Weights'!$H$12="", NA(), '1.2 Weights'!$H$12 ) ) -> 1
B26: Restructuring Complexity | C26: =IF($D$25="","",1/$D$25) -> 1 | D26: 1
B27: Column Sum | C27: =SUM(C25:C26) -> 2 | D27: =SUM(D25:D26) -> 2
B29: Subcriterion | C29: Norm. Col 1 | D29: Norm. Col 2 | E29: Row Average (unnormalised) | F29: Normalised Weight (÷ Σ row avgs)
B30: Scope | C30: =C25/C27 -> 0.5 | D30: =IF(OR($D$25="",$D$27="",$D$27=0),"",$D$25/$D$27) -> 0.5 | E30: =AVERAGE(C30:D30) -> 0.5 | F30: =E30/SUM($E$30:$E$31) -> 0.5
B31: Restructuring Complexity | C31: =IF(OR($C$26="",$C$27="",$C$27=0),"",$C$26/$C$27) -> 0.5 | D31: =D26/D27 -> 0.5 | E31: =AVERAGE(C31:D31) -> 0.5 | F31: =E31/SUM($E$30:$E$31) -> 0.5
B32: Σ row avgs (unnorm) → Σ normalised weights → must = 1.0000 | E32: =SUM(E30:E31) -> 1 | F32: =SUM(F30:F31) -> 1
B34: Level 2b — Impact Subcriteria: Evolution Constraint / Gov. Overhead / Op. Reliability (n=3)
B36: Subcriterion | C36: Evol. Constraint | D36: Gov. & Coord. Overhead | E36: Op. Reliability Impact
B37: Evolution Constraint | C37: 1 | D37: =IF('1.2 Weights'!$F$15="Equal importance", 1, IF('1.2 Weights'!$H$15="", NA(), '1.2 Weights'!$H$15 ) ) -> 1 | E37: =IF('1.2 Weights'!$F$16="Equal importance", 1, IF('1.2 Weights'!$H$16="", NA(), '1.2 Weights'!$H$16 ) ) -> 1
B38: Gov. & Coord. Overhead | C38: =IF($D$37="","",1/$D$37) -> 1 | D38: 1 | E38: =IF('1.2 Weights'!$F$17="Equal importance", 1, IF('1.2 Weights'!$H$17="", NA(), '1.2 Weights'!$H$17 ) ) -> 1
B39: Op. Reliability Impact | C39: =IF($E$37="","",1/$E$37) -> 1 | D39: =IF($E$38="","",1/$E$38) -> 1 | E39: 1
B40: Column Sum | C40: =SUM(C37:C39) -> 3 | D40: =SUM(D37:D39) -> 3 | E40: =SUM(E37:E39) -> 3
B42: Subcriterion | C42: Norm. Col 1 | D42: Norm. Col 2 | E42: Norm. Col 3 | F42: Row Average (unnormalised) | G42: Normalised Weight (÷ Σ row avgs)
B43: Evolution Constraint | C43: =C37/C40 -> 0.33333333 | D43: =IF(OR($D$37="",$D$40="",$D$40=0),"",$D$37/$D$40) -> 0.33333333 | E43: =IF(OR($E$37="",$E$40="",$E$40=0),"",$E$37/$E$40) -> 0.33333333 | F43: =AVERAGE(C43:E43) -> 0.33333333 | G43: =F43/SUM($F$43:$F$45) -> 0.33333333
B44: Gov. & Coord. Overhead | C44: =IF(OR($C$38="",$C$40="",$C$40=0),"",$C$38/$C$40) -> 0.33333333 | D44: =D38/D40 -> 0.33333333 | E44: =IF(OR($E$38="",$E$40="",$E$40=0),"",$E$38/$E$40) -> 0.33333333 | F44: =AVERAGE(C44:E44) -> 0.33333333 | G44: =F44/SUM($F$43:$F$45) -> 0.33333333
B45: Op. Reliability Impact | C45: =IF(OR($C$39="",$C$40="",$C$40=0),"",$C$39/$C$40) -> 0.33333333 | D45: =IF(OR($D$39="",$D$40="",$D$40=0),"",$D$39/$D$40) -> 0.33333333 | E45: =E39/E40 -> 0.33333333 | F45: =AVERAGE(C45:E45) -> 0.33333333 | G45: =F45/SUM($F$43:$F$45) -> 0.33333333
B46: Σ row avgs (unnorm) → Σ normalised weights → must = 1.0000 | F46: =SUM(F43:F45) -> 1 | G46: =SUM(G43:G45) -> 1
B48: λmax (weighted sum vector average) | C48: =IFERROR( IF(OR(COUNTBLANK(C37:E39)>0,COUNTBLANK(G43:G45)>0,G43=0,G44=0,G45=0),NA(), AVERAGE( (C37*G43+D37*G44+E37*G45)/G43, (C38*G43+D38*G44+E38*G45)/G44, (C39*G43+D39*G44+E39*G45)/G45 )), NA()) -> 3
B49: n (matrix size) | C49: 3
B50: CI = (λmax − n) / (n − 1) | C50: =IF(C48="","",(C48-3)/(3-1)) -> 0
B51: RI = 0.525 (Saaty table, n=3) | C51: 0.525
B52: CR = CI / RI | C52: =IF($C$50="","",$C$50/$C$51) -> 0
B53: CR Status | C53: =IF(ISNA($C$52), "Awaiting input", IF($C$52<=0.1, "Acceptable", "Not Acceptable – Revise judgments")) -> Acceptable
B55: PHASE 2 — Apply Weights to Smell Scores
B57: Step 7 — Global Weights = Level 1 parent weight × Level 2 local weight
B59: Subcriterion | C59: L1 Parent Weight | D59: L2 Local Weight | E59: Global Weight (L1 × L2) | F59: % of Total
B60: Scope | C60: =$F$18 -> 0.5 | D60: =$F$30 -> 0.5 | E60: =C60*D60 -> 0.25 | F60: =E60/SUM($E$60:$E$64) -> 0.25
B61: Restructuring Complexity | C61: =$F$18 -> 0.5 | D61: =$F$31 -> 0.5 | E61: =C61*D61 -> 0.25 | F61: =E61/SUM($E$60:$E$64) -> 0.25
B62: Evolution Constraint | C62: =$F$19 -> 0.5 | D62: =$G$43 -> 0.33333333 | E62: =C62*D62 -> 0.16666667 | F62: =E62/SUM($E$60:$E$64) -> 0.16666667
B63: Gov. & Coord. Overhead | C63: =$F$19 -> 0.5 | D63: =$G$44 -> 0.33333333 | E63: =C63*D63 -> 0.16666667 | F63: =E63/SUM($E$60:$E$64) -> 0.16666667
B64: Op. Reliability Impact | C64: =$F$19 -> 0.5 | D64: =$G$45 -> 0.33333333 | E64: =C64*D64 -> 0.16666667 | F64: =E64/SUM($E$60:$E$64) -> 0.16666667
B65: Sum of all global weights → should equal 1.0000 | E65: =SUM(E60:E64) -> 1
B67: Steps 8–11 — Weighted Score Calculation per EA Smell
B69: EA Smell Instance | C69: Scope | D69: Restructuring Complexity | E69: Evolution Constraint | F69: Governance Overhead | G69: Reliability Impact | H69: Scope Intensity Priority | I69: Restructuring Complexity Intensity Priority | J69: Evolution Constraint Intensity Priority | K69: Governance Overhead Intensity Priority | L69: Reliability Impact Intensity Priority | M69: Scope Intensity Priority * Weight | N69: Restructuring Complexity Internsity Priority * Weight | O69: Evolution Constraint Intensity Priority * Weight | P69: Governance Overhead Intensity Priority * Weight | Q69: Reliability Impact Intensity Priority * Weight | R69: Weighted Score / Total | S69: Rank | T69: Priority | U69: Scope Rating / Intensity Priority | V69: Restructuring Complexity Rating / Intensity Priority | W69: Evolution Constraint Rating / Intensity Priority | X69: Governance Overhead Rating / Intensity Priority | Y69: Operational Reliability Rating / Intensity Priority
A70: 1 | B70: {=_xlfn._xlws.FILTER('1.4 EA Smell Scoring'!C9:C18,'1.4 EA Smell Scoring'!C9:C18<>"","")} -> Cyclic Dependency | C70: =IFERROR(IF(INDEX('1.4 EA Smell Scoring'!$D$9:$H$18,MATCH($B70,'1.4 EA Smell Scoring'!$C$9:$C$18,0),MATCH(C$69,'1.4 EA Smell Scoring'!$D$8:$H$8,0))=0,"",INDEX('1.4 EA Smell Scoring'!$D$9:$H$18,MATCH($B70,'1.4 EA Smell Scoring'!$C$9:$C$18,0),MATCH(C$69,'1.4 EA Smell Scoring'!$D$8:$H$8,0))),"") -> 4 | D70: =IFERROR(IF(INDEX('1.4 EA Smell Scoring'!$D$9:$H$18,MATCH($B70,'1.4 EA Smell Scoring'!$C$9:$C$18,0),MATCH(D$69,'1.4 EA Smell Scoring'!$D$8:$H$8,0))=0,"",INDEX('1.4 EA Smell Scoring'!$D$9:$H$18,MATCH($B70,'1.4 EA Smell Scoring'!$C$9:$C$18,0),MATCH(D$69,'1.4 EA Smell Scoring'!$D$8:$H$8,0))),"") -> 4 | E70: =IFERROR(IF(INDEX('1.4 EA Smell Scoring'!$D$9:$H$18,MATCH($B70,'1.4 EA Smell Scoring'!$C$9:$C$18,0),MATCH(E$69,'1.4 EA Smell Scoring'!$D$8:$H$8,0))=0,"",INDEX('1.4 EA Smell Scoring'!$D$9:$H$18,MATCH($B70,'1.4 EA Smell Scoring'!$C$9:$C$18,0),MATCH(E$69,'1.4 EA Smell Scoring'!$D$8:$H$8,0))),"") -> 4 | F70: =IFERROR(IF(INDEX('1.4 EA Smell Scoring'!$D$9:$H$18,MATCH($B70,'1.4 EA Smell Scoring'!$C$9:$C$18,0),MATCH(F$69,'1.4 EA Smell Scoring'!$D$8:$H$8,0))=0,"",INDEX('1.4 EA Smell Scoring'!$D$9:$H$18,MATCH($B70,'1.4 EA Smell Scoring'!$C$9:$C$18,0),MATCH(F$69,'1.4 EA Smell Scoring'!$D$8:$H$8,0))),"") -> 3 | G70: =IFERROR(IF(INDEX('1.4 EA Smell Scoring'!$D$9:$H$18,MATCH($B70,'1.4 EA Smell Scoring'!$C$9:$C$18,0),MATCH(G$69,'1.4 EA Smell Scoring'!$D$8:$H$8,0))=0,"",INDEX('1.4 EA Smell Scoring'!$D$9:$H$18,MATCH($B70,'1.4 EA Smell Scoring'!$C$9:$C$18,0),MATCH(G$69,'1.4 EA Smell Scoring'!$D$8:$H$8,0))),"") -> 3 | H70: =IF(C70="","",IFERROR(_xlfn.XLOOKUP("L"&C70,'1.6 IP Calculations'!$B$26:$B$30,'1.6 IP Calculations'!$D$26:$D$30),"")) -> 0.22309669 | I70: =IF($D70="","",IFERROR(_xlfn.XLOOKUP("L"&$D70,'1.6 IP Calculations'!$L$26:$L$30,'1.6 IP Calculations'!$N$26:$N$30),"")) -> 0.19626433 | J70: =IF(E70="","",IFERROR(_xlfn.XLOOKUP("L"&E70,'1.6 IP Calculations'!$V$26:$V$30,'1.6 IP Calculations'!$X$26:$X$30),"")) -> 0.40764893 | K70: =IF(F70="","",IFERROR(_xlfn.XLOOKUP("L"&F70,'1.6 IP Calculations'!$AG$26:$AG$30,'1.6 IP Calculations'!$AI$26:$AI$30),"")) -> 0.20441776 | L70: =IF(G70="","",IFERROR(_xlfn.XLOOKUP("L"&G70,'1.6 IP Calculations'!$AQ$26:$AQ$30,'1.6 IP Calculations'!$AS$26:$AS$30),"")) -> 0.19150767 | M70: =IF(H70="","",H70*$E$60) -> 0.055774173 | N70: =IF(I70="","",I70*$E$61) -> 0.049066084 | O70: =IF(J70="","",J70*$E$62) -> 0.067941488 | P70: =IF(K70="","",K70*$E$63) -> 0.034069627 | Q70: =IF(L70="","",L70*$E$64) -> 0.031917944 | R70: =IF(COUNTIF(C70:G70,">0")=0,"",SUM(M70:Q70)) -> 0.23876932 | S70: =IF(COUNTIF(C70:G70,">0")=0,"",RANK(R70,$R$70:$R$79,0)) -> 5 | T70: =IF(COUNTIF(C70:G70,">0")=0,"",R70/SUM($R$70:$R$79)) -> 0.13350863 | U70: =IF(OR(C70="",H70=""),"",_xlfn.CONCAT(C70," (",TEXT(H70,"0.0000"),")")) -> 4 (0.2231) | V70: =IF(OR(D70="",I70=""),"",_xlfn.CONCAT(D70," (",TEXT(I70,"0.0000"),")")) -> 4 (0.1963) | W70: =IF(OR(E70="",J70=""),"",_xlfn.CONCAT(E70," (",TEXT(J70,"0.0000"),")")) -> 4 (0.4076) | X70: =IF(OR(F70="",K70=""),"",_xlfn.CONCAT(F70," (",TEXT(K70,"0.0000"),")")) -> 3 (0.2044) | Y70: =IF(OR(G70="",L70=""),"",_xlfn.CONCAT(G70," (",TEXT(L70,"0.0000"),")")) -> 3 (0.1915)
A71: 2 | B71: Shared Persistency | C71: =IFERROR(IF(INDEX('1.4 EA Smell Scoring'!$D$9:$H$18,MATCH($B71,'1.4 EA Smell Scoring'!$C$9:$C$18,0),MATCH(C$69,'1.4 EA Smell Scoring'!$D$8:$H$8,0))=0,"",INDEX('1.4 EA Smell Scoring'!$D$9:$H$18,MATCH($B71,'1.4 EA Smell Scoring'!$C$9:$C$18,0),MATCH(C$69,'1.4 EA Smell Scoring'!$D$8:$H$8,0))),"") -> 5 | D71: =IFERROR(IF(INDEX('1.4 EA Smell Scoring'!$D$9:$H$18,MATCH($B71,'1.4 EA Smell Scoring'!$C$9:$C$18,0),MATCH(D$69,'1.4 EA Smell Scoring'!$D$8:$H$8,0))=0,"",INDEX('1.4 EA Smell Scoring'!$D$9:$H$18,MATCH($B71,'1.4 EA Smell Scoring'!$C$9:$C$18,0),MATCH(D$69,'1.4 EA Smell Scoring'!$D$8:$H$8,0))),"") -> 3 | E71: =IFERROR(IF(INDEX('1.4 EA Smell Scoring'!$D$9:$H$18,MATCH($B71,'1.4 EA Smell Scoring'!$C$9:$C$18,0),MATCH(E$69,'1.4 EA Smell Scoring'!$D$8:$H$8,0))=0,"",INDEX('1.4 EA Smell Scoring'!$D$9:$H$18,MATCH($B71,'1.4 EA Smell Scoring'!$C$9:$C$18,0),MATCH(E$69,'1.4 EA Smell Scoring'!$D$8:$H$8,0))),"") -> 5 | F71: =IFERROR(IF(INDEX('1.4 EA Smell Scoring'!$D$9:$H$18,MATCH($B71,'1.4 EA Smell Scoring'!$C$9:$C$18,0),MATCH(F$69,'1.4 EA Smell Scoring'!$D$8:$H$8,0))=0,"",INDEX('1.4 EA Smell Scoring'!$D$9:$H$18,MATCH($B71,'1.4 EA Smell Scoring'!$C$9:$C$18,0),MATCH(F$69,'1.4 EA Smell Scoring'!$D$8:$H$8,0))),"") -> 4 | G71: =IFERROR(IF(INDEX('1.4 EA Smell Scoring'!$D$9:$H$18,MATCH($B71,'1.4 EA Smell Scoring'!$C$9:$C$18,0),MATCH(G$69,'1.4 EA Smell Scoring'!$D$8:$H$8,0))=0,"",INDEX('1.4 EA Smell Scoring'!$D$9:$H$18,MATCH($B71,'1.4 EA Smell Scoring'!$C$9:$C$18,0),MATCH(G$69,'1.4 EA Smell Scoring'!$D$8:$H$8,0))),"") -> 4 | H71: =IF(C71="","",IFERROR(_xlfn.XLOOKUP("L"&C71,'1.6 IP Calculations'!$B$26:$B$30,'1.6 IP Calculations'!$D$26:$D$30),"")) -> 0.085534816 | I71: =IF($D71="","",IFERROR(_xlfn.XLOOKUP("L"&$D71,'1.6 IP Calculations'!$L$26:$L$30,'1.6 IP Calculations'!$N$26:$N$30),"")) -> 0.47573088 | J71: =IF(E71="","",IFERROR(_xlfn.XLOOKUP("L"&E71,'1.6 IP Calculations'!$V$26:$V$30,'1.6 IP Calculations'!$X$26:$X$30),"")) -> 1 | K71: =IF(F71="","",IFERROR(_xlfn.XLOOKUP("L"&F71,'1.6 IP Calculations'!$AG$26:$AG$30,'1.6 IP Calculations'!$AI$26:$AI$30),"")) -> 0.53621892 | L71: =IF(G71="","",IFERROR(_xlfn.XLOOKUP("L"&G71,'1.6 IP Calculations'!$AQ$26:$AQ$30,'1.6 IP Calculations'!$AS$26:$AS$30),"")) -> 0.54226592 | M71: =IF(H71="","",H71*$E$60) -> 0.021383704 | N71: =IF(I71="","",I71*$E$61) -> 0.11893272 | O71: =IF(J71="","",J71*$E$62) -> 0.16666667 | P71: =IF(K71="","",K71*$E$63) -> 0.08936982 | Q71: =IF(L71="","",L71*$E$64) -> 0.090377653 | R71: =IF(COUNTIF(C71:G71,">0")=0,"",SUM(M71:Q71)) -> 0.48673056 | S71: =IF(COUNTIF(C71:G71,">0")=0,"",RANK(R71,$R$70:$R$79,0)) -> 2 | T71: =IF(COUNTIF(C71:G71,">0")=0,"",R71/SUM($R$70:$R$79)) -> 0.27215696 | U71: =IF(OR(C71="",H71=""),"",_xlfn.CONCAT(C71," (",TEXT(H71,"0.0000"),")")) -> 5 (0.0855) | V71: =IF(OR(D71="",I71=""),"",_xlfn.CONCAT(D71," (",TEXT(I71,"0.0000"),")")) -> 3 (0.4757) | W71: =IF(OR(E71="",J71=""),"",_xlfn.CONCAT(E71," (",TEXT(J71,"0.0000"),")")) -> 5 (1.0000) | X71: =IF(OR(F71="",K71=""),"",_xlfn.CONCAT(F71," (",TEXT(K71,"0.0000"),")")) -> 4 (0.5362) | Y71: =IF(OR(G71="",L71=""),"",_xlfn.CONCAT(G71," (",TEXT(L71,"0.0000"),")")) -> 4 (0.5423)
A72: 3 | B72: Feature Envy | C72: =IFERROR(IF(INDEX('1.4 EA Smell Scoring'!$D$9:$H$18,MATCH($B72,'1.4 EA Smell Scoring'!$C$9:$C$18,0),MATCH(C$69,'1.4 EA Smell Scoring'!$D$8:$H$8,0))=0,"",INDEX('1.4 EA Smell Scoring'!$D$9:$H$18,MATCH($B72,'1.4 EA Smell Scoring'!$C$9:$C$18,0),MATCH(C$69,'1.4 EA Smell Scoring'!$D$8:$H$8,0))),"") -> 3 | D72: =IFERROR(IF(INDEX('1.4 EA Smell Scoring'!$D$9:$H$18,MATCH($B72,'1.4 EA Smell Scoring'!$C$9:$C$18,0),MATCH(D$69,'1.4 EA Smell Scoring'!$D$8:$H$8,0))=0,"",INDEX('1.4 EA Smell Scoring'!$D$9:$H$18,MATCH($B72,'1.4 EA Smell Scoring'!$C$9:$C$18,0),MATCH(D$69,'1.4 EA Smell Scoring'!$D$8:$H$8,0))),"") -> 3 | E72: =IFERROR(IF(INDEX('1.4 EA Smell Scoring'!$D$9:$H$18,MATCH($B72,'1.4 EA Smell Scoring'!$C$9:$C$18,0),MATCH(E$69,'1.4 EA Smell Scoring'!$D$8:$H$8,0))=0,"",INDEX('1.4 EA Smell Scoring'!$D$9:$H$18,MATCH($B72,'1.4 EA Smell Scoring'!$C$9:$C$18,0),MATCH(E$69,'1.4 EA Smell Scoring'!$D$8:$H$8,0))),"") -> 3 | F72: =IFERROR(IF(INDEX('1.4 EA Smell Scoring'!$D$9:$H$18,MATCH($B72,'1.4 EA Smell Scoring'!$C$9:$C$18,0),MATCH(F$69,'1.4 EA Smell Scoring'!$D$8:$H$8,0))=0,"",INDEX('1.4 EA Smell Scoring'!$D$9:$H$18,MATCH($B72,'1.4 EA Smell Scoring'!$C$9:$C$18,0),MATCH(F$69,'1.4 EA Smell Scoring'!$D$8:$H$8,0))),"") -> 2 | G72: =IFERROR(IF(INDEX('1.4 EA Smell Scoring'!$D$9:$H$18,MATCH($B72,'1.4 EA Smell Scoring'!$C$9:$C$18,0),MATCH(G$69,'1.4 EA Smell Scoring'!$D$8:$H$8,0))=0,"",INDEX('1.4 EA Smell Scoring'!$D$9:$H$18,MATCH($B72,'1.4 EA Smell Scoring'!$C$9:$C$18,0),MATCH(G$69,'1.4 EA Smell Scoring'!$D$8:$H$8,0))),"") -> 2 | H72: =IF(C72="","",IFERROR(_xlfn.XLOOKUP("L"&C72,'1.6 IP Calculations'!$B$26:$B$30,'1.6 IP Calculations'!$D$26:$D$30),"")) -> 0.34263524 | I72: =IF($D72="","",IFERROR(_xlfn.XLOOKUP("L"&$D72,'1.6 IP Calculations'!$L$26:$L$30,'1.6 IP Calculations'!$N$26:$N$30),"")) -> 0.47573088 | J72: =IF(E72="","",IFERROR(_xlfn.XLOOKUP("L"&E72,'1.6 IP Calculations'!$V$26:$V$30,'1.6 IP Calculations'!$X$26:$X$30),"")) -> 0.15959483 | K72: =IF(F72="","",IFERROR(_xlfn.XLOOKUP("L"&F72,'1.6 IP Calculations'!$AG$26:$AG$30,'1.6 IP Calculations'!$AI$26:$AI$30),"")) -> 0.11414868 | L72: =IF(G72="","",IFERROR(_xlfn.XLOOKUP("L"&G72,'1.6 IP Calculations'!$AQ$26:$AQ$30,'1.6 IP Calculations'!$AS$26:$AS$30),"")) -> 0.087469293 | M72: =IF(H72="","",H72*$E$60) -> 0.08565881 | N72: =IF(I72="","",I72*$E$61) -> 0.11893272 | O72: =IF(J72="","",J72*$E$62) -> 0.026599138 | P72: =IF(K72="","",K72*$E$63) -> 0.01902478 | Q72: =IF(L72="","",L72*$E$64) -> 0.014578216 | R72: =IF(COUNTIF(C72:G72,">0")=0,"",SUM(M72:Q72)) -> 0.26479366 | S72: =IF(COUNTIF(C72:G72,">0")=0,"",RANK(R72,$R$70:$R$79,0)) -> 4 | T72: =IF(COUNTIF(C72:G72,">0")=0,"",R72/SUM($R$70:$R$79)) -> 0.14806023 | U72: =IF(OR(C72="",H72=""),"",_xlfn.CONCAT(C72," (",TEXT(H72,"0.0000"),")")) -> 3 (0.3426) | V72: =IF(OR(D72="",I72=""),"",_xlfn.CONCAT(D72," (",TEXT(I72,"0.0000"),")")) -> 3 (0.4757) | W72: =IF(OR(E72="",J72=""),"",_xlfn.CONCAT(E72," (",TEXT(J72,"0.0000"),")")) -> 3 (0.1596) | X72: =IF(OR(F72="",K72=""),"",_xlfn.CONCAT(F72," (",TEXT(K72,"0.0000"),")")) -> 2 (0.1141) | Y72: =IF(OR(G72="",L72=""),"",_xlfn.CONCAT(G72," (",TEXT(L72,"0.0000"),")")) -> 2 (0.0875)
A73: 4 | B73: Stovepipe System | C73: =IFERROR(IF(INDEX('1.4 EA Smell Scoring'!$D$9:$H$18,MATCH($B73,'1.4 EA Smell Scoring'!$C$9:$C$18,0),MATCH(C$69,'1.4 EA Smell Scoring'!$D$8:$H$8,0))=0,"",INDEX('1.4 EA Smell Scoring'!$D$9:$H$18,MATCH($B73,'1.4 EA Smell Scoring'!$C$9:$C$18,0),MATCH(C$69,'1.4 EA Smell Scoring'!$D$8:$H$8,0))),"") -> 4 | D73: =IFERROR(IF(INDEX('1.4 EA Smell Scoring'!$D$9:$H$18,MATCH($B73,'1.4 EA Smell Scoring'!$C$9:$C$18,0),MATCH(D$69,'1.4 EA Smell Scoring'!$D$8:$H$8,0))=0,"",INDEX('1.4 EA Smell Scoring'!$D$9:$H$18,MATCH($B73,'1.4 EA Smell Scoring'!$C$9:$C$18,0),MATCH(D$69,'1.4 EA Smell Scoring'!$D$8:$H$8,0))),"") -> 4 | E73: =IFERROR(IF(INDEX('1.4 EA Smell Scoring'!$D$9:$H$18,MATCH($B73,'1.4 EA Smell Scoring'!$C$9:$C$18,0),MATCH(E$69,'1.4 EA Smell Scoring'!$D$8:$H$8,0))=0,"",INDEX('1.4 EA Smell Scoring'!$D$9:$H$18,MATCH($B73,'1.4 EA Smell Scoring'!$C$9:$C$18,0),MATCH(E$69,'1.4 EA Smell Scoring'!$D$8:$H$8,0))),"") -> 4 | F73: =IFERROR(IF(INDEX('1.4 EA Smell Scoring'!$D$9:$H$18,MATCH($B73,'1.4 EA Smell Scoring'!$C$9:$C$18,0),MATCH(F$69,'1.4 EA Smell Scoring'!$D$8:$H$8,0))=0,"",INDEX('1.4 EA Smell Scoring'!$D$9:$H$18,MATCH($B73,'1.4 EA Smell Scoring'!$C$9:$C$18,0),MATCH(F$69,'1.4 EA Smell Scoring'!$D$8:$H$8,0))),"") -> 3 | G73: =IFERROR(IF(INDEX('1.4 EA Smell Scoring'!$D$9:$H$18,MATCH($B73,'1.4 EA Smell Scoring'!$C$9:$C$18,0),MATCH(G$69,'1.4 EA Smell Scoring'!$D$8:$H$8,0))=0,"",INDEX('1.4 EA Smell Scoring'!$D$9:$H$18,MATCH($B73,'1.4 EA Smell Scoring'!$C$9:$C$18,0),MATCH(G$69,'1.4 EA Smell Scoring'!$D$8:$H$8,0))),"") -> 4 | H73: =IF(C73="","",IFERROR(_xlfn.XLOOKUP("L"&C73,'1.6 IP Calculations'!$B$26:$B$30,'1.6 IP Calculations'!$D$26:$D$30),"")) -> 0.22309669 | I73: =IF($D73="","",IFERROR(_xlfn.XLOOKUP("L"&$D73,'1.6 IP Calculations'!$L$26:$L$30,'1.6 IP Calculations'!$N$26:$N$30),"")) -> 0.19626433 | J73: =IF(E73="","",IFERROR(_xlfn.XLOOKUP("L"&E73,'1.6 IP Calculations'!$V$26:$V$30,'1.6 IP Calculations'!$X$26:$X$30),"")) -> 0.40764893 | K73: =IF(F73="","",IFERROR(_xlfn.XLOOKUP("L"&F73,'1.6 IP Calculations'!$AG$26:$AG$30,'1.6 IP Calculations'!$AI$26:$AI$30),"")) -> 0.20441776 | L73: =IF(G73="","",IFERROR(_xlfn.XLOOKUP("L"&G73,'1.6 IP Calculations'!$AQ$26:$AQ$30,'1.6 IP Calculations'!$AS$26:$AS$30),"")) -> 0.54226592 | M73: =IF(H73="","",H73*$E$60) -> 0.055774173 | N73: =IF(I73="","",I73*$E$61) -> 0.049066084 | O73: =IF(J73="","",J73*$E$62) -> 0.067941488 | P73: =IF(K73="","",K73*$E$63) -> 0.034069627 | Q73: =IF(L73="","",L73*$E$64) -> 0.090377653 | R73: =IF(COUNTIF(C73:G73,">0")=0,"",SUM(M73:Q73)) -> 0.29722902 | S73: =IF(COUNTIF(C73:G73,">0")=0,"",RANK(R73,$R$70:$R$79,0)) -> 3 | T73: =IF(COUNTIF(C73:G73,">0")=0,"",R73/SUM($R$70:$R$79)) -> 0.16619656 | U73: =IF(OR(C73="",H73=""),"",_xlfn.CONCAT(C73," (",TEXT(H73,"0.0000"),")")) -> 4 (0.2231) | V73: =IF(OR(D73="",I73=""),"",_xlfn.CONCAT(D73," (",TEXT(I73,"0.0000"),")")) -> 4 (0.1963) | W73: =IF(OR(E73="",J73=""),"",_xlfn.CONCAT(E73," (",TEXT(J73,"0.0000"),")")) -> 4 (0.4076) | X73: =IF(OR(F73="",K73=""),"",_xlfn.CONCAT(F73," (",TEXT(K73,"0.0000"),")")) -> 3 (0.2044) | Y73: =IF(OR(G73="",L73=""),"",_xlfn.CONCAT(G73," (",TEXT(L73,"0.0000"),")")) -> 4 (0.5423)
A74: 5 | B74: Vendor Lock-In | C74: =IFERROR(IF(INDEX('1.4 EA Smell Scoring'!$D$9:$H$18,MATCH($B74,'1.4 EA Smell Scoring'!$C$9:$C$18,0),MATCH(C$69,'1.4 EA Smell Scoring'!$D$8:$H$8,0))=0,"",INDEX('1.4 EA Smell Scoring'!$D$9:$H$18,MATCH($B74,'1.4 EA Smell Scoring'!$C$9:$C$18,0),MATCH(C$69,'1.4 EA Smell Scoring'!$D$8:$H$8,0))),"") -> 4 | D74: =IFERROR(IF(INDEX('1.4 EA Smell Scoring'!$D$9:$H$18,MATCH($B74,'1.4 EA Smell Scoring'!$C$9:$C$18,0),MATCH(D$69,'1.4 EA Smell Scoring'!$D$8:$H$8,0))=0,"",INDEX('1.4 EA Smell Scoring'!$D$9:$H$18,MATCH($B74,'1.4 EA Smell Scoring'!$C$9:$C$18,0),MATCH(D$69,'1.4 EA Smell Scoring'!$D$8:$H$8,0))),"") -> 5 | E74: =IFERROR(IF(INDEX('1.4 EA Smell Scoring'!$D$9:$H$18,MATCH($B74,'1.4 EA Smell Scoring'!$C$9:$C$18,0),MATCH(E$69,'1.4 EA Smell Scoring'!$D$8:$H$8,0))=0,"",INDEX('1.4 EA Smell Scoring'!$D$9:$H$18,MATCH($B74,'1.4 EA Smell Scoring'!$C$9:$C$18,0),MATCH(E$69,'1.4 EA Smell Scoring'!$D$8:$H$8,0))),"") -> 5 | F74: =IFERROR(IF(INDEX('1.4 EA Smell Scoring'!$D$9:$H$18,MATCH($B74,'1.4 EA Smell Scoring'!$C$9:$C$18,0),MATCH(F$69,'1.4 EA Smell Scoring'!$D$8:$H$8,0))=0,"",INDEX('1.4 EA Smell Scoring'!$D$9:$H$18,MATCH($B74,'1.4 EA Smell Scoring'!$C$9:$C$18,0),MATCH(F$69,'1.4 EA Smell Scoring'!$D$8:$H$8,0))),"") -> 5 | G74: =IFERROR(IF(INDEX('1.4 EA Smell Scoring'!$D$9:$H$18,MATCH($B74,'1.4 EA Smell Scoring'!$C$9:$C$18,0),MATCH(G$69,'1.4 EA Smell Scoring'!$D$8:$H$8,0))=0,"",INDEX('1.4 EA Smell Scoring'!$D$9:$H$18,MATCH($B74,'1.4 EA Smell Scoring'!$C$9:$C$18,0),MATCH(G$69,'1.4 EA Smell Scoring'!$D$8:$H$8,0))),"") -> 4 | H74: =IF(C74="","",IFERROR(_xlfn.XLOOKUP("L"&C74,'1.6 IP Calculations'!$B$26:$B$30,'1.6 IP Calculations'!$D$26:$D$30),"")) -> 0.22309669 | I74: =IF($D74="","",IFERROR(_xlfn.XLOOKUP("L"&$D74,'1.6 IP Calculations'!$L$26:$L$30,'1.6 IP Calculations'!$N$26:$N$30),"")) -> 0.085643476 | J74: =IF(E74="","",IFERROR(_xlfn.XLOOKUP("L"&E74,'1.6 IP Calculations'!$V$26:$V$30,'1.6 IP Calculations'!$X$26:$X$30),"")) -> 1 | K74: =IF(F74="","",IFERROR(_xlfn.XLOOKUP("L"&F74,'1.6 IP Calculations'!$AG$26:$AG$30,'1.6 IP Calculations'!$AI$26:$AI$30),"")) -> 1 | L74: =IF(G74="","",IFERROR(_xlfn.XLOOKUP("L"&G74,'1.6 IP Calculations'!$AQ$26:$AQ$30,'1.6 IP Calculations'!$AS$26:$AS$30),"")) -> 0.54226592 | M74: =IF(H74="","",H74*$E$60) -> 0.055774173 | N74: =IF(I74="","",I74*$E$61) -> 0.021410869 | O74: =IF(J74="","",J74*$E$62) -> 0.16666667 | P74: =IF(K74="","",K74*$E$63) -> 0.16666667 | Q74: =IF(L74="","",L74*$E$64) -> 0.090377653 | R74: =IF(COUNTIF(C74:G74,">0")=0,"",SUM(M74:Q74)) -> 0.50089603 | S74: =IF(COUNTIF(C74:G74,">0")=0,"",RANK(R74,$R$70:$R$79,0)) -> 1 | T74: =IF(COUNTIF(C74:G74,">0")=0,"",R74/SUM($R$70:$R$79)) -> 0.28007762 | U74: =IF(OR(C74="",H74=""),"",_xlfn.CONCAT(C74," (",TEXT(H74,"0.0000"),")")) -> 4 (0.2231) | V74: =IF(OR(D74="",I74=""),"",_xlfn.CONCAT(D74," (",TEXT(I74,"0.0000"),")")) -> 5 (0.0856) | W74: =IF(OR(E74="",J74=""),"",_xlfn.CONCAT(E74," (",TEXT(J74,"0.0000"),")")) -> 5 (1.0000) | X74: =IF(OR(F74="",K74=""),"",_xlfn.CONCAT(F74," (",TEXT(K74,"0.0000"),")")) -> 5 (1.0000) | Y74: =IF(OR(G74="",L74=""),"",_xlfn.CONCAT(G74," (",TEXT(L74,"0.0000"),")")) -> 4 (0.5423)
A75: 6 | C75: =IFERROR(IF(INDEX('1.4 EA Smell Scoring'!$D$9:$H$18,MATCH($B75,'1.4 EA Smell Scoring'!$C$9:$C$18,0),MATCH(C$69,'1.4 EA Smell Scoring'!$D$8:$H$8,0))=0,"",INDEX('1.4 EA Smell Scoring'!$D$9:$H$18,MATCH($B75,'1.4 EA Smell Scoring'!$C$9:$C$18,0),MATCH(C$69,'1.4 EA Smell Scoring'!$D$8:$H$8,0))),"") | D75: =IFERROR(IF(INDEX('1.4 EA Smell Scoring'!$D$9:$H$18,MATCH($B75,'1.4 EA Smell Scoring'!$C$9:$C$18,0),MATCH(D$69,'1.4 EA Smell Scoring'!$D$8:$H$8,0))=0,"",INDEX('1.4 EA Smell Scoring'!$D$9:$H$18,MATCH($B75,'1.4 EA Smell Scoring'!$C$9:$C$18,0),MATCH(D$69,'1.4 EA Smell Scoring'!$D$8:$H$8,0))),"") | E75: =IFERROR(IF(INDEX('1.4 EA Smell Scoring'!$D$9:$H$18,MATCH($B75,'1.4 EA Smell Scoring'!$C$9:$C$18,0),MATCH(E$69,'1.4 EA Smell Scoring'!$D$8:$H$8,0))=0,"",INDEX('1.4 EA Smell Scoring'!$D$9:$H$18,MATCH($B75,'1.4 EA Smell Scoring'!$C$9:$C$18,0),MATCH(E$69,'1.4 EA Smell Scoring'!$D$8:$H$8,0))),"") | F75: =IFERROR(IF(INDEX('1.4 EA Smell Scoring'!$D$9:$H$18,MATCH($B75,'1.4 EA Smell Scoring'!$C$9:$C$18,0),MATCH(F$69,'1.4 EA Smell Scoring'!$D$8:$H$8,0))=0,"",INDEX('1.4 EA Smell Scoring'!$D$9:$H$18,MATCH($B75,'1.4 EA Smell Scoring'!$C$9:$C$18,0),MATCH(F$69,'1.4 EA Smell Scoring'!$D$8:$H$8,0))),"") | G75: =IFERROR(IF(INDEX('1.4 EA Smell Scoring'!$D$9:$H$18,MATCH($B75,'1.4 EA Smell Scoring'!$C$9:$C$18,0),MATCH(G$69,'1.4 EA Smell Scoring'!$D$8:$H$8,0))=0,"",INDEX('1.4 EA Smell Scoring'!$D$9:$H$18,MATCH($B75,'1.4 EA Smell Scoring'!$C$9:$C$18,0),MATCH(G$69,'1.4 EA Smell Scoring'!$D$8:$H$8,0))),"") | H75: =IF(C75="","",IFERROR(_xlfn.XLOOKUP("L"&C75,'1.6 IP Calculations'!$B$26:$B$30,'1.6 IP Calculations'!$D$26:$D$30),"")) | I75: =IF($D75="","",IFERROR(_xlfn.XLOOKUP("L"&$D75,'1.6 IP Calculations'!$L$26:$L$30,'1.6 IP Calculations'!$N$26:$N$30),"")) | J75: =IF(E75="","",IFERROR(_xlfn.XLOOKUP("L"&E75,'1.6 IP Calculations'!$V$26:$V$30,'1.6 IP Calculations'!$X$26:$X$30),"")) | K75: =IF(F75="","",IFERROR(_xlfn.XLOOKUP("L"&F75,'1.6 IP Calculations'!$AG$26:$AG$30,'1.6 IP Calculations'!$AI$26:$AI$30),"")) | L75: =IF(G75="","",IFERROR(_xlfn.XLOOKUP("L"&G75,'1.6 IP Calculations'!$AQ$26:$AQ$30,'1.6 IP Calculations'!$AS$26:$AS$30),"")) | M75: =IF(H75="","",H75*$E$60) | N75: =IF(I75="","",I75*$E$61) | O75: =IF(J75="","",J75*$E$62) | P75: =IF(K75="","",K75*$E$63) | Q75: =IF(L75="","",L75*$E$64) | R75: =IF(COUNTIF(C75:G75,">0")=0,"",SUM(M75:Q75)) | S75: =IF(COUNTIF(C75:G75,">0")=0,"",RANK(R75,$R$70:$R$79,0)) | T75: =IF(COUNTIF(C75:G75,">0")=0,"",R75/SUM($R$70:$R$79)) | U75: =IF(OR(C75="",H75=""),"",_xlfn.CONCAT(C75," (",TEXT(H75,"0.0000"),")")) | V75: =IF(OR(D75="",I75=""),"",_xlfn.CONCAT(D75," (",TEXT(I75,"0.0000"),")")) | W75: =IF(OR(E75="",J75=""),"",_xlfn.CONCAT(E75," (",TEXT(J75,"0.0000"),")")) | X75: =IF(OR(F75="",K75=""),"",_xlfn.CONCAT(F75," (",TEXT(K75,"0.0000"),")")) | Y75: =IF(OR(G75="",L75=""),"",_xlfn.CONCAT(G75," (",TEXT(L75,"0.0000"),")"))
A76: 7 | C76: =IFERROR(IF(INDEX('1.4 EA Smell Scoring'!$D$9:$H$18,MATCH($B76,'1.4 EA Smell Scoring'!$C$9:$C$18,0),MATCH(C$69,'1.4 EA Smell Scoring'!$D$8:$H$8,0))=0,"",INDEX('1.4 EA Smell Scoring'!$D$9:$H$18,MATCH($B76,'1.4 EA Smell Scoring'!$C$9:$C$18,0),MATCH(C$69,'1.4 EA Smell Scoring'!$D$8:$H$8,0))),"") | D76: =IFERROR(IF(INDEX('1.4 EA Smell Scoring'!$D$9:$H$18,MATCH($B76,'1.4 EA Smell Scoring'!$C$9:$C$18,0),MATCH(D$69,'1.4 EA Smell Scoring'!$D$8:$H$8,0))=0,"",INDEX('1.4 EA Smell Scoring'!$D$9:$H$18,MATCH($B76,'1.4 EA Smell Scoring'!$C$9:$C$18,0),MATCH(D$69,'1.4 EA Smell Scoring'!$D$8:$H$8,0))),"") | E76: =IFERROR(IF(INDEX('1.4 EA Smell Scoring'!$D$9:$H$18,MATCH($B76,'1.4 EA Smell Scoring'!$C$9:$C$18,0),MATCH(E$69,'1.4 EA Smell Scoring'!$D$8:$H$8,0))=0,"",INDEX('1.4 EA Smell Scoring'!$D$9:$H$18,MATCH($B76,'1.4 EA Smell Scoring'!$C$9:$C$18,0),MATCH(E$69,'1.4 EA Smell Scoring'!$D$8:$H$8,0))),"") | F76: =IFERROR(IF(INDEX('1.4 EA Smell Scoring'!$D$9:$H$18,MATCH($B76,'1.4 EA Smell Scoring'!$C$9:$C$18,0),MATCH(F$69,'1.4 EA Smell Scoring'!$D$8:$H$8,0))=0,"",INDEX('1.4 EA Smell Scoring'!$D$9:$H$18,MATCH($B76,'1.4 EA Smell Scoring'!$C$9:$C$18,0),MATCH(F$69,'1.4 EA Smell Scoring'!$D$8:$H$8,0))),"") | G76: =IFERROR(IF(INDEX('1.4 EA Smell Scoring'!$D$9:$H$18,MATCH($B76,'1.4 EA Smell Scoring'!$C$9:$C$18,0),MATCH(G$69,'1.4 EA Smell Scoring'!$D$8:$H$8,0))=0,"",INDEX('1.4 EA Smell Scoring'!$D$9:$H$18,MATCH($B76,'1.4 EA Smell Scoring'!$C$9:$C$18,0),MATCH(G$69,'1.4 EA Smell Scoring'!$D$8:$H$8,0))),"") | H76: =IF(C76="","",IFERROR(_xlfn.XLOOKUP("L"&C76,'1.6 IP Calculations'!$B$26:$B$30,'1.6 IP Calculations'!$D$26:$D$30),"")) | I76: =IF($D76="","",IFERROR(_xlfn.XLOOKUP("L"&$D76,'1.6 IP Calculations'!$L$26:$L$30,'1.6 IP Calculations'!$N$26:$N$30),"")) | J76: =IF(E76="","",IFERROR(_xlfn.XLOOKUP("L"&E76,'1.6 IP Calculations'!$V$26:$V$30,'1.6 IP Calculations'!$X$26:$X$30),"")) | K76: =IF(F76="","",IFERROR(_xlfn.XLOOKUP("L"&F76,'1.6 IP Calculations'!$AG$26:$AG$30,'1.6 IP Calculations'!$AI$26:$AI$30),"")) | L76: =IF(G76="","",IFERROR(_xlfn.XLOOKUP("L"&G76,'1.6 IP Calculations'!$AQ$26:$AQ$30,'1.6 IP Calculations'!$AS$26:$AS$30),"")) | M76: =IF(H76="","",H76*$E$60) | N76: =IF(I76="","",I76*$E$61) | O76: =IF(J76="","",J76*$E$62) | P76: =IF(K76="","",K76*$E$63) | Q76: =IF(L76="","",L76*$E$64) | R76: =IF(COUNTIF(C76:G76,">0")=0,"",SUM(M76:Q76)) | S76: =IF(COUNTIF(C76:G76,">0")=0,"",RANK(R76,$R$70:$R$79,0)) | T76: =IF(COUNTIF(C76:G76,">0")=0,"",R76/SUM($R$70:$R$79)) | U76: =IF(OR(C76="",H76=""),"",_xlfn.CONCAT(C76," (",TEXT(H76,"0.0000"),")")) | V76: =IF(OR(D76="",I76=""),"",_xlfn.CONCAT(D76," (",TEXT(I76,"0.0000"),")")) | W76: =IF(OR(E76="",J76=""),"",_xlfn.CONCAT(E76," (",TEXT(J76,"0.0000"),")")) | X76: =IF(OR(F76="",K76=""),"",_xlfn.CONCAT(F76," (",TEXT(K76,"0.0000"),")")) | Y76: =IF(OR(G76="",L76=""),"",_xlfn.CONCAT(G76," (",TEXT(L76,"0.0000"),")"))
A77: 8 | C77: =IFERROR(IF(INDEX('1.4 EA Smell Scoring'!$D$9:$H$18,MATCH($B77,'1.4 EA Smell Scoring'!$C$9:$C$18,0),MATCH(C$69,'1.4 EA Smell Scoring'!$D$8:$H$8,0))=0,"",INDEX('1.4 EA Smell Scoring'!$D$9:$H$18,MATCH($B77,'1.4 EA Smell Scoring'!$C$9:$C$18,0),MATCH(C$69,'1.4 EA Smell Scoring'!$D$8:$H$8,0))),"") | D77: =IFERROR(IF(INDEX('1.4 EA Smell Scoring'!$D$9:$H$18,MATCH($B77,'1.4 EA Smell Scoring'!$C$9:$C$18,0),MATCH(D$69,'1.4 EA Smell Scoring'!$D$8:$H$8,0))=0,"",INDEX('1.4 EA Smell Scoring'!$D$9:$H$18,MATCH($B77,'1.4 EA Smell Scoring'!$C$9:$C$18,0),MATCH(D$69,'1.4 EA Smell Scoring'!$D$8:$H$8,0))),"") | E77: =IFERROR(IF(INDEX('1.4 EA Smell Scoring'!$D$9:$H$18,MATCH($B77,'1.4 EA Smell Scoring'!$C$9:$C$18,0),MATCH(E$69,'1.4 EA Smell Scoring'!$D$8:$H$8,0))=0,"",INDEX('1.4 EA Smell Scoring'!$D$9:$H$18,MATCH($B77,'1.4 EA Smell Scoring'!$C$9:$C$18,0),MATCH(E$69,'1.4 EA Smell Scoring'!$D$8:$H$8,0))),"") | F77: =IFERROR(IF(INDEX('1.4 EA Smell Scoring'!$D$9:$H$18,MATCH($B77,'1.4 EA Smell Scoring'!$C$9:$C$18,0),MATCH(F$69,'1.4 EA Smell Scoring'!$D$8:$H$8,0))=0,"",INDEX('1.4 EA Smell Scoring'!$D$9:$H$18,MATCH($B77,'1.4 EA Smell Scoring'!$C$9:$C$18,0),MATCH(F$69,'1.4 EA Smell Scoring'!$D$8:$H$8,0))),"") | G77: =IFERROR(IF(INDEX('1.4 EA Smell Scoring'!$D$9:$H$18,MATCH($B77,'1.4 EA Smell Scoring'!$C$9:$C$18,0),MATCH(G$69,'1.4 EA Smell Scoring'!$D$8:$H$8,0))=0,"",INDEX('1.4 EA Smell Scoring'!$D$9:$H$18,MATCH($B77,'1.4 EA Smell Scoring'!$C$9:$C$18,0),MATCH(G$69,'1.4 EA Smell Scoring'!$D$8:$H$8,0))),"") | H77: =IF(C77="","",IFERROR(_xlfn.XLOOKUP("L"&C77,'1.6 IP Calculations'!$B$26:$B$30,'1.6 IP Calculations'!$D$26:$D$30),"")) | I77: =IF($D77="","",IFERROR(_xlfn.XLOOKUP("L"&$D77,'1.6 IP Calculations'!$L$26:$L$30,'1.6 IP Calculations'!$N$26:$N$30),"")) | J77: =IF(E77="","",IFERROR(_xlfn.XLOOKUP("L"&E77,'1.6 IP Calculations'!$V$26:$V$30,'1.6 IP Calculations'!$X$26:$X$30),"")) | K77: =IF(F77="","",IFERROR(_xlfn.XLOOKUP("L"&F77,'1.6 IP Calculations'!$AG$26:$AG$30,'1.6 IP Calculations'!$AI$26:$AI$30),"")) | L77: =IF(G77="","",IFERROR(_xlfn.XLOOKUP("L"&G77,'1.6 IP Calculations'!$AQ$26:$AQ$30,'1.6 IP Calculations'!$AS$26:$AS$30),"")) | M77: =IF(H77="","",H77*$E$60) | N77: =IF(I77="","",I77*$E$61) | O77: =IF(J77="","",J77*$E$62) | P77: =IF(K77="","",K77*$E$63) | Q77: =IF(L77="","",L77*$E$64) | R77: =IF(COUNTIF(C77:G77,">0")=0,"",SUM(M77:Q77)) | S77: =IF(COUNTIF(C77:G77,">0")=0,"",RANK(R77,$R$70:$R$79,0)) | T77: =IF(COUNTIF(C77:G77,">0")=0,"",R77/SUM($R$70:$R$79)) | U77: =IF(OR(C77="",H77=""),"",_xlfn.CONCAT(C77," (",TEXT(H77,"0.0000"),")")) | V77: =IF(OR(D77="",I77=""),"",_xlfn.CONCAT(D77," (",TEXT(I77,"0.0000"),")")) | W77: =IF(OR(E77="",J77=""),"",_xlfn.CONCAT(E77," (",TEXT(J77,"0.0000"),")")) | X77: =IF(OR(F77="",K77=""),"",_xlfn.CONCAT(F77," (",TEXT(K77,"0.0000"),")")) | Y77: =IF(OR(G77="",L77=""),"",_xlfn.CONCAT(G77," (",TEXT(L77,"0.0000"),")"))
A78: 9 | C78: =IFERROR(IF(INDEX('1.4 EA Smell Scoring'!$D$9:$H$18,MATCH($B78,'1.4 EA Smell Scoring'!$C$9:$C$18,0),MATCH(C$69,'1.4 EA Smell Scoring'!$D$8:$H$8,0))=0,"",INDEX('1.4 EA Smell Scoring'!$D$9:$H$18,MATCH($B78,'1.4 EA Smell Scoring'!$C$9:$C$18,0),MATCH(C$69,'1.4 EA Smell Scoring'!$D$8:$H$8,0))),"") | D78: =IFERROR(IF(INDEX('1.4 EA Smell Scoring'!$D$9:$H$18,MATCH($B78,'1.4 EA Smell Scoring'!$C$9:$C$18,0),MATCH(D$69,'1.4 EA Smell Scoring'!$D$8:$H$8,0))=0,"",INDEX('1.4 EA Smell Scoring'!$D$9:$H$18,MATCH($B78,'1.4 EA Smell Scoring'!$C$9:$C$18,0),MATCH(D$69,'1.4 EA Smell Scoring'!$D$8:$H$8,0))),"") | E78: =IFERROR(IF(INDEX('1.4 EA Smell Scoring'!$D$9:$H$18,MATCH($B78,'1.4 EA Smell Scoring'!$C$9:$C$18,0),MATCH(E$69,'1.4 EA Smell Scoring'!$D$8:$H$8,0))=0,"",INDEX('1.4 EA Smell Scoring'!$D$9:$H$18,MATCH($B78,'1.4 EA Smell Scoring'!$C$9:$C$18,0),MATCH(E$69,'1.4 EA Smell Scoring'!$D$8:$H$8,0))),"") | F78: =IFERROR(IF(INDEX('1.4 EA Smell Scoring'!$D$9:$H$18,MATCH($B78,'1.4 EA Smell Scoring'!$C$9:$C$18,0),MATCH(F$69,'1.4 EA Smell Scoring'!$D$8:$H$8,0))=0,"",INDEX('1.4 EA Smell Scoring'!$D$9:$H$18,MATCH($B78,'1.4 EA Smell Scoring'!$C$9:$C$18,0),MATCH(F$69,'1.4 EA Smell Scoring'!$D$8:$H$8,0))),"") | G78: =IFERROR(IF(INDEX('1.4 EA Smell Scoring'!$D$9:$H$18,MATCH($B78,'1.4 EA Smell Scoring'!$C$9:$C$18,0),MATCH(G$69,'1.4 EA Smell Scoring'!$D$8:$H$8,0))=0,"",INDEX('1.4 EA Smell Scoring'!$D$9:$H$18,MATCH($B78,'1.4 EA Smell Scoring'!$C$9:$C$18,0),MATCH(G$69,'1.4 EA Smell Scoring'!$D$8:$H$8,0))),"") | H78: =IF(C78="","",IFERROR(_xlfn.XLOOKUP("L"&C78,'1.6 IP Calculations'!$B$26:$B$30,'1.6 IP Calculations'!$D$26:$D$30),"")) | I78: =IF($D78="","",IFERROR(_xlfn.XLOOKUP("L"&$D78,'1.6 IP Calculations'!$L$26:$L$30,'1.6 IP Calculations'!$N$26:$N$30),"")) | J78: =IF(E78="","",IFERROR(_xlfn.XLOOKUP("L"&E78,'1.6 IP Calculations'!$V$26:$V$30,'1.6 IP Calculations'!$X$26:$X$30),"")) | K78: =IF(F78="","",IFERROR(_xlfn.XLOOKUP("L"&F78,'1.6 IP Calculations'!$AG$26:$AG$30,'1.6 IP Calculations'!$AI$26:$AI$30),"")) | L78: =IF(G78="","",IFERROR(_xlfn.XLOOKUP("L"&G78,'1.6 IP Calculations'!$AQ$26:$AQ$30,'1.6 IP Calculations'!$AS$26:$AS$30),"")) | M78: =IF(H78="","",H78*$E$60) | N78: =IF(I78="","",I78*$E$61) | O78: =IF(J78="","",J78*$E$62) | P78: =IF(K78="","",K78*$E$63) | Q78: =IF(L78="","",L78*$E$64) | R78: =IF(COUNTIF(C78:G78,">0")=0,"",SUM(M78:Q78)) | S78: =IF(COUNTIF(C78:G78,">0")=0,"",RANK(R78,$R$70:$R$79,0)) | T78: =IF(COUNTIF(C78:G78,">0")=0,"",R78/SUM($R$70:$R$79)) | U78: =IF(OR(C78="",H78=""),"",_xlfn.CONCAT(C78," (",TEXT(H78,"0.0000"),")")) | V78: =IF(OR(D78="",I78=""),"",_xlfn.CONCAT(D78," (",TEXT(I78,"0.0000"),")")) | W78: =IF(OR(E78="",J78=""),"",_xlfn.CONCAT(E78," (",TEXT(J78,"0.0000"),")")) | X78: =IF(OR(F78="",K78=""),"",_xlfn.CONCAT(F78," (",TEXT(K78,"0.0000"),")")) | Y78: =IF(OR(G78="",L78=""),"",_xlfn.CONCAT(G78," (",TEXT(L78,"0.0000"),")"))
A79: 10 | C79: =IFERROR(IF(INDEX('1.4 EA Smell Scoring'!$D$9:$H$18,MATCH($B79,'1.4 EA Smell Scoring'!$C$9:$C$18,0),MATCH(C$69,'1.4 EA Smell Scoring'!$D$8:$H$8,0))=0,"",INDEX('1.4 EA Smell Scoring'!$D$9:$H$18,MATCH($B79,'1.4 EA Smell Scoring'!$C$9:$C$18,0),MATCH(C$69,'1.4 EA Smell Scoring'!$D$8:$H$8,0))),"") | D79: =IFERROR(IF(INDEX('1.4 EA Smell Scoring'!$D$9:$H$18,MATCH($B79,'1.4 EA Smell Scoring'!$C$9:$C$18,0),MATCH(D$69,'1.4 EA Smell Scoring'!$D$8:$H$8,0))=0,"",INDEX('1.4 EA Smell Scoring'!$D$9:$H$18,MATCH($B79,'1.4 EA Smell Scoring'!$C$9:$C$18,0),MATCH(D$69,'1.4 EA Smell Scoring'!$D$8:$H$8,0))),"") | E79: =IFERROR(IF(INDEX('1.4 EA Smell Scoring'!$D$9:$H$18,MATCH($B79,'1.4 EA Smell Scoring'!$C$9:$C$18,0),MATCH(E$69,'1.4 EA Smell Scoring'!$D$8:$H$8,0))=0,"",INDEX('1.4 EA Smell Scoring'!$D$9:$H$18,MATCH($B79,'1.4 EA Smell Scoring'!$C$9:$C$18,0),MATCH(E$69,'1.4 EA Smell Scoring'!$D$8:$H$8,0))),"") | F79: =IFERROR(IF(INDEX('1.4 EA Smell Scoring'!$D$9:$H$18,MATCH($B79,'1.4 EA Smell Scoring'!$C$9:$C$18,0),MATCH(F$69,'1.4 EA Smell Scoring'!$D$8:$H$8,0))=0,"",INDEX('1.4 EA Smell Scoring'!$D$9:$H$18,MATCH($B79,'1.4 EA Smell Scoring'!$C$9:$C$18,0),MATCH(F$69,'1.4 EA Smell Scoring'!$D$8:$H$8,0))),"") | G79: =IFERROR(IF(INDEX('1.4 EA Smell Scoring'!$D$9:$H$18,MATCH($B79,'1.4 EA Smell Scoring'!$C$9:$C$18,0),MATCH(G$69,'1.4 EA Smell Scoring'!$D$8:$H$8,0))=0,"",INDEX('1.4 EA Smell Scoring'!$D$9:$H$18,MATCH($B79,'1.4 EA Smell Scoring'!$C$9:$C$18,0),MATCH(G$69,'1.4 EA Smell Scoring'!$D$8:$H$8,0))),"") | H79: =IF(C79="","",IFERROR(_xlfn.XLOOKUP("L"&C79,'1.6 IP Calculations'!$B$26:$B$30,'1.6 IP Calculations'!$D$26:$D$30),"")) | I79: =IF($D79="","",IFERROR(_xlfn.XLOOKUP("L"&$D79,'1.6 IP Calculations'!$L$26:$L$30,'1.6 IP Calculations'!$N$26:$N$30),"")) | J79: =IF(E79="","",IFERROR(_xlfn.XLOOKUP("L"&E79,'1.6 IP Calculations'!$V$26:$V$30,'1.6 IP Calculations'!$X$26:$X$30),"")) | K79: =IF(F79="","",IFERROR(_xlfn.XLOOKUP("L"&F79,'1.6 IP Calculations'!$AG$26:$AG$30,'1.6 IP Calculations'!$AI$26:$AI$30),"")) | L79: =IF(G79="","",IFERROR(_xlfn.XLOOKUP("L"&G79,'1.6 IP Calculations'!$AQ$26:$AQ$30,'1.6 IP Calculations'!$AS$26:$AS$30),"")) | M79: =IF(H79="","",H79*$E$60) | N79: =IF(I79="","",I79*$E$61) | O79: =IF(J79="","",J79*$E$62) | P79: =IF(K79="","",K79*$E$63) | Q79: =IF(L79="","",L79*$E$64) | R79: =IF(COUNTIF(C79:G79,">0")=0,"",SUM(M79:Q79)) | S79: =IF(COUNTIF(C79:G79,">0")=0,"",RANK(R79,$R$70:$R$79,0)) | T79: =IF(COUNTIF(C79:G79,">0")=0,"",R79/SUM($R$70:$R$79)) | U79: =IF(OR(C79="",H79=""),"",_xlfn.CONCAT(C79," (",TEXT(H79,"0.0000"),")")) | V79: =IF(OR(D79="",I79=""),"",_xlfn.CONCAT(D79," (",TEXT(I79,"0.0000"),")")) | W79: =IF(OR(E79="",J79=""),"",_xlfn.CONCAT(E79," (",TEXT(J79,"0.0000"),")")) | X79: =IF(OR(F79="",K79=""),"",_xlfn.CONCAT(F79," (",TEXT(K79,"0.0000"),")")) | Y79: =IF(OR(G79="",L79=""),"",_xlfn.CONCAT(G79," (",TEXT(L79,"0.0000"),")"))

Sheet AHP Saaty Reference
B2: AHP Reference Tables (Saaty Scale and Consistency Guidelines)
B4: Saaty, T. L. (1980). *The Analytic Hierarchy Process: Planning, Priority Setting, Resource Allocation*. New York: McGraw-Hill. | G4: ► Column Helper (click +)
B7: AHP SCALE REFERENCE (Saaty 1–9) | H7: Display Text | I7: Value
B8: Score | C8: Meaning | D8: Reciprocal | H8: ▼ Select a judgment…
B9: 1 | C9: Equal importance | D9: Two elements contribute equally to the objective | H9: Criterion A – Extreme importance (9) | I9: 9
B10: 3 | C10: Moderate importance | D10: Judgment slightly favors one element over another | H10: Criterion A – Intermediate value between Very strong and Extreme importance (8) | I10: 8
B11: 5 | C11: Strong importance | D11: Judgment strongly favors one element over another | H11: Criterion A – Very strong importance (7) | I11: 7
B12: 7 | C12: Very strong importance | D12: Judgment strongly favors one element over another, its dominance is demonstrated by experience | H12: Criterion A – Intermediate value between Strong and Very strong importance (6) | I12: 6
B13: 9 | C13: Extreme importance | D13: The dominance of one element over another is demonstrated and absolute | H13: Criterion A – Strong importance (5) | I13: 5
B14: 2, 4, 6, 8 | C14: can be used to express intermediate values | H14: Criterion A – Intermediate value between Moderate and Strong importance (4) | I14: 4
B15: Reciprocity | C15: If the element i has one of the above non-zero numbers assigned to it when compared with element j, then j has the reciprocal value when compared with i. | H15: Criterion A – Moderate importance (3) | I15: 3
H16: Criterion A – Intermediate value between Equal and Moderate importance (2) | I16: 2
B17: CONSISTENCY RATIO (CR) GUIDE | H17: Equal importance (1) | I17: 1
B18: CR < 0.10 | C18: ACCEPTABLE — judgments are sufficiently consistent | H18: Criterion B – Intermediate value between Equal and Moderate importance (2) | I18: =1/2 -> 0.5
B19: CR > 0.10 | C19: NOT ACCEPTABLE - revise the pairwise judgments | H19: Criterion B – Moderate importance (3) | I19: =1/3 -> 0.33333333
B20: Saaty’s CIr values for matrices are given by the following table | H20: Criterion B – Strong importance (5) | I20: =1/5 -> 0.2
B21: Size of Matrix | C21: Random Consistency (CIr) | H21: Criterion B – Intermediate value between Strong and Very strong importance (6) | I21: =1/6 -> 0.16666667
B22: 1 | C22: 0 | D22: 1 | H22: Criterion B – Very strong importance (7) | I22: =1/7 -> 0.14285714
B23: 2 | C23: 0 | D23: 2 | H23: Criterion B – Intermediate value between Very strong and Extreme importance (8) | I23: =1/8 -> 0.125
B24: 3 | C24: 0.525 | D24: 3 | H24: Criterion B – Extreme importance (9) | I24: =1/9 -> 0.11111111
B25: 4 | C25: 0.882 | D25: 4
B26: 5 | C26: 1.11 | D26: 5
B27: 6 | C27: 1.125 | D27: 6
B28: 7 | C28: 1.341 | D28: 7
B29: 8 | C29: 1.404 | D29: 8
B30: 9 | C30: 1.451 | D30: 9
B31: 10 | C31: 1.486 | D31: 10
B32: 11 | C32: 1.514 | D32: 11
B33: 12 | C33: 1.536 | D33: 12
B34: 13 | C34: 1.555 | D34: 13
B35: 14 | C35: 1.57 | D35: 14
B36: 15 | C36: 1.584 | D36: 15
B37: 16 | C37: =C36 -> 1.584 | D37: 16

Sheet EA Smell Catalogue
B1: EA Smell Catalogue
B3: Count | C3: Analytical Grouping | D3: Theoretical basis in Lankhorst et al. | F3: Operationalization in this study | G3: SOURCES: Lankhorst, M. (2017). Enterprise Architecture at Work: Modelling, Communication and Analysis (4th ed.). Springer. RWTH Aachen University. EA Smell Catalogue. EA Smell Catalogue
B4: =COUNTIFS($D:$D,"Modifiability",$E:$E,"Structure") -> 22 | C4: Modifiability — Structure | D4: Architectural structuring decisions affect quality attributes such as modifiability. | F4: Primary architectural effect is increased difficulty changing, maintaining, or evolving the architecture due to structural characteristics such as coupling, cohesion, component organization, or dependencies.
B5: =COUNTIFS($D:$D,"Modifiability",$E:$E,"Behavior") -> 3 | C5: Modifiability — Behavior | F5: Primary architectural effect is increased difficulty changing, maintaining, or evolving the architecture due to interactions or behavioral dependencies between architectural elements, such as service calls or chains.
B6: =COUNTIFS($D:$D,"Interoperability") -> 3 | C6: Interoperability | D6: Service orientation promotes interoperability at the information technology and higher semantic levels. | F6: Primary architectural effect is impaired interaction, integration, or information exchange between architectural elements, including problems arising from incompatible interfaces or inappropriate separation of interacting concerns.
B7: =COUNTIFS($D:$D,"Comprehensibility") -> 7 | C7: Comprehensibility | D7: The comprehensibility of a representation for its intended audience is crucial for effective communication. | F7: Primary architectural effect is reduced clarity, interpretability, or understandability of the architecture, its elements, relationships, responsibilities, or representation.
B8: =COUNTIFS($D:$D,"Strategic Alignment") -> 9 | C8: Strategic Alignment | D8: Architecture alignment concerns aligning IT architecture with business architecture and acts as a regulating idea that directs architectural decisions. | F8: Primary architectural effect is a constraint on the architecture's ability to support business needs, architectural direction, or longer-term organizational objectives.
B10: Selection: Choose Yes to include an EA smell in the assessment (maximum 10). | E10: =IF(COUNTIF(tblEASmellCatalogue[Include],"Yes")>10, "⚠ Too many selected: "&COUNTIF(tblEASmellCatalogue[Include],"Yes")&" / 10", COUNTIF(tblEASmellCatalogue[Include],"Yes")&" / 10 selected") -> 5 / 10 selected
B11: Include | C11: Smell Name | D11: EA Concen | E11: Architectural Scope | F11: Description | G11: Context | H11: Consequences` | I11: Cause
B12: No | C12: Bloated Service | D12: Modifiability | E12: Structure | F12: A service that has one large interface with many parameters or requires much data and performs mostly heterogeneous operations with low cohesion. | G12: Derived from: "Long Parameter List"<br /> Don't get rid of options if doing so would cause unwanted dependency between components. | H12: Bad understandability. Refactoring may reveal previously unnoticed Duplication of functionality. | I12: A long list of required inputs might happen after several types of operations are merged in a single element. A long list may have been created to control which functionality will be run and how. It's hard to understand such lists, which become contradictory and hard to use as they grow longer.
B13: No | C13: Combinatorial Explosion | D13: Modifiability | E13: Structure | F13: A subtle form of Duplication, this smell exists when numerous elements do the same thing using different combinations of data or behavior. | G13: Derived from: "Combinatorial Explosion" | I13: Lack of refactoring and awareness of changing concerns, making naive design decisions.
B14: Yes | C14: Cyclic Dependency | D14: Modifiability | E14: Structure | F14: This smell arises when two or more abstractions depend on each other directly or indirectly (creating a tight coupling between the abstractions). A cyclic chain of calls between abstractions exists. | G14: Derived from: "Cyclic Dependency" or "Circular Dependency" <br /> A special form of Cyclic Dependency is sometimes exhibited with specializations. A subtype has an obvious dependency on its supertype. However, when the supertype also depends on the subtype (for instance, by having an explicit reference to the subtype), it results in a cyclic dependency. | H14: Abstractions involved in a cyclic dependency can be harder to maintain or reuse, as they are more strongly coupled. | I14: Hard to visualize indirect dependencies.
B15: No | C15: Data Service | D15: Modifiability | E15: Structure | F15: A service that exclusively performs information retrieval and typically provides only simple read operations. Often goes hand in hand with Feature Envy, because relevant functionality is not provided. | G15: Derived from: "Data Class"<br /> This smell can, but does not have to, be applied to the provided model, depending on the used architectural style | H15: A data service may have a large number of operations with low cohesion, which can have a negative influence on maintainability. | I15: Data and behavior should be tightly coupled in the same abstraction. If they spread across different components, then it is likely that an abstraction contains only data, whereas the behavior that requires that data lies in another abstraction.
B16: No | C16: Dead Component | D16: Modifiability | E16: Structure | F16: A component is no longer used (usually because it is now obsolete). Or you have generic or abstract elements that are not actually needed today. Such components often exists to support future behavior, which may or may not be necessary in the future. | G16: Derived from: "Dead Code"<br /> Dead Code is software or lines of code that are no longer used or have become redundant but, for safety’s sake, remain in the code base. | H16: Unused elements increase the complexity which harms the readability and maintainability. | I16: When requirements have changed or corrections have been made, nobody had time to clean up the old structure. Sometimes components are created "just in case" to support anticipated future features that never get implemented.
B17: No | C17: Dense Structure | D17: Modifiability | E17: Structure | F17: This smell arises when an EA repository has excessive and dense dependencies without any particular structure. | G17: Derived from: "Dense Structure" | H17: Modifications to the system may be cumbersome and many dependencies have to be added, due to the high coupling. | I17: Inefficient abstraction that needs high coupling of components to work.
B18: No | C18: Duplication | D18: Modifiability | E18: Structure | F18: Two or more abstractions with highly similar functionality exist. | G18: Derived from: "Duplicated Code"<br /> Don't Repeat Yourself! While Microservices usually follow a "share nothing" philosophy, reuse is a common theme in SOA. Service normalization and consolidation are therefore frequent activities in an SOA to reduce the level of duplication. In Microservices on the other, you consciously allow duplication to exist up to a certain degree, because it reduces coupling and dependencies in your system. | H18: Duplicated functionality reduces the level of reuse and may confuse service consumers that cannot identify the service or operation they need. Moreover, if this common functionality changes, it needs to change in all duplicated locations, therefore causing higher maintenance efforts. A culture of "build and expose" may form where the enterprise becomes a mess of services all attempting to do the same thing. | I18: Duplication usually occurs when multiple architects are working on different parts of the same architecture at the same time. Since they're working on different tasks, they may be unaware their colleague has already defined similar components that could be repurposed for their own needs. There's also more subtle duplication, when specific parts look different but actually perform the same job. This kind of duplication can be hard to find and fix. Sometimes duplication is purposeful. When rushing to meet deadlines and the existing architecture is "almost right" for the job, novice architects may not be able to resist the temptation of copying and pasting the relevant elements. And in some cases, the developer is simply too lazy to de-clutter.
B19: No | C19: Hub-like Modularization | D19: Modifiability | E19: Structure | F19: This smell arises when an abstraction has dependencies (both incoming and outgoing) with a large number of other abstractions, being a single point of failure. | G19: Derived from: "Hub-like Modularization" | H19: The service may have increased response times and low availability. It also becomes a single point of failure in the architecture. | I19: Functionality may gradually become more and more important and is therefore used by more and more consumers, maybe even external ones via a public service interface. To maximize reuse, service interfaces are sometimes also generalized which leads to more service consumers as well.
B20: No | C20: Lazy Component | D20: Modifiability | E20: Structure | F20: A component that is not doing enough to pay for itself should be eliminated. Those components have limited responsibilities. That way, they clutter design, creating unnecessary abstractions. Although delegation is good, and one of the key fundamental features of abstractions, too much of a good thing can lead to objects that add no value, simply passing messages on to another component. | G20: Derived from: "Lazy Class" and "Middle Man"<br /> This smell can be the result of overzealous elimination of Message Chains. Sometimes a Lazy Component is created in order to delineate intentions for future development or to avoid dependencies between elements (e.g. Decorator Pattern). In this case, try to maintain a balance between clarity and simplicity in your architecture. | I20: This smell can be the result of overzealous elimination of Message Chains. In other cases, it can be the result of the useful work of a functional component being gradually moved to other components during refactoring, for example. The original component remains as an empty shell that has become ridiculously small and doesn't do anything other than delegate.
B21: No | C21: Multifaceted Abstraction | D21: Modifiability | E21: Structure | F21: A good abstraction should only be responsible for one specific functionality, and when it encapsulates more than one responsibility, it signifies the the Multifaceted Abstraction Smell. The Multifaceted Abstraction Smell violates the single responsibility principle and has a low cohesion, which also violates the principle of modularization. | G21: Derived from: "Multifaceted Abstraction"<br /> High cohesion is one of the most important design principles. Services should provide operations that are closely related to each other. Functionality that is likely to change together should be in the same service. | H21: The Multifaceted Abstraction Smell violates the single responsibility principle, which also violates the principle of modularization. The maintainability of such a service may be reduced. It may be more difficult to analyze and grasp all provided service functionality. The business logic is not reusable, because it contains service-specific implementation. Low cohesion and possibly low availability with high response times. | I21: Often these divergent modifications are due to poor architectural structure or "cloning".
B22: No | C22: Scattered Parasitic Functionality | D22: Modifiability | E22: Structure | F22: Multiple services are responsible for the same concern and some of these services are also responsible for orthogonal concerns. | G22: Derived from: "Scattered Parasitic Functionality"<br /> That a single concern is split among multiple services and that at least one service handles multiple orthogonal concerns violates important service-oriented principles. This means that these concerns infect services with another orthogonal concern, like a parasite. | H22: Modifiability, reusability, and testability may be reduced. Changing a scattered shared concern requires the changing and testing of several services. The shared concern also cannot be efficiently reused. | I22: It may be a tempting shortcut to distribute a concern over several existing services.
B23: Yes | C23: Shared Persistency | D23: Modifiability | E23: Structure | F23: Different services access the same database. In the worst case, different services access the same entities of the same schema. | G23: Derived from: "Shared Persistency"<br /> The implementation of services usually follows a "share nothing" philosophy. This is especially relevant for clear data ownership. Each data collection or schema usually belongs to exactly one service. The only allowed access to this data is via this service. | H23: This smell highly couples the services connected to the same data, reducing team and service independence.
B24: No | C24: Shotgun Surgery | D24: Modifiability | E24: Structure | F24: Generally, when many abstractions are dependent to a single abstraction, any changes in the single abstraction may force some modifications in the dependent abstractions. This smell is evident when you must change lots of pieces in different places of the system simply to add a new or extended piece of behavior. | G24: Derived from: "Shotgun Surgery" | I24: A single responsibility has been split up among a large number of classes. This can happen after overzealous reduction of Multifaceted Abstraction. All was well as long as the structure stayed small. But with new components being added, making changes has become harder and harder.
B25: No | C25: The God Object | D25: Modifiability | E25: Structure | F25: A service that provides a large number of operations for multiple different business and technical abstractions. Often has a bloated interface and implementation. | G25: Derived from: "The God Object" | H25: Having only a few or even a single large service within the system may impact maintainability, performance, and availability. A very large service is harder to analyze and comprehend. Furthermore, multiple developers will concurrently work on the same service, which can cause unnecessary conflicts. Such a service will also have many consumers and therefore increases coupling in the system. Any changes to its interface result in ripples to these consumers. Moreover, testing such a service becomes very time consuming due to the dependencies within the service. The size and complexity of the service can also mean that using the service needs special effort. Lastly, such a service may become a performance bottleneck or a single point of failure. | I25: Hidden or unclear requirements may make it difficult to identify fitting abstractions. Wrongly applied patterns may also lead to a megaservice. The service designer may also be unfamiliar with the principles of high cohesion and low coupling.
B26: No | C26: Weakened Modularity | D26: Modifiability | E26: Structure | F26: Each module must strive for high cohesion and low coupling. This smell arises when a module exhibits high coupling and low cohesion. | G26: Derived from: "Weakened Modularity"<br /> High cohesion is one of the most important design principles. Modules should provide operations that are closely related to each other. Functionality that is likely to change together should be in the same artifact. | H26: The maintainability and possibility for development may be reduced. It may be more difficult to analyze and grasp all provided functionality. | I26: Often these divergent modifications are due to poor program structure.
B27: No | C27: Chatty Service | D27: Modifiability | E27: Behavior | F27: When a service requires multiple interactions with other services to complete a single task, it is considered "chatty" and leads to increased overhead. A high number of operations is required to complete one abstraction. Such operations are typically rather simple tasks that needlessly slow down an entire process. | G27: Derived from: "Chatty Service" | H27: Maintenance becomes harder, like e.g. changing the order of invocations. Many interactions are required, which leads to overall higher time consumption. This can be especially harmful when synchronous tasks are chained together.
B28: Yes | C28: Feature Envy | D28: Modifiability | E28: Behavior | F28: This Smell occurs when an abstraction becomes more focused on the methods and fields of other abstractions rather than its functions and variables. This issue typically arises when data and functionality that should be kept together are separated across multiple components. It is often, but not always, accompanied by another smell, Data Service. | G28: Derived from: "Feature Envy"<br /> Sometimes behavior is purposefully kept separate from the element that holds the data. The usual advantage of this is the ability to dynamically change the behavior. Depending on the architecture, this smell can be applied differently. | I28: This smell may occur after further data is moved to a data component. If this is the case, you may want to move the operations on data to this component as well.
B29: No | C29: Message Chain | D29: Modifiability | E29: Behavior | F29: A chain of service calls and messages fulfills common functionality. | G29: Derived from: "Message Chain"<br /> Multiple services exist that call each other sequentially to fulfill an abstraction or business process. Overly aggressive delegate hiding can cause structures in which it is hard to see where the functionality is actually occurring. | H29: Such a chain may slow down performance and reduces the availability of the chained abstraction. It may also be harder to change the abstraction, especially with respect to the invocation order of services. | I29: The organization may have created a detailed map of processes, which resulted in a series of grand "end to end" process models that are categorized by their large number of steps and a lack of sub-processes. However, no valid business services have been identified and thus the process maps have been created without a proper service structure. This makes identifying valid services a tricky process, especially when looking for cross-functional or horizontal services.
B30: No | C30: Connector Envy | D30: Interoperability | F30: Services implement large amounts of low-level interaction-related functionality, e.g. for communication, coordination, conversation, or facilitation. These functionalities should be implemented by a connector instead. | G30: Derived from: "Connector Envy" | H30: Reusability is reduced, because these low-level details are too specific and not agnostic enough. Understandability is reduced, because different concerns are mixed. Testability is reduced, because the connector and service functionality cannot be tested separately. | I30: Performance may have been preferred over maintainability, since separation of connector and service functionality would create an additional level of indirection.
B31: No | C31: Inconsistent Versioning | D31: Interoperability | F31: A lack of semantically consistent versions of EA models (e.g. v1.1, v1.2, etc.) or poor versioning in general. | G31: Derived from: "API Versioning"<br /> The version is the first hint at different behaviors or changed functionality. | H31: In case of updates to non-semantically versioned models, users may face breaking changes. For example, the structure is changed fundamentally, such that the majority of procedures has to be performed in a new way.
B32: No | C32: Jumble | D32: Comprehensibility | F32: When horizontal and vertical design elements are intermixed, an unstable architecture results. Vertical design elements are dependent upon the individual application and specific implementations. Horizontal design elements are those that are common across applications and specific implementations. | G32: Derived from: "Jumble"<br /> It takes some time to fully understand the meaning and implications of horizontal and vertical design elements. Horizontal rather talks about technical related and vertical talks more about business functionality. In particular, the Horizontal-Vertical-Metadata (HVM) pattern establishes key principles for software architecture design that could be adapted for EA. The Jumble antipattern describes the most common misuse of these principles. | H32: Unstable architecture with unclear possibilities for development.
B33: No | C33: Nanoservices | D33: Modifiability | E33: Structure | F33: A nano service is a fine-grained service with a simple operation that implements only a part of an abstraction and exchanges a large amount of information with a group of services to complete an abstraction task. | G33: Derived from: "Nanoservices"<br /> A SOA is often created by combining several relatively simple services. These services may not have been built with an SOA scenario in mind, but may rely more on simple RPC interaction. This may produce a large number of calls between services. | H33: Bad performance, fragmented logic, and an overhead in maintenance efforts. The functionality of one core abstraction is scattered across multiple services. This means multiple services may have to be changed to address a single feature or concept. Testing such a feature therefore also involves several services. | I33: Hidden or unclear requirements make it very hard to identify fitting abstractions. Sometimes, individual use cases are therefore mapped to separate services. Misunderstanding or wrongly applying patterns may also lead to nanoservices.
B34: No | C34: Sand Pile | D34: Modifiability | E34: Structure | F34: An EA is implemented with one elementary service per component resulting in many small components that are sharing data. | G34: Derived from: "Sand Pile" | H34: The large amount of small components may cause inefficiencies and maintenance problems. | I34: Sand Pile may be caused by a wrong grouping of "atomic" capabilities.
B35: Yes | C35: Stovepipe System | D35: Interoperability | F35: Multiple systems within an EA model are designed independently at every level. It occurs when the interface of two components are different and yet the components themselves are quite similar. Subsystems are integrated in an ad hoc manner using multiple integration strategies and mechanisms. | G35: Derived from: "Stovepipe System"<br /> Stovepipe is a popular term used to describe software systems with ad hoc architectures. It is a metaphor to the exhaust pipes of wood-burning stoves, so-called pot-bellied stoves. Since wood burning produces corrosive substances that erode metal, a stovepipe must be constantly maintained and repaired in order to avoid leakage. Often, the pipes are repaired with any materials at hand, thus wood-burning stovepipes quickly become a hodgepodge of ad hoc repairs - hence, the reference is used to describe the ad hoc structure of many systems. | H35: Technical and utility functions are implemented inconsistently. Development time of stovepipe services is considerably larger. Duplication and different implementations for the same functionality also has a negative impact on maintainability. Lack of commonality inhibits interoperability between systems, prevents reuse, and drives up cost; in addition, reinvented system architecture and services lack quality structure supporting adaptability. | I35: Inexperience in developing multilayer architectures is one reason that can result in stovepipe systems. They can also be caused by insufficient team communication and a lack of design reviews.
B36: No | C36: Strict Layers Violation | D36: Modifiability | E36: Structure | F36: Archimate's specification offers certain relationships between it's core layers. They are realization and serving relationships. Serving is used when an element from upper layer use the services from lower layer and realization is used when a lower level realizes or implements the more abstract concept from the upper layer. The application and technology layers must communicate with the business layer with these two types of relations. Using other relation types is not syntactically restricted, although not suggested. | G36: Derived from: "Strict Layers Violation"<br /> This violation very often occurs in the real world, although the model itself defined the layers and processes precisely. | H36: Alterability is affected. The number of a layer's potential clients will increase, and the dependency between layers will grow. | I36: Layers must be built based on conventions.
B37: No | C37: Wrong Cuts | D37: Modifiability | E37: Structure | F37: Services are split on the basis of technical layers (presentation, business, and data layers) instead of business capabilities. Transactions extend across service boundaries and are not isolated inside services. | G37: Derived from: "Wrong Cuts" | H37: Such a wrong separation of concerns can lead to increased data-splitting complexity. Moreover, this may cause ripple effects on changes and therefore decreases maintainability. Lastly, it may impact performance, if several services are needed to fulfill an abstraction. | I37: Rapidly evolving business processes may result in such transactions. Starting the design of an EA completely upfront without keeping some design decisions open may also lead to this antipattern.
B38: No | C38: Ambiguous Viewpoint | D38: Comprehensibility | F38: Analysis and design models are often presented without clarifying the viewpoint represented by the model. Mixed viewpoints don't allow the fundamental separation of concerns, confusing blueprints of abstractions and implementation details. | G38: Derived from: "Ambiguous Viewpoint"<br /> Models can be less useful if they don't focus on the required perspective(s). A perspective applies filters to the information. It can also be the case that multiple viewpoints are maintained, although no stakeholder is responsible for this unused viewpoint. Then viewpoints are created just for the sake of having viewpoints. | H38: Different viewpoints emphasize different aspects, which can also cause disregard of some crucial factors of other viewpoints. | I38: It is hard to specify every important aspect from all possible viewpoints. Thus, it is important to state the taken viewpoint which should be elaborated extensively.
B39: No | C39: Architecture by Implication | D39: Comprehensibility | F39: This antipattern is characterized by the lack of architecture specifications for a system under development. Usually, the architects responsible for the project have experience with previous system construction, and therefore assume that documentation is unnecessary. | G39: Derived from: "Architecture by Implication"<br /> The antipattern is acceptable for a repeated solution, where there are minor differences to previous ones. The Architecture by Implication antipattern differs from the Stovepipe System antipattern in scope; the latter focuses on deficiencies in architecture. In particular, it identifies how improper abstraction of subcomponents leads to brittle architecture solutions. In contrast, the Architecture by Implication antipattern involves planning gaps constituted of multiple architecture viewpoints. | H39: Lack of architecture planning and specification; insufficient definition of architecture for software, hardware, communications, persistence, security, and systems management. Hidden risks caused by scale, domain knowledge, technology, and complexity, all of which emerge as the project progresses. | I39: No risk management. Overconfidence of managers, architects, and/or developers. Reliance on previous experience, which may differ in critical areas. Implicit and unresolved architecture issues caused by gaps in systems engineering.
B40: No | C40: Deficient Encapsulation | D40: Modifiability | E40: Structure | F40: This Smell occurs when an abstraction makes its members accessible to other abstractions in a more permissive way, which is not necessarily required. In the EA domain, particularly in the ArchiMate modeling language there are no access modifiers. As a result, we need to slightly adjust the definition to apply this concept to ArchiMate. Instead of modifiers, we try to identify sources of information that contain sensitive data while the rules for accessing those data are more lenient than necessary. | G40: Derived from: "Deficient Encapsulation"<br /> Components have too deep insight into unimportant details of other elements, making their work harder. | H40: Not restricted sensitive data can be retrieved and modified by other abstractions unintentionally or imperceptibly. | I40: Keep a close eye on components that spend too much time together. Good elements should know as little about each other as possible. Such elements are easier to maintain and reuse.
B41: No | C41: Deficient Names | D41: Comprehensibility | F41: Pick a set of standard terminology and stick to it throughout your naming. Avoid meaningless names and try to match the responsibility/functionality of an component with an intuitive catchy name. | G41: Derived from: "Deficient Names"<br /> Does the name of the component succinctly describe what that component does? Could you read the element's name to a coworker and have them explain to you what it does? | H41: Unclear behavior of components and inconsistent names. | I41: Can be caused by multiple architects with no common standard of naming.
B42: No | C42: Documentation | D42: Comprehensibility | F42: When you feel like writing a long and complex comment on aspects and the use of one element, try to refactor so that the comment becomes superfluous. Often documentations are even poorly written or completely unnecessary. | G42: Derived from: "Comments"<br /> Explanations can sometimes be useful: When explaining why something is being implemented in a particular way. When explaining complex structures/processes (when all other methods for simplification have been tried and come up short). Note that this smell is called "Documentation" because it is compliant to the ArchiMate-Notation. Maybe it should be renamed in the future with a more accurate name, because it can be confused with a holistic documentation. | I42: Comments are usually created with the best of intentions, when something is not intuitive or obvious. In such cases, explanations are like a deodorant masking the smell of fishy abstractions that could be improved.
B43: No | C43: Incomplete Node or Collaboration | D43: Modifiability | E43: Structure | F43: Occurs when responsibilities emerge in our system that clearly should be moved to a separate group, but we are unable or unwilling to modify the group to accept these new responsibilities | G43: Derived from: "Incomplete Library Class"<br /> Extending a group (node or collaboration) can generate additional work if the changes to the group involve changes in existing components or structure. | I43: The developer of the group hasn't provided the features you need or has refused to implement them.
B44: No | C44: Missing Abstraction | D44: Comprehensibility | F44: Architects tend to make every functionality or data element a separate component, ignoring the benefits of abstractions altogether. In the EA domain, the model should also contain abstract elements to illustrate a more general point of view. The absence of such elements may indicate that the model suffers from Missing Abstraction EA Smell. | G44: Derived from: "Functional Decomposition" and "Primitive Obsession"<br /> The EA model should give a more abstract insight and, thus, provide also more general components. Inside those abstractions further elements can be introduced to enable extensive description of the architecture. | H44: The model is hard to read, complex and very confusing. | I44: Lack of architecture enforcement. Sometimes, those who generate specifications and requirements don't necessarily have real experience with those EA systems. Creating a simple element is so much easier than making a whole new extended component, right?
B45: No | C45: Overgeneralization | D45: Comprehensibility | F45: In order to assure that components provide the greatest extent of reusability, they must be flexibly applicable. This generalization can be overdone though, which will result in overgeneralization. It will become more flexible than it actually needs to be. | G45: Derived from: "Ambiguous Interface"<br /> A service offers a single and very general operation instead of allocating its provided functionality. Sometimes combined with Bloated Service. | H45: Not only does this smell lead to additional development work, it also makes using the components more difficult. Analyzability and understandability are reduced, because a service does not allocate all its provided functionality in a clear manner. Therefore, a user has to analyze this element before using it. | I45: May easily appear in systems, where interactions are not explicitly modeled and multiple services exchange event messages on a regular basis.
B46: No | C46: Big Bang | D46: Strategic Alignment | F46: A strategy often preferred by large vendors where an entire Enterprise Architecture Model is built "at once". | G46: Derived from: "Big Bang"<br /> Even in the design process "divide and conquer is useful". So don't try to design the whole structure at the same time. Take steps to increase the quality of the system and avoid many other smells with a thought out architecture. | H46: Creating a whole Enterprise Architecture Model in a Big Bang may lead to poorly understood requirements and inconsistencies in the architecture. Communication between and integration of services may be inefficient. | I46: Due to fine-grained interfaces, services are not independent enough and an incremental development is not possible.
B47: No | C47: Business Process Forever | D47: Strategic Alignment | F47: Business processes have been strictly defined and are now static and cannot be easily changed. | G47: Derived from: "Business Process Forever"<br /> Especially in small and medium sized businesses, business processes are often not stable. Moreover, not enough data of good quality may be available to allow a solid design. | H47: Business process owners have little to no control over the outcome and quality of their processes, since they cannot change their structure. They are merely observers. | I47: Business processes have been rigorously defined in the past and are now regarded as stable by technical experts. Therefore, business owners may not be able to easily commission for changes.
B48: No | C48: Data-Driven Migration | D48: Modifiability | E48: Structure | F48: You migrate from a monolithic application to a microservices architecture and try to migrate both service functionality and the corresponding data together. | G48: Derived from: "Data-Driven Migration"<br /> Because it is difficult to get the granularity of each service right the first time, you may be frequently merging or splitting your services. Ideally, you want to migrate the data for each service only once, because data migrations are complex and error-prone much more than functionality migrations. | H48: Additional efforts for data migration, because you will need several iterations to get it right. | I48: Trying to split the data for each service right the first time.
B49: No | C49: Golden Hammer | D49: Strategic Alignment | F49: A system implements its functionality as services although there are no objective reasons for and benefits from this. It depicts the overzealous utilization of apparently universal solutions, instead of well suited adaptions of such solutions. | G49: Derived from: "Golden Hammer"<br /> It seems like a Golden Hammer is a tool that is very familiar, simple to apply, and works best on things within striking distance: everyday problems. "I have a hammer and everything else is a nail". A Golden Hammer is something we already have, and it worked great lots of time before, so it will be used for whatever comes next. | H49: Unnecessary distribution can lead to performance issues, because direct communication is more efficient. There are also higher efforts for development, testing, and debugging, because implementing functionality as services is complex. | I49: Services may be chosen because of their promised scalability, modifiability, or interoperability, even though these quality attributes are not really vital for the system at hand. A general reason therefore is a poor understanding of the system's requirements. Lastly, using new and hyped technology or architectural styles is attractive and tempting for a lot of developers and architects.
B50: No | C50: No Legacy | D50: Strategic Alignment | F50: A legacy component is completely rebuilt instead of being (partly) modernized and integrated. Often, this anti-pattern is combined with the "Big Bang" anti-pattern where the entire system is built all at once. | G50: Derived from: "No Legacy"<br /> Management does not want to keep a legacy system of decent quality and therefore wants to rebuild the entire system. The idea is that obsolete parts should be dropped and integration and modernization efforts are perceived to be similar to a complete rewrite. However, since SOA usually enables the efficient integration of applications, a complete rewrite of the legacy system should require much more efforts. | H50: Very high investments and considerable risk are associated with a complete rewrite of large complex systems. | I50: Project management does not understand that integrating legacy systems into a new environment does not necessarily have to be a bad thing.
B51: No | C51: Nothing New | D51: Strategic Alignment | F51: Practices of object-orientation or other non-SOA techniques are used because the principles of service orientation have not been understood. | G51: Derived from: "Nothing New"<br /> In a migration or transition context, there is often a clash between the principles or foundations of paradigms or architectural styles, e.g. object orientation and service orientation. | H51: These practices may lead to poorly usable interfaces and may hinder maintainability. | I51: Experienced object-oriented developers may fail to see new features in service orientation and therefore apply their standard practices in the new style. No trainings are provided to address this and prepare the developers for the new paradigm.
B52: No | C52: Temporary Solution | D52: Strategic Alignment | F52: Some components are introduced, in order to make a relatively fast adaption such that the established environment is working, although this temporary solution does not represent the desired or intended solution. This is the very common view of debt being taken. | G52: Inspired by: "Temporary Field"<br /> Oftentimes, those adaptions are made "on the fly", without a full model being designed. | I52: In order to keep the architecture working, adjustments have to be made shortly. Those adjustments are no optimal solutions resulting in cluttered abstractions and messed up architecture.
B53: No | C53: The Shiny Nickel | D53: Strategic Alignment | F53: The latest technology buzz is incorporated into your system for the sake of telling people about it. | G53: Derived from: "The Shiny Nickel" | H53: Technologies are rarely re-used from one project to the next as IT delivery moves to the next shiny nickel. Each project lays down another technology stratum that increases the cost and complexity of support and creates an integration challenge for future projects. | I53: The Shiny Nickel antipattern is often caused by soft procurement rules and a lack of a common IT strategy and vision. Often, product procurement takes place independently from projects, which leads to technology decisions on projects being driven by a desire to minimize shelfware.
B54: Yes | C54: Vendor Lock-In | D54: Strategic Alignment | F54: The Vendor Lock-In is an anti-pattern when a product becomes strongly dependent on a technology provided by a vendor. | G54: Derived from: "Vendor Lock-In"<br /> Standardization is a useful part of any technical domain, but standards are commonly set by large software vendors and do not focus on compatibility with other standards. | H54: Being overly reliant on a vendor's technology impacts the software quality, and the cost of switching to another technology becomes so high that the software is forced to stick with the current vendor. | I54: The tendency to standardize all technical aspects and dimensions leads to such an overstandardization.
B55: No | C55: Warm Bodies | D55: Strategic Alignment | F55: Project teams that grow beyond five people generally experience escalating difficulties with group coordination. The members have trouble making efficient decisions and maintaining a common vision. Working toward a near-term deadline is essential to encourage the team to focus and begin producing a solution. | G55: Derived from: "Warm Bodies"<br /> Skilled developers are essential to the success of a project. So-called heroic developers are exceptionally productive, but as few as 1 in 20 have this talent. They produce an order of magnitude of more suitable solutions than an average developer. Large-scale projects are prevalent in many industries. These projects employ hundreds of developers to build an enterprise system; a staff of 100 to 400 on a single project is not atypical. Many times this is not modelled, such that the smell must not become evident during design, but only afterwards in practice.
B57: Helper List — Selected EA Smells (do not edit) Automatically generated from EA smells marked “Yes”. Used for scoring-sheet dropdowns.
B58: 1 | C58: {=_xlfn.TAKE(_xlfn._xlws.FILTER(tblEASmellCatalogue[Smell Name],tblEASmellCatalogue[Include]="Yes",""),10)} -> Cyclic Dependency
B59: 2 | C59: Shared Persistency
B60: 3 | C60: Feature Envy
B61: 4 | C61: Stovepipe System
B62: 5 | C62: Vendor Lock-In
B63: 6
B64: 7
B65: 8
B66: 9
B67: 10
